{"chartInfos":{"levelName":"Chroma","bpm":"180","composer":"R_TOP","designer":"粒子","level":"FL","chartID":"10102"},"noteLists":[{"isFakenote":false,"isSkynote":true,"skyjudgeNumber":4,"notetype":3,"startJudgeTime":1.362,"endJudgeTime":0.029,"xOffset":0,"speedGroup":0,"draginfolist":[]},{"isFakenote":false,"isSkynote":true,"skyjudgeNumber":4,"notetype":3,"startJudgeTime":1.696,"endJudgeTime":0.029,"xOffset":0,"speedGroup":0,"draginfolist":[]},{"isFakenote":false,"isSkynote":true,"skyjudgeNumber":4,"notetype":3,"startJudgeTime":2.029,"endJudgeTime":0.029,"xOffset":0,"speedGroup":0,"draginfolist":[]},{"isFakenote":false,"isSkynote":true,"skyjudgeNumber":4,"notetype":3,"startJudgeTime":2.362,"endJudgeTime":0.029,"xOffset":0,"speedGroup":0,"draginfolist":[]},{"isFakenote":false,"isSkynote":true,"skyjudgeNumber":4,"notetype":3,"startJudgeTime":2.696,"endJudgeTime":0.029,"xOffset":0,"speedGroup":0,"draginfolist":[]},{"isFakenote":false,"isSkynote":true,"skyjudgeNumber":4,"notetype":3,"startJudgeTime":3.029,"endJudgeTime":0.029,"xOffset":0,"speedGroup":0,"draginfolist":[]},{"isFakenote":false,"isSkynote":true,"skyjudgeNumber":4,"notetype":3,"startJudgeTime":3.362,"endJudgeTime":0.029,"xOffset":0,"speedGroup":0,"draginfolist":[]},{"isFakenote":false,"isSkynote":true,"skyjudgeNumber":4,"notetype":3,"startJudgeTime":3.696,"endJudgeTime":0.029,"xOffset":0,"speedGroup":0,"draginfolist":[]},{"isFakenote":false,"isSkynote":true,"skyjudgeNumber":3,"notetype":3,"startJudgeTime":4.029,"endJudgeTime":0.029,"xOffset":0,"speedGroup":0,"draginfolist":[]},{"isFakenote":false,"isSkynote":true,"skyjudgeNumber":3,"notetype":3,"startJudgeTime":4.362,"endJudgeTime":0.029,"xOffset":0,"speedGroup":0,"draginfolist":[]},{"isFakenote":false,"isSkynote":true,"skyjudgeNumber":3,"notetype":3,"startJudgeTime":4.696,"endJudgeTime":0.029,"xOffset":0,"speedGroup":0,"draginfolist":[]},{"isFakenote":false,"isSkynote":true,"skyjudgeNumber":3,"notetype":3,"startJudgeTime":5.029,"endJudgeTime":0.029,"xOffset":0,"speedGroup":0,"draginfolist":[]},{"isFakenote":false,"isSkynote":true,"skyjudgeNumber":3,"notetype":3,"startJudgeTime":5.362,"endJudgeTime":0.029,"xOffset":0,"speedGroup":0,"draginfolist":[]},{"isFakenote":false,"isSkynote":true,"skyjudgeNumber":3,"notetype":3,"startJudgeTime":5.696,"endJudgeTime":0.029,"xOffset":0,"speedGroup":0,"draginfolist":[]},{"isFakenote":false,"isSkynote":true,"skyjudgeNumber":3,"notetype":3,"startJudgeTime":6.029,"endJudgeTime":0.029,"xOffset":0,"speedGroup":0,"draginfolist":[]},{"isFakenote":false,"isSkynote":true,"skyjudgeNumber":3,"notetype":3,"startJudgeTime":6.362,"endJudgeTime":0.029,"xOffset":0,"speedGroup":0,"draginfolist":[]},{"isFakenote":false,"isSkynote":true,"skyjudgeNumber":4,"notetype":3,"startJudgeTime":6.696,"endJudgeTime":0.029,"xOffset":0,"speedGroup":0,"draginfolist":[]},{"isFakenote":false,"isSkynote":true,"skyjudgeNumber":4,"notetype":3,"startJudgeTime":7.029,"endJudgeTime":0.029,"xOffset":0,"speedGroup":0,"draginfolist":[]},{"isFakenote":false,"isSkynote":true,"skyjudgeNumber":4,"notetype":3,"startJudgeTime":7.362,"endJudgeTime":0.029,"xOffset":0,"speedGroup":0,"draginfolist":[]},{"isFakenote":false,"isSkynote":true,"skyjudgeNumber":4,"notetype":3,"startJudgeTime":7.696,"endJudgeTime":0.029,"xOffset":0,"speedGroup":0,"draginfolist":[]},{"isFakenote":false,"isSkynote":true,"skyjudgeNumber":3,"notetype":3,"startJudgeTime":8.029,"endJudgeTime":0.029,"xOffset":0,"speedGroup":0,"draginfolist":[]},{"isFakenote":false,"isSkynote":true,"skyjudgeNumber":3,"notetype":3,"startJudgeTime":8.362,"endJudgeTime":0.029,"xOffset":0,"speedGroup":0,"draginfolist":[]},{"isFakenote":false,"isSkynote":true,"skyjudgeNumber":3,"notetype":3,"startJudgeTime":8.696,"endJudgeTime":0.029,"xOffset":0,"speedGroup":0,"draginfolist":[]},{"isFakenote":false,"isSkynote":true,"skyjudgeNumber":3,"notetype":3,"startJudgeTime":9.029,"endJudgeTime":0.029,"xOffset":0,"speedGroup":0,"draginfolist":[]},{"isFakenote":false,"isSkynote":true,"skyjudgeNumber":4,"notetype":3,"startJudgeTime":9.362,"endJudgeTime":0.029,"xOffset":0,"speedGroup":0,"draginfolist":[]},{"isFakenote":false,"isSkynote":true,"skyjudgeNumber":4,"notetype":3,"startJudgeTime":9.696,"endJudgeTime":0.029,"xOffset":0,"speedGroup":0,"draginfolist":[]},{"isFakenote":false,"isSkynote":true,"skyjudgeNumber":3,"notetype":3,"startJudgeTime":10.029,"endJudgeTime":0.029,"xOffset":0,"speedGroup":0,"draginfolist":[]},{"isFakenote":false,"isSkynote":true,"skyjudgeNumber":3,"notetype":3,"startJudgeTime":10.362,"endJudgeTime":0.029,"xOffset":0,"speedGroup":0,"draginfolist":[]},{"isFakenote":false,"isSkynote":true,"skyjudgeNumber":4,"notetype":3,"startJudgeTime":10.696,"endJudgeTime":0.029,"xOffset":0,"speedGroup":0,"draginfolist":[]},{"isFakenote":false,"isSkynote":false,"skyjudgeNumber":0,"notetype":3,"startJudgeTime":11.362,"endJudgeTime":0.029,"xOffset":0.9731534,"speedGroup":0,"draginfolist":[{"isFakenote":false,"isSkynote":true,"skyjudgeNumber":4,"startJudgeTime":11.446,"xOffset":0,"speedGroup":0},{"isFakenote":false,"isSkynote":false,"skyjudgeNumber":0,"startJudgeTime":11.529,"xOffset":0.9731537,"speedGroup":0}]},{"isFakenote":false,"isSkynote":true,"skyjudgeNumber":3,"notetype":3,"startJudgeTime":11.696,"endJudgeTime":0.029,"xOffset":0,"speedGroup":0,"draginfolist":[{"isFakenote":false,"isSkynote":false,"skyjudgeNumber":0,"startJudgeTime":11.862,"xOffset":0.04578054,"speedGroup":0}]},{"isFakenote":false,"isSkynote":true,"skyjudgeNumber":3,"notetype":3,"startJudgeTime":10.862,"endJudgeTime":0.029,"xOffset":0,"speedGroup":0,"draginfolist":[{"isFakenote":false,"isSkynote":false,"skyjudgeNumber":0,"startJudgeTime":10.946,"xOffset":0.06722345,"speedGroup":0},{"isFakenote":false,"isSkynote":false,"skyjudgeNumber":0,"startJudgeTime":11.029,"xOffset":0.06722345,"speedGroup":0}]},{"isFakenote":false,"isSkynote":true,"skyjudgeNumber":4,"notetype":0,"startJudgeTime":12.029,"endJudgeTime":0.029,"xOffset":0,"speedGroup":0,"draginfolist":[]},{"isFakenote":false,"isSkynote":true,"skyjudgeNumber":4,"notetype":0,"startJudgeTime":12.696,"endJudgeTime":0.029,"xOffset":0,"speedGroup":0,"draginfolist":[]},{"isFakenote":false,"isSkynote":true,"skyjudgeNumber":4,"notetype":0,"startJudgeTime":13.362,"endJudgeTime":0.029,"xOffset":0,"speedGroup":0,"draginfolist":[]},{"isFakenote":false,"isSkynote":true,"skyjudgeNumber":4,"notetype":0,"startJudgeTime":14.029,"endJudgeTime":0.029,"xOffset":0,"speedGroup":0,"draginfolist":[]},{"isFakenote":false,"isSkynote":true,"skyjudgeNumber":3,"notetype":0,"startJudgeTime":14.696,"endJudgeTime":0.029,"xOffset":0,"speedGroup":0,"draginfolist":[]},{"isFakenote":false,"isSkynote":true,"skyjudgeNumber":3,"notetype":0,"startJudgeTime":15.362,"endJudgeTime":0.029,"xOffset":0,"speedGroup":0,"draginfolist":[]},{"isFakenote":false,"isSkynote":true,"skyjudgeNumber":3,"notetype":0,"startJudgeTime":16.029,"endJudgeTime":0.029,"xOffset":0,"speedGroup":0,"draginfolist":[]},{"isFakenote":false,"isSkynote":true,"skyjudgeNumber":3,"notetype":0,"startJudgeTime":16.696,"endJudgeTime":0.029,"xOffset":0,"speedGroup":0,"draginfolist":[]},{"isFakenote":false,"isSkynote":true,"skyjudgeNumber":4,"notetype":0,"startJudgeTime":17.362,"endJudgeTime":0.029,"xOffset":0,"speedGroup":0,"draginfolist":[]},{"isFakenote":false,"isSkynote":true,"skyjudgeNumber":4,"notetype":0,"startJudgeTime":18.029,"endJudgeTime":0.029,"xOffset":0,"speedGroup":0,"draginfolist":[]},{"isFakenote":false,"isSkynote":true,"skyjudgeNumber":3,"notetype":0,"startJudgeTime":18.696,"endJudgeTime":0.029,"xOffset":0,"speedGroup":0,"draginfolist":[]},{"isFakenote":false,"isSkynote":true,"skyjudgeNumber":3,"notetype":0,"startJudgeTime":19.362,"endJudgeTime":0.029,"xOffset":0,"speedGroup":0,"draginfolist":[]},{"isFakenote":false,"isSkynote":true,"skyjudgeNumber":4,"notetype":0,"startJudgeTime":20.029,"endJudgeTime":0.029,"xOffset":0,"speedGroup":0,"draginfolist":[]},{"isFakenote":false,"isSkynote":true,"skyjudgeNumber":3,"notetype":0,"startJudgeTime":20.696,"endJudgeTime":0.029,"xOffset":0,"speedGroup":0,"draginfolist":[]},{"isFakenote":false,"isSkynote":true,"skyjudgeNumber":4,"notetype":0,"startJudgeTime":21.362,"endJudgeTime":0.029,"xOffset":0,"speedGroup":0,"draginfolist":[]},{"isFakenote":false,"isSkynote":true,"skyjudgeNumber":3,"notetype":0,"startJudgeTime":21.362,"endJudgeTime":0.029,"xOffset":0,"speedGroup":0,"draginfolist":[]},{"isFakenote":false,"isSkynote":true,"skyjudgeNumber":4,"notetype":3,"startJudgeTime":12.196,"endJudgeTime":0.029,"xOffset":0,"speedGroup":0,"draginfolist":[]},{"isFakenote":false,"isSkynote":true,"skyjudgeNumber":3,"notetype":1,"startJudgeTime":12.362,"endJudgeTime":0.029,"xOffset":0,"speedGroup":0,"draginfolist":[]},{"isFakenote":false,"isSkynote":true,"skyjudgeNumber":1,"notetype":1,"startJudgeTime":13.029,"endJudgeTime":0.029,"xOffset":0,"speedGroup":0,"draginfolist":[]},{"isFakenote":false,"isSkynote":true,"skyjudgeNumber":4,"notetype":3,"startJudgeTime":12.862,"endJudgeTime":0.029,"xOffset":0,"speedGroup":0,"draginfolist":[]},{"isFakenote":false,"isSkynote":true,"skyjudgeNumber":3,"notetype":1,"startJudgeTime":13.696,"endJudgeTime":0.029,"xOffset":0,"speedGroup":0,"draginfolist":[]},{"isFakenote":false,"isSkynote":true,"skyjudgeNumber":4,"notetype":3,"startJudgeTime":13.529,"endJudgeTime":0.029,"xOffset":0,"speedGroup":0,"draginfolist":[]},{"isFakenote":false,"isSkynote":true,"skyjudgeNumber":1,"notetype":1,"startJudgeTime":14.362,"endJudgeTime":0.029,"xOffset":0,"speedGroup":0,"draginfolist":[]},{"isFakenote":false,"isSkynote":true,"skyjudgeNumber":4,"notetype":3,"startJudgeTime":14.196,"endJudgeTime":0.029,"xOffset":0,"speedGroup":0,"draginfolist":[]},{"isFakenote":false,"isSkynote":true,"skyjudgeNumber":4,"notetype":1,"startJudgeTime":15.029,"endJudgeTime":0.029,"xOffset":0,"speedGroup":0,"draginfolist":[]},{"isFakenote":false,"isSkynote":true,"skyjudgeNumber":3,"notetype":3,"startJudgeTime":14.862,"endJudgeTime":0.029,"xOffset":0,"speedGroup":0,"draginfolist":[]},{"isFakenote":false,"isSkynote":true,"skyjudgeNumber":2,"notetype":1,"startJudgeTime":15.696,"endJudgeTime":0.029,"xOffset":0,"speedGroup":0,"draginfolist":[]},{"isFakenote":false,"isSkynote":true,"skyjudgeNumber":3,"notetype":3,"startJudgeTime":15.529,"endJudgeTime":0.029,"xOffset":0,"speedGroup":0,"draginfolist":[]},{"isFakenote":false,"isSkynote":true,"skyjudgeNumber":4,"notetype":1,"startJudgeTime":16.362,"endJudgeTime":0.029,"xOffset":0,"speedGroup":0,"draginfolist":[]},{"isFakenote":false,"isSkynote":true,"skyjudgeNumber":3,"notetype":3,"startJudgeTime":16.196,"endJudgeTime":0.029,"xOffset":0,"speedGroup":0,"draginfolist":[]},{"isFakenote":false,"isSkynote":true,"skyjudgeNumber":2,"notetype":1,"startJudgeTime":17.029,"endJudgeTime":0.029,"xOffset":0,"speedGroup":0,"draginfolist":[]},{"isFakenote":false,"isSkynote":true,"skyjudgeNumber":3,"notetype":3,"startJudgeTime":16.862,"endJudgeTime":0.029,"xOffset":0,"speedGroup":0,"draginfolist":[]},{"isFakenote":false,"isSkynote":true,"skyjudgeNumber":3,"notetype":1,"startJudgeTime":17.696,"endJudgeTime":0.029,"xOffset":0,"speedGroup":0,"draginfolist":[]},{"isFakenote":false,"isSkynote":true,"skyjudgeNumber":4,"notetype":3,"startJudgeTime":17.529,"endJudgeTime":0.029,"xOffset":0,"speedGroup":0,"draginfolist":[]},{"isFakenote":false,"isSkynote":true,"skyjudgeNumber":1,"notetype":1,"startJudgeTime":18.362,"endJudgeTime":0.029,"xOffset":0,"speedGroup":0,"draginfolist":[]},{"isFakenote":false,"isSkynote":true,"skyjudgeNumber":4,"notetype":3,"startJudgeTime":18.196,"endJudgeTime":0.029,"xOffset":0,"speedGroup":0,"draginfolist":[]},{"isFakenote":false,"isSkynote":true,"skyjudgeNumber":4,"notetype":1,"startJudgeTime":19.029,"endJudgeTime":0.029,"xOffset":0,"speedGroup":0,"draginfolist":[]},{"isFakenote":false,"isSkynote":true,"skyjudgeNumber":3,"notetype":3,"startJudgeTime":18.862,"endJudgeTime":0.029,"xOffset":0,"speedGroup":0,"draginfolist":[]},{"isFakenote":false,"isSkynote":true,"skyjudgeNumber":2,"notetype":1,"startJudgeTime":19.696,"endJudgeTime":0.029,"xOffset":0,"speedGroup":0,"draginfolist":[]},{"isFakenote":false,"isSkynote":true,"skyjudgeNumber":3,"notetype":3,"startJudgeTime":19.529,"endJudgeTime":0.029,"xOffset":0,"speedGroup":0,"draginfolist":[]},{"isFakenote":false,"isSkynote":true,"skyjudgeNumber":1,"notetype":1,"startJudgeTime":20.362,"endJudgeTime":0.029,"xOffset":0,"speedGroup":0,"draginfolist":[]},{"isFakenote":false,"isSkynote":true,"skyjudgeNumber":4,"notetype":3,"startJudgeTime":20.196,"endJudgeTime":0.029,"xOffset":0,"speedGroup":0,"draginfolist":[]},{"isFakenote":false,"isSkynote":true,"skyjudgeNumber":2,"notetype":1,"startJudgeTime":21.029,"endJudgeTime":0.029,"xOffset":0,"speedGroup":0,"draginfolist":[]},{"isFakenote":false,"isSkynote":true,"skyjudgeNumber":3,"notetype":3,"startJudgeTime":20.862,"endJudgeTime":0.029,"xOffset":0,"speedGroup":0,"draginfolist":[]},{"isFakenote":false,"isSkynote":true,"skyjudgeNumber":3,"notetype":0,"startJudgeTime":22.696,"endJudgeTime":0.029,"xOffset":0,"speedGroup":0,"draginfolist":[]},{"isFakenote":false,"isSkynote":true,"skyjudgeNumber":4,"notetype":3,"startJudgeTime":22.696,"endJudgeTime":0.029,"xOffset":0,"speedGroup":0,"draginfolist":[{"isFakenote":false,"isSkynote":true,"skyjudgeNumber":2,"startJudgeTime":25.362,"xOffset":0,"speedGroup":0}]},{"isFakenote":false,"isSkynote":true,"skyjudgeNumber":3,"notetype":3,"startJudgeTime":25.362,"endJudgeTime":0.029,"xOffset":0,"speedGroup":0,"draginfolist":[{"isFakenote":false,"isSkynote":false,"skyjudgeNumber":0,"startJudgeTime":28.029,"xOffset":0.090546,"speedGroup":0}]},{"isFakenote":false,"isSkynote":true,"skyjudgeNumber":4,"notetype":3,"startJudgeTime":28.029,"endJudgeTime":0.029,"xOffset":0,"speedGroup":0,"draginfolist":[{"isFakenote":false,"isSkynote":false,"skyjudgeNumber":0,"startJudgeTime":30.696,"xOffset":0.5,"speedGroup":0}]},{"isFakenote":false,"isSkynote":true,"skyjudgeNumber":1,"notetype":3,"startJudgeTime":30.696,"endJudgeTime":0.029,"xOffset":0,"speedGroup":0,"draginfolist":[{"isFakenote":false,"isSkynote":true,"skyjudgeNumber":3,"startJudgeTime":33.362,"xOffset":0,"speedGroup":0}]},{"isFakenote":false,"isSkynote":true,"skyjudgeNumber":4,"notetype":2,"startJudgeTime":43.696,"endJudgeTime":44.029,"xOffset":0,"speedGroup":0,"draginfolist":[]},{"isFakenote":false,"isSkynote":true,"skyjudgeNumber":3,"notetype":2,"startJudgeTime":44.029,"endJudgeTime":45.362,"xOffset":0,"speedGroup":0,"draginfolist":[]},{"isFakenote":false,"isSkynote":true,"skyjudgeNumber":4,"notetype":2,"startJudgeTime":45.362,"endJudgeTime":46.696,"xOffset":0,"speedGroup":0,"draginfolist":[]},{"isFakenote":false,"isSkynote":true,"skyjudgeNumber":1,"notetype":2,"startJudgeTime":46.696,"endJudgeTime":48.029,"xOffset":0,"speedGroup":0,"draginfolist":[]},{"isFakenote":false,"isSkynote":true,"skyjudgeNumber":1,"notetype":2,"startJudgeTime":49.362,"endJudgeTime":50.696,"xOffset":0,"speedGroup":0,"draginfolist":[]},{"isFakenote":false,"isSkynote":true,"skyjudgeNumber":2,"notetype":2,"startJudgeTime":50.696,"endJudgeTime":52.029,"xOffset":0,"speedGroup":0,"draginfolist":[]},{"isFakenote":false,"isSkynote":true,"skyjudgeNumber":3,"notetype":2,"startJudgeTime":52.029,"endJudgeTime":53.362,"xOffset":0,"speedGroup":0,"draginfolist":[]},{"isFakenote":false,"isSkynote":true,"skyjudgeNumber":3,"notetype":2,"startJudgeTime":54.696,"endJudgeTime":56.029,"xOffset":0,"speedGroup":0,"draginfolist":[]},{"isFakenote":false,"isSkynote":true,"skyjudgeNumber":2,"notetype":2,"startJudgeTime":56.029,"endJudgeTime":57.362,"xOffset":0,"speedGroup":0,"draginfolist":[]},{"isFakenote":false,"isSkynote":true,"skyjudgeNumber":1,"notetype":2,"startJudgeTime":57.362,"endJudgeTime":58.696,"xOffset":0,"speedGroup":0,"draginfolist":[]},{"isFakenote":false,"isSkynote":true,"skyjudgeNumber":4,"notetype":2,"startJudgeTime":58.696,"endJudgeTime":60.029,"xOffset":0,"speedGroup":0,"draginfolist":[]},{"isFakenote":false,"isSkynote":true,"skyjudgeNumber":3,"notetype":2,"startJudgeTime":60.029,"endJudgeTime":61.362,"xOffset":0,"speedGroup":0,"draginfolist":[]},{"isFakenote":false,"isSkynote":false,"skyjudgeNumber":0,"notetype":2,"startJudgeTime":61.362,"endJudgeTime":62.696,"xOffset":0.9,"speedGroup":0,"draginfolist":[]},{"isFakenote":false,"isSkynote":false,"skyjudgeNumber":0,"notetype":3,"startJudgeTime":64.029,"endJudgeTime":0.029,"xOffset":0.9,"speedGroup":0,"draginfolist":[{"isFakenote":false,"isSkynote":false,"skyjudgeNumber":0,"startJudgeTime":64.196,"xOffset":0.85,"speedGroup":0},{"isFakenote":false,"isSkynote":false,"skyjudgeNumber":0,"startJudgeTime":64.362,"xOffset":0.8,"speedGroup":0},{"isFakenote":false,"isSkynote":false,"skyjudgeNumber":0,"startJudgeTime":64.529,"xOffset":0.75,"speedGroup":0},{"isFakenote":false,"isSkynote":false,"skyjudgeNumber":0,"startJudgeTime":64.696,"xOffset":0.7,"speedGroup":0},{"isFakenote":false,"isSkynote":false,"skyjudgeNumber":0,"startJudgeTime":64.862,"xOffset":0.65,"speedGroup":0},{"isFakenote":false,"isSkynote":false,"skyjudgeNumber":0,"startJudgeTime":65.029,"xOffset":0.6,"speedGroup":0},{"isFakenote":false,"isSkynote":false,"skyjudgeNumber":0,"startJudgeTime":65.112,"xOffset":1,"speedGroup":0},{"isFakenote":false,"isSkynote":true,"skyjudgeNumber":4,"startJudgeTime":65.196,"xOffset":0,"speedGroup":0}]},{"isFakenote":false,"isSkynote":false,"skyjudgeNumber":0,"notetype":3,"startJudgeTime":75.362,"endJudgeTime":0.029,"xOffset":0.5,"speedGroup":0,"draginfolist":[{"isFakenote":false,"isSkynote":false,"skyjudgeNumber":0,"startJudgeTime":75.446,"xOffset":0.6,"speedGroup":0},{"isFakenote":false,"isSkynote":false,"skyjudgeNumber":0,"startJudgeTime":75.529,"xOffset":0.7,"speedGroup":0},{"isFakenote":false,"isSkynote":false,"skyjudgeNumber":0,"startJudgeTime":75.612,"xOffset":0.8,"speedGroup":0}]},{"isFakenote":false,"isSkynote":false,"skyjudgeNumber":0,"notetype":3,"startJudgeTime":75.696,"endJudgeTime":0.029,"xOffset":0.2,"speedGroup":0,"draginfolist":[{"isFakenote":false,"isSkynote":false,"skyjudgeNumber":0,"startJudgeTime":75.779,"xOffset":0.3,"speedGroup":0},{"isFakenote":false,"isSkynote":false,"skyjudgeNumber":0,"startJudgeTime":75.862,"xOffset":0.4,"speedGroup":0},{"isFakenote":false,"isSkynote":false,"skyjudgeNumber":0,"startJudgeTime":75.946,"xOffset":0.5,"speedGroup":0}]},{"isFakenote":false,"isSkynote":false,"skyjudgeNumber":0,"notetype":3,"startJudgeTime":82.862,"endJudgeTime":0.029,"xOffset":0.9,"speedGroup":0,"draginfolist":[{"isFakenote":false,"isSkynote":false,"skyjudgeNumber":0,"startJudgeTime":83.029,"xOffset":0.7,"speedGroup":0},{"isFakenote":false,"isSkynote":false,"skyjudgeNumber":0,"startJudgeTime":83.196,"xOffset":0.5,"speedGroup":0}]},{"isFakenote":false,"isSkynote":false,"skyjudgeNumber":0,"notetype":3,"startJudgeTime":83.362,"endJudgeTime":0.029,"xOffset":0.1,"speedGroup":0,"draginfolist":[{"isFakenote":false,"isSkynote":false,"skyjudgeNumber":0,"startJudgeTime":83.529,"xOffset":0.3,"speedGroup":0},{"isFakenote":false,"isSkynote":false,"skyjudgeNumber":0,"startJudgeTime":83.696,"xOffset":0.5,"speedGroup":0},{"isFakenote":false,"isSkynote":false,"skyjudgeNumber":0,"startJudgeTime":83.862,"xOffset":0.2,"speedGroup":0}]},{"isFakenote":false,"isSkynote":true,"skyjudgeNumber":4,"notetype":0,"startJudgeTime":102.696,"endJudgeTime":0.029,"xOffset":0,"speedGroup":0,"draginfolist":[]},{"isFakenote":false,"isSkynote":false,"skyjudgeNumber":0,"notetype":3,"startJudgeTime":102.862,"endJudgeTime":0.029,"xOffset":0.85,"speedGroup":0,"draginfolist":[{"isFakenote":false,"isSkynote":false,"skyjudgeNumber":0,"startJudgeTime":102.946,"xOffset":0.6,"speedGroup":0}]},{"isFakenote":false,"isSkynote":true,"skyjudgeNumber":3,"notetype":0,"startJudgeTime":103.029,"endJudgeTime":0.029,"xOffset":0,"speedGroup":0,"draginfolist":[]},{"isFakenote":false,"isSkynote":false,"skyjudgeNumber":0,"notetype":3,"startJudgeTime":103.196,"endJudgeTime":0.029,"xOffset":0.15,"speedGroup":0,"draginfolist":[{"isFakenote":false,"isSkynote":false,"skyjudgeNumber":0,"startJudgeTime":103.279,"xOffset":0.4,"speedGroup":0}]},{"isFakenote":false,"isSkynote":true,"skyjudgeNumber":4,"notetype":0,"startJudgeTime":103.362,"endJudgeTime":0.029,"xOffset":0,"speedGroup":1,"draginfolist":[]},{"isFakenote":false,"isSkynote":false,"skyjudgeNumber":0,"notetype":3,"startJudgeTime":103.529,"endJudgeTime":0.029,"xOffset":0.8,"speedGroup":1,"draginfolist":[{"isFakenote":false,"isSkynote":false,"skyjudgeNumber":0,"startJudgeTime":103.612,"xOffset":0.5,"speedGroup":1}]},{"isFakenote":false,"isSkynote":true,"skyjudgeNumber":3,"notetype":0,"startJudgeTime":103.696,"endJudgeTime":0.029,"xOffset":0,"speedGroup":1,"draginfolist":[]},{"isFakenote":false,"isSkynote":false,"skyjudgeNumber":0,"notetype":3,"startJudgeTime":103.862,"endJudgeTime":0.029,"xOffset":0.2,"speedGroup":1,"draginfolist":[{"isFakenote":false,"isSkynote":false,"skyjudgeNumber":0,"startJudgeTime":103.946,"xOffset":0.5,"speedGroup":1}]},{"isFakenote":false,"isSkynote":false,"skyjudgeNumber":0,"notetype":3,"startJudgeTime":104.029,"endJudgeTime":0.029,"xOffset":0.4,"speedGroup":1,"draginfolist":[{"isFakenote":false,"isSkynote":false,"skyjudgeNumber":0,"startJudgeTime":104.196,"xOffset":0.2,"speedGroup":1},{"isFakenote":false,"isSkynote":false,"skyjudgeNumber":0,"startJudgeTime":104.279,"xOffset":0.1,"speedGroup":1}]},{"isFakenote":false,"isSkynote":true,"skyjudgeNumber":3,"notetype":3,"startJudgeTime":105.362,"endJudgeTime":0.029,"xOffset":0,"speedGroup":1,"draginfolist":[{"isFakenote":false,"isSkynote":true,"skyjudgeNumber":3,"startJudgeTime":105.446,"xOffset":0,"speedGroup":1},{"isFakenote":false,"isSkynote":true,"skyjudgeNumber":3,"startJudgeTime":105.529,"xOffset":0,"speedGroup":1},{"isFakenote":false,"isSkynote":true,"skyjudgeNumber":3,"startJudgeTime":105.612,"xOffset":0,"speedGroup":1}]},{"isFakenote":false,"isSkynote":true,"skyjudgeNumber":4,"notetype":3,"startJudgeTime":105.696,"endJudgeTime":0.029,"xOffset":0,"speedGroup":1,"draginfolist":[{"isFakenote":false,"isSkynote":true,"skyjudgeNumber":4,"startJudgeTime":105.779,"xOffset":0,"speedGroup":1},{"isFakenote":false,"isSkynote":true,"skyjudgeNumber":4,"startJudgeTime":105.862,"xOffset":0,"speedGroup":1},{"isFakenote":false,"isSkynote":true,"skyjudgeNumber":4,"startJudgeTime":105.946,"xOffset":0,"speedGroup":1}]},{"isFakenote":false,"isSkynote":true,"skyjudgeNumber":2,"notetype":3,"startJudgeTime":106.362,"endJudgeTime":0.029,"xOffset":0,"speedGroup":1,"draginfolist":[{"isFakenote":false,"isSkynote":true,"skyjudgeNumber":2,"startJudgeTime":106.446,"xOffset":0,"speedGroup":1},{"isFakenote":false,"isSkynote":true,"skyjudgeNumber":2,"startJudgeTime":106.529,"xOffset":0,"speedGroup":1},{"isFakenote":false,"isSkynote":true,"skyjudgeNumber":2,"startJudgeTime":106.612,"xOffset":0,"speedGroup":1},{"isFakenote":false,"isSkynote":true,"skyjudgeNumber":2,"startJudgeTime":106.696,"xOffset":0,"speedGroup":1},{"isFakenote":false,"isSkynote":true,"skyjudgeNumber":2,"startJudgeTime":106.779,"xOffset":0,"speedGroup":1},{"isFakenote":false,"isSkynote":true,"skyjudgeNumber":2,"startJudgeTime":106.862,"xOffset":0,"speedGroup":1},{"isFakenote":false,"isSkynote":true,"skyjudgeNumber":2,"startJudgeTime":106.946,"xOffset":0,"speedGroup":1},{"isFakenote":false,"isSkynote":true,"skyjudgeNumber":2,"startJudgeTime":107.029,"xOffset":0,"speedGroup":1},{"isFakenote":false,"isSkynote":true,"skyjudgeNumber":2,"startJudgeTime":107.112,"xOffset":0,"speedGroup":1},{"isFakenote":false,"isSkynote":true,"skyjudgeNumber":2,"startJudgeTime":107.196,"xOffset":0,"speedGroup":1},{"isFakenote":false,"isSkynote":true,"skyjudgeNumber":2,"startJudgeTime":107.279,"xOffset":0,"speedGroup":1},{"isFakenote":false,"isSkynote":true,"skyjudgeNumber":2,"startJudgeTime":107.362,"xOffset":0,"speedGroup":1},{"isFakenote":false,"isSkynote":true,"skyjudgeNumber":2,"startJudgeTime":107.446,"xOffset":0,"speedGroup":1},{"isFakenote":false,"isSkynote":true,"skyjudgeNumber":2,"startJudgeTime":107.529,"xOffset":0,"speedGroup":1},{"isFakenote":false,"isSkynote":true,"skyjudgeNumber":2,"startJudgeTime":107.612,"xOffset":0,"speedGroup":1}]},{"isFakenote":false,"isSkynote":true,"skyjudgeNumber":2,"notetype":1,"startJudgeTime":107.696,"endJudgeTime":0.029,"xOffset":0,"speedGroup":1,"draginfolist":[]},{"isFakenote":false,"isSkynote":true,"skyjudgeNumber":1,"notetype":3,"startJudgeTime":106.029,"endJudgeTime":0.029,"xOffset":0,"speedGroup":1,"draginfolist":[{"isFakenote":false,"isSkynote":true,"skyjudgeNumber":1,"startJudgeTime":106.112,"xOffset":0,"speedGroup":1},{"isFakenote":false,"isSkynote":true,"skyjudgeNumber":1,"startJudgeTime":106.196,"xOffset":0,"speedGroup":1},{"isFakenote":false,"isSkynote":true,"skyjudgeNumber":1,"startJudgeTime":106.279,"xOffset":0,"speedGroup":1}]},{"isFakenote":false,"isSkynote":true,"skyjudgeNumber":1,"notetype":3,"startJudgeTime":106.696,"endJudgeTime":0.029,"xOffset":0,"speedGroup":1,"draginfolist":[{"isFakenote":false,"isSkynote":true,"skyjudgeNumber":1,"startJudgeTime":106.779,"xOffset":0,"speedGroup":1},{"isFakenote":false,"isSkynote":true,"skyjudgeNumber":1,"startJudgeTime":106.862,"xOffset":0,"speedGroup":1},{"isFakenote":false,"isSkynote":true,"skyjudgeNumber":1,"startJudgeTime":106.946,"xOffset":0,"speedGroup":1},{"isFakenote":false,"isSkynote":true,"skyjudgeNumber":1,"startJudgeTime":107.029,"xOffset":0,"speedGroup":1},{"isFakenote":false,"isSkynote":true,"skyjudgeNumber":1,"startJudgeTime":107.112,"xOffset":0,"speedGroup":1},{"isFakenote":false,"isSkynote":true,"skyjudgeNumber":1,"startJudgeTime":107.196,"xOffset":0,"speedGroup":1},{"isFakenote":false,"isSkynote":true,"skyjudgeNumber":1,"startJudgeTime":107.279,"xOffset":0,"speedGroup":1},{"isFakenote":false,"isSkynote":true,"skyjudgeNumber":1,"startJudgeTime":107.362,"xOffset":0,"speedGroup":1},{"isFakenote":false,"isSkynote":true,"skyjudgeNumber":1,"startJudgeTime":107.446,"xOffset":0,"speedGroup":1},{"isFakenote":false,"isSkynote":true,"skyjudgeNumber":1,"startJudgeTime":107.529,"xOffset":0,"speedGroup":1},{"isFakenote":false,"isSkynote":true,"skyjudgeNumber":1,"startJudgeTime":107.612,"xOffset":0,"speedGroup":1}]},{"isFakenote":false,"isSkynote":true,"skyjudgeNumber":1,"notetype":1,"startJudgeTime":107.696,"endJudgeTime":0.029,"xOffset":0,"speedGroup":1,"draginfolist":[]},{"isFakenote":false,"isSkynote":true,"skyjudgeNumber":4,"notetype":0,"startJudgeTime":104.362,"endJudgeTime":0.029,"xOffset":0,"speedGroup":1,"draginfolist":[]},{"isFakenote":false,"isSkynote":false,"skyjudgeNumber":0,"notetype":3,"startJudgeTime":104.529,"endJudgeTime":0.029,"xOffset":0.85,"speedGroup":1,"draginfolist":[{"isFakenote":false,"isSkynote":false,"skyjudgeNumber":0,"startJudgeTime":104.612,"xOffset":0.6,"speedGroup":1}]},{"isFakenote":false,"isSkynote":true,"skyjudgeNumber":3,"notetype":0,"startJudgeTime":104.696,"endJudgeTime":0.029,"xOffset":0,"speedGroup":1,"draginfolist":[]},{"isFakenote":false,"isSkynote":true,"skyjudgeNumber":4,"notetype":0,"startJudgeTime":105.029,"endJudgeTime":0.029,"xOffset":0,"speedGroup":1,"draginfolist":[]},{"isFakenote":false,"isSkynote":true,"skyjudgeNumber":4,"notetype":0,"startJudgeTime":108.362,"endJudgeTime":0.029,"xOffset":0,"speedGroup":0,"draginfolist":[]},{"isFakenote":false,"isSkynote":false,"skyjudgeNumber":0,"notetype":0,"startJudgeTime":108.696,"endJudgeTime":0.029,"xOffset":0.9,"speedGroup":0,"draginfolist":[]},{"isFakenote":false,"isSkynote":true,"skyjudgeNumber":4,"notetype":0,"startJudgeTime":109.029,"endJudgeTime":0.029,"xOffset":0,"speedGroup":0,"draginfolist":[]},{"isFakenote":false,"isSkynote":false,"skyjudgeNumber":0,"notetype":0,"startJudgeTime":109.362,"endJudgeTime":0.029,"xOffset":0.9,"speedGroup":0,"draginfolist":[]},{"isFakenote":false,"isSkynote":true,"skyjudgeNumber":4,"notetype":0,"startJudgeTime":109.696,"endJudgeTime":0.029,"xOffset":0,"speedGroup":0,"draginfolist":[]},{"isFakenote":false,"isSkynote":true,"skyjudgeNumber":4,"notetype":0,"startJudgeTime":110.362,"endJudgeTime":0.029,"xOffset":0,"speedGroup":0,"draginfolist":[]},{"isFakenote":false,"isSkynote":true,"skyjudgeNumber":3,"notetype":1,"startJudgeTime":108.362,"endJudgeTime":0.029,"xOffset":0,"speedGroup":0,"draginfolist":[]},{"isFakenote":false,"isSkynote":true,"skyjudgeNumber":3,"notetype":1,"startJudgeTime":109.029,"endJudgeTime":0.029,"xOffset":0,"speedGroup":0,"draginfolist":[]},{"isFakenote":false,"isSkynote":true,"skyjudgeNumber":3,"notetype":1,"startJudgeTime":109.696,"endJudgeTime":0.029,"xOffset":0,"speedGroup":0,"draginfolist":[]},{"isFakenote":false,"isSkynote":true,"skyjudgeNumber":3,"notetype":1,"startJudgeTime":110.362,"endJudgeTime":0.029,"xOffset":0,"speedGroup":0,"draginfolist":[]},{"isFakenote":false,"isSkynote":true,"skyjudgeNumber":3,"notetype":0,"startJudgeTime":110.696,"endJudgeTime":0.029,"xOffset":0,"speedGroup":0,"draginfolist":[]},{"isFakenote":false,"isSkynote":true,"skyjudgeNumber":3,"notetype":0,"startJudgeTime":111.029,"endJudgeTime":0.029,"xOffset":0,"speedGroup":0,"draginfolist":[]},{"isFakenote":false,"isSkynote":true,"skyjudgeNumber":3,"notetype":0,"startJudgeTime":111.362,"endJudgeTime":0.029,"xOffset":0,"speedGroup":0,"draginfolist":[]},{"isFakenote":false,"isSkynote":true,"skyjudgeNumber":3,"notetype":0,"startJudgeTime":111.696,"endJudgeTime":0.029,"xOffset":0,"speedGroup":0,"draginfolist":[]},{"isFakenote":false,"isSkynote":true,"skyjudgeNumber":4,"notetype":0,"startJudgeTime":112.029,"endJudgeTime":0.029,"xOffset":0,"speedGroup":0,"draginfolist":[]},{"isFakenote":false,"isSkynote":true,"skyjudgeNumber":4,"notetype":0,"startJudgeTime":112.362,"endJudgeTime":0.029,"xOffset":0,"speedGroup":0,"draginfolist":[]},{"isFakenote":false,"isSkynote":true,"skyjudgeNumber":4,"notetype":0,"startJudgeTime":112.696,"endJudgeTime":0.029,"xOffset":0,"speedGroup":0,"draginfolist":[]},{"isFakenote":false,"isSkynote":true,"skyjudgeNumber":4,"notetype":0,"startJudgeTime":113.029,"endJudgeTime":0.029,"xOffset":0,"speedGroup":0,"draginfolist":[]},{"isFakenote":false,"isSkynote":true,"skyjudgeNumber":4,"notetype":1,"startJudgeTime":111.029,"endJudgeTime":0.029,"xOffset":0,"speedGroup":0,"draginfolist":[]},{"isFakenote":false,"isSkynote":true,"skyjudgeNumber":4,"notetype":1,"startJudgeTime":111.696,"endJudgeTime":0.029,"xOffset":0,"speedGroup":0,"draginfolist":[]},{"isFakenote":false,"isSkynote":true,"skyjudgeNumber":3,"notetype":1,"startJudgeTime":112.362,"endJudgeTime":0.029,"xOffset":0,"speedGroup":0,"draginfolist":[]},{"isFakenote":false,"isSkynote":true,"skyjudgeNumber":3,"notetype":1,"startJudgeTime":113.029,"endJudgeTime":0.029,"xOffset":0,"speedGroup":0,"draginfolist":[]},{"isFakenote":false,"isSkynote":false,"skyjudgeNumber":0,"notetype":0,"startJudgeTime":108.029,"endJudgeTime":0.029,"xOffset":0.9,"speedGroup":2,"draginfolist":[]},{"isFakenote":false,"isSkynote":false,"skyjudgeNumber":0,"notetype":0,"startJudgeTime":113.362,"endJudgeTime":0.029,"xOffset":0.1,"speedGroup":0,"draginfolist":[]},{"isFakenote":false,"isSkynote":true,"skyjudgeNumber":3,"notetype":0,"startJudgeTime":113.696,"endJudgeTime":0.029,"xOffset":0,"speedGroup":0,"draginfolist":[]},{"isFakenote":false,"isSkynote":true,"skyjudgeNumber":3,"notetype":0,"startJudgeTime":114.362,"endJudgeTime":0.029,"xOffset":0,"speedGroup":0,"draginfolist":[]},{"isFakenote":false,"isSkynote":false,"skyjudgeNumber":0,"notetype":0,"startJudgeTime":114.696,"endJudgeTime":0.029,"xOffset":0.1,"speedGroup":0,"draginfolist":[]},{"isFakenote":false,"isSkynote":true,"skyjudgeNumber":3,"notetype":0,"startJudgeTime":115.029,"endJudgeTime":0.029,"xOffset":0,"speedGroup":0,"draginfolist":[]},{"isFakenote":false,"isSkynote":true,"skyjudgeNumber":3,"notetype":0,"startJudgeTime":115.696,"endJudgeTime":0.029,"xOffset":0,"speedGroup":0,"draginfolist":[]},{"isFakenote":false,"isSkynote":true,"skyjudgeNumber":4,"notetype":0,"startJudgeTime":116.029,"endJudgeTime":0.029,"xOffset":0,"speedGroup":0,"draginfolist":[]},{"isFakenote":false,"isSkynote":true,"skyjudgeNumber":4,"notetype":0,"startJudgeTime":116.362,"endJudgeTime":0.029,"xOffset":0,"speedGroup":0,"draginfolist":[]},{"isFakenote":false,"isSkynote":true,"skyjudgeNumber":4,"notetype":0,"startJudgeTime":116.696,"endJudgeTime":0.029,"xOffset":0,"speedGroup":0,"draginfolist":[]},{"isFakenote":false,"isSkynote":true,"skyjudgeNumber":4,"notetype":0,"startJudgeTime":117.029,"endJudgeTime":0.029,"xOffset":0,"speedGroup":0,"draginfolist":[]},{"isFakenote":false,"isSkynote":true,"skyjudgeNumber":3,"notetype":0,"startJudgeTime":117.362,"endJudgeTime":0.029,"xOffset":0,"speedGroup":0,"draginfolist":[]},{"isFakenote":false,"isSkynote":true,"skyjudgeNumber":3,"notetype":0,"startJudgeTime":117.696,"endJudgeTime":0.029,"xOffset":0,"speedGroup":0,"draginfolist":[]},{"isFakenote":false,"isSkynote":true,"skyjudgeNumber":3,"notetype":0,"startJudgeTime":118.029,"endJudgeTime":0.029,"xOffset":0,"speedGroup":0,"draginfolist":[]},{"isFakenote":false,"isSkynote":true,"skyjudgeNumber":4,"notetype":1,"startJudgeTime":113.696,"endJudgeTime":0.029,"xOffset":0,"speedGroup":0,"draginfolist":[]},{"isFakenote":false,"isSkynote":true,"skyjudgeNumber":4,"notetype":1,"startJudgeTime":114.362,"endJudgeTime":0.029,"xOffset":0,"speedGroup":0,"draginfolist":[]},{"isFakenote":false,"isSkynote":true,"skyjudgeNumber":4,"notetype":1,"startJudgeTime":115.029,"endJudgeTime":0.029,"xOffset":0,"speedGroup":0,"draginfolist":[]},{"isFakenote":false,"isSkynote":true,"skyjudgeNumber":4,"notetype":1,"startJudgeTime":115.696,"endJudgeTime":0.029,"xOffset":0,"speedGroup":0,"draginfolist":[]},{"isFakenote":false,"isSkynote":true,"skyjudgeNumber":3,"notetype":1,"startJudgeTime":116.362,"endJudgeTime":0.029,"xOffset":0,"speedGroup":0,"draginfolist":[]},{"isFakenote":false,"isSkynote":true,"skyjudgeNumber":3,"notetype":1,"startJudgeTime":117.029,"endJudgeTime":0.029,"xOffset":0,"speedGroup":0,"draginfolist":[]},{"isFakenote":false,"isSkynote":true,"skyjudgeNumber":4,"notetype":1,"startJudgeTime":117.696,"endJudgeTime":0.029,"xOffset":0,"speedGroup":0,"draginfolist":[]},{"isFakenote":false,"isSkynote":true,"skyjudgeNumber":3,"notetype":3,"startJudgeTime":118.196,"endJudgeTime":0.029,"xOffset":0,"speedGroup":0,"draginfolist":[]},{"isFakenote":false,"isSkynote":true,"skyjudgeNumber":3,"notetype":0,"startJudgeTime":119.029,"endJudgeTime":0.029,"xOffset":0,"speedGroup":0,"draginfolist":[]},{"isFakenote":false,"isSkynote":true,"skyjudgeNumber":3,"notetype":0,"startJudgeTime":119.362,"endJudgeTime":0.029,"xOffset":0,"speedGroup":0,"draginfolist":[]},{"isFakenote":false,"isSkynote":true,"skyjudgeNumber":3,"notetype":0,"startJudgeTime":119.696,"endJudgeTime":0.029,"xOffset":0,"speedGroup":0,"draginfolist":[]},{"isFakenote":false,"isSkynote":true,"skyjudgeNumber":3,"notetype":0,"startJudgeTime":120.029,"endJudgeTime":0.029,"xOffset":0,"speedGroup":0,"draginfolist":[]},{"isFakenote":false,"isSkynote":true,"skyjudgeNumber":3,"notetype":0,"startJudgeTime":120.362,"endJudgeTime":0.029,"xOffset":0,"speedGroup":0,"draginfolist":[]},{"isFakenote":false,"isSkynote":true,"skyjudgeNumber":3,"notetype":0,"startJudgeTime":120.696,"endJudgeTime":0.029,"xOffset":0,"speedGroup":0,"draginfolist":[]},{"isFakenote":false,"isSkynote":true,"skyjudgeNumber":3,"notetype":0,"startJudgeTime":121.029,"endJudgeTime":0.029,"xOffset":0,"speedGroup":0,"draginfolist":[]},{"isFakenote":false,"isSkynote":true,"skyjudgeNumber":4,"notetype":0,"startJudgeTime":121.362,"endJudgeTime":0.029,"xOffset":0,"speedGroup":0,"draginfolist":[]},{"isFakenote":false,"isSkynote":true,"skyjudgeNumber":4,"notetype":0,"startJudgeTime":121.696,"endJudgeTime":0.029,"xOffset":0,"speedGroup":0,"draginfolist":[]},{"isFakenote":false,"isSkynote":true,"skyjudgeNumber":4,"notetype":0,"startJudgeTime":122.029,"endJudgeTime":0.029,"xOffset":0,"speedGroup":0,"draginfolist":[]},{"isFakenote":false,"isSkynote":true,"skyjudgeNumber":4,"notetype":0,"startJudgeTime":122.362,"endJudgeTime":0.029,"xOffset":0,"speedGroup":0,"draginfolist":[]},{"isFakenote":false,"isSkynote":true,"skyjudgeNumber":4,"notetype":0,"startJudgeTime":122.696,"endJudgeTime":0.029,"xOffset":0,"speedGroup":0,"draginfolist":[]},{"isFakenote":false,"isSkynote":true,"skyjudgeNumber":4,"notetype":0,"startJudgeTime":123.029,"endJudgeTime":0.029,"xOffset":0,"speedGroup":0,"draginfolist":[]},{"isFakenote":false,"isSkynote":true,"skyjudgeNumber":4,"notetype":0,"startJudgeTime":123.362,"endJudgeTime":0.029,"xOffset":0,"speedGroup":0,"draginfolist":[]},{"isFakenote":false,"isSkynote":true,"skyjudgeNumber":4,"notetype":0,"startJudgeTime":123.696,"endJudgeTime":0.029,"xOffset":0,"speedGroup":0,"draginfolist":[]},{"isFakenote":false,"isSkynote":true,"skyjudgeNumber":2,"notetype":1,"startJudgeTime":119.696,"endJudgeTime":0.029,"xOffset":0,"speedGroup":0,"draginfolist":[]},{"isFakenote":false,"isSkynote":true,"skyjudgeNumber":2,"notetype":1,"startJudgeTime":120.362,"endJudgeTime":0.029,"xOffset":0,"speedGroup":0,"draginfolist":[]},{"isFakenote":false,"isSkynote":true,"skyjudgeNumber":2,"notetype":1,"startJudgeTime":121.029,"endJudgeTime":0.029,"xOffset":0,"speedGroup":0,"draginfolist":[]},{"isFakenote":false,"isSkynote":true,"skyjudgeNumber":1,"notetype":1,"startJudgeTime":122.362,"endJudgeTime":0.029,"xOffset":0,"speedGroup":0,"draginfolist":[]},{"isFakenote":false,"isSkynote":true,"skyjudgeNumber":1,"notetype":1,"startJudgeTime":123.029,"endJudgeTime":0.029,"xOffset":0,"speedGroup":0,"draginfolist":[]},{"isFakenote":false,"isSkynote":true,"skyjudgeNumber":1,"notetype":1,"startJudgeTime":123.696,"endJudgeTime":0.029,"xOffset":0,"speedGroup":0,"draginfolist":[]},{"isFakenote":false,"isSkynote":true,"skyjudgeNumber":3,"notetype":0,"startJudgeTime":124.362,"endJudgeTime":0.029,"xOffset":0,"speedGroup":0,"draginfolist":[]},{"isFakenote":false,"isSkynote":true,"skyjudgeNumber":4,"notetype":0,"startJudgeTime":126.029,"endJudgeTime":0.029,"xOffset":0,"speedGroup":0,"draginfolist":[]},{"isFakenote":false,"isSkynote":true,"skyjudgeNumber":4,"notetype":0,"startJudgeTime":126.362,"endJudgeTime":0.029,"xOffset":0,"speedGroup":0,"draginfolist":[]},{"isFakenote":false,"isSkynote":true,"skyjudgeNumber":2,"notetype":1,"startJudgeTime":124.362,"endJudgeTime":0.029,"xOffset":0,"speedGroup":0,"draginfolist":[]},{"isFakenote":false,"isSkynote":true,"skyjudgeNumber":1,"notetype":1,"startJudgeTime":126.362,"endJudgeTime":0.029,"xOffset":0,"speedGroup":0,"draginfolist":[]},{"isFakenote":false,"isSkynote":true,"skyjudgeNumber":4,"notetype":3,"startJudgeTime":126.696,"endJudgeTime":0.029,"xOffset":0,"speedGroup":0,"draginfolist":[{"isFakenote":false,"isSkynote":true,"skyjudgeNumber":4,"startJudgeTime":126.779,"xOffset":0,"speedGroup":0},{"isFakenote":false,"isSkynote":true,"skyjudgeNumber":4,"startJudgeTime":126.862,"xOffset":0,"speedGroup":0},{"isFakenote":false,"isSkynote":true,"skyjudgeNumber":4,"startJudgeTime":126.946,"xOffset":0,"speedGroup":0}]},{"isFakenote":false,"isSkynote":true,"skyjudgeNumber":3,"notetype":3,"startJudgeTime":127.029,"endJudgeTime":0.029,"xOffset":0,"speedGroup":0,"draginfolist":[{"isFakenote":false,"isSkynote":true,"skyjudgeNumber":3,"startJudgeTime":127.112,"xOffset":0,"speedGroup":0},{"isFakenote":false,"isSkynote":true,"skyjudgeNumber":3,"startJudgeTime":127.196,"xOffset":0,"speedGroup":0},{"isFakenote":false,"isSkynote":true,"skyjudgeNumber":3,"startJudgeTime":127.279,"xOffset":0,"speedGroup":0}]},{"isFakenote":false,"isSkynote":true,"skyjudgeNumber":2,"notetype":3,"startJudgeTime":127.362,"endJudgeTime":0.029,"xOffset":0,"speedGroup":0,"draginfolist":[{"isFakenote":false,"isSkynote":true,"skyjudgeNumber":2,"startJudgeTime":127.446,"xOffset":0,"speedGroup":0},{"isFakenote":false,"isSkynote":true,"skyjudgeNumber":2,"startJudgeTime":127.529,"xOffset":0,"speedGroup":0},{"isFakenote":false,"isSkynote":true,"skyjudgeNumber":2,"startJudgeTime":127.612,"xOffset":0,"speedGroup":0}]},{"isFakenote":false,"isSkynote":true,"skyjudgeNumber":1,"notetype":3,"startJudgeTime":127.696,"endJudgeTime":0.029,"xOffset":0,"speedGroup":0,"draginfolist":[{"isFakenote":false,"isSkynote":true,"skyjudgeNumber":1,"startJudgeTime":127.779,"xOffset":0,"speedGroup":0},{"isFakenote":false,"isSkynote":true,"skyjudgeNumber":1,"startJudgeTime":127.862,"xOffset":0,"speedGroup":0},{"isFakenote":false,"isSkynote":true,"skyjudgeNumber":1,"startJudgeTime":127.946,"xOffset":0,"speedGroup":0},{"isFakenote":false,"isSkynote":true,"skyjudgeNumber":1,"startJudgeTime":128.029,"xOffset":0,"speedGroup":0},{"isFakenote":false,"isSkynote":true,"skyjudgeNumber":1,"startJudgeTime":128.112,"xOffset":0,"speedGroup":0},{"isFakenote":false,"isSkynote":true,"skyjudgeNumber":1,"startJudgeTime":128.196,"xOffset":0,"speedGroup":0},{"isFakenote":false,"isSkynote":true,"skyjudgeNumber":1,"startJudgeTime":128.279,"xOffset":0,"speedGroup":0},{"isFakenote":false,"isSkynote":true,"skyjudgeNumber":1,"startJudgeTime":128.362,"xOffset":0,"speedGroup":0},{"isFakenote":false,"isSkynote":true,"skyjudgeNumber":1,"startJudgeTime":128.446,"xOffset":0,"speedGroup":0},{"isFakenote":false,"isSkynote":true,"skyjudgeNumber":1,"startJudgeTime":128.529,"xOffset":0,"speedGroup":0},{"isFakenote":false,"isSkynote":true,"skyjudgeNumber":1,"startJudgeTime":128.612,"xOffset":0,"speedGroup":0},{"isFakenote":false,"isSkynote":true,"skyjudgeNumber":1,"startJudgeTime":128.696,"xOffset":0,"speedGroup":0},{"isFakenote":false,"isSkynote":true,"skyjudgeNumber":1,"startJudgeTime":128.779,"xOffset":0,"speedGroup":0},{"isFakenote":false,"isSkynote":true,"skyjudgeNumber":1,"startJudgeTime":128.862,"xOffset":0,"speedGroup":0},{"isFakenote":false,"isSkynote":true,"skyjudgeNumber":1,"startJudgeTime":128.946,"xOffset":0,"speedGroup":0}]},{"isFakenote":false,"isSkynote":true,"skyjudgeNumber":2,"notetype":3,"startJudgeTime":128.029,"endJudgeTime":0.029,"xOffset":0,"speedGroup":0,"draginfolist":[{"isFakenote":false,"isSkynote":true,"skyjudgeNumber":2,"startJudgeTime":128.112,"xOffset":0,"speedGroup":0},{"isFakenote":false,"isSkynote":true,"skyjudgeNumber":2,"startJudgeTime":128.196,"xOffset":0,"speedGroup":0},{"isFakenote":false,"isSkynote":true,"skyjudgeNumber":2,"startJudgeTime":128.279,"xOffset":0,"speedGroup":0},{"isFakenote":false,"isSkynote":true,"skyjudgeNumber":2,"startJudgeTime":128.362,"xOffset":0,"speedGroup":0},{"isFakenote":false,"isSkynote":true,"skyjudgeNumber":2,"startJudgeTime":128.446,"xOffset":0,"speedGroup":0},{"isFakenote":false,"isSkynote":true,"skyjudgeNumber":2,"startJudgeTime":128.529,"xOffset":0,"speedGroup":0},{"isFakenote":false,"isSkynote":true,"skyjudgeNumber":2,"startJudgeTime":128.612,"xOffset":0,"speedGroup":0},{"isFakenote":false,"isSkynote":true,"skyjudgeNumber":2,"startJudgeTime":128.696,"xOffset":0,"speedGroup":0},{"isFakenote":false,"isSkynote":true,"skyjudgeNumber":2,"startJudgeTime":128.779,"xOffset":0,"speedGroup":0},{"isFakenote":false,"isSkynote":true,"skyjudgeNumber":2,"startJudgeTime":128.862,"xOffset":0,"speedGroup":0},{"isFakenote":false,"isSkynote":true,"skyjudgeNumber":2,"startJudgeTime":128.946,"xOffset":0,"speedGroup":0}]},{"isFakenote":false,"isSkynote":true,"skyjudgeNumber":2,"notetype":1,"startJudgeTime":129.029,"endJudgeTime":0.029,"xOffset":0,"speedGroup":0,"draginfolist":[]},{"isFakenote":false,"isSkynote":true,"skyjudgeNumber":2,"notetype":1,"startJudgeTime":129.196,"endJudgeTime":0.029,"xOffset":0,"speedGroup":0,"draginfolist":[]},{"isFakenote":false,"isSkynote":true,"skyjudgeNumber":4,"notetype":0,"startJudgeTime":130.029,"endJudgeTime":0.029,"xOffset":0,"speedGroup":0,"draginfolist":[]},{"isFakenote":false,"isSkynote":true,"skyjudgeNumber":4,"notetype":0,"startJudgeTime":130.696,"endJudgeTime":0.029,"xOffset":0,"speedGroup":0,"draginfolist":[]},{"isFakenote":false,"isSkynote":true,"skyjudgeNumber":4,"notetype":0,"startJudgeTime":131.362,"endJudgeTime":0.029,"xOffset":0,"speedGroup":0,"draginfolist":[]},{"isFakenote":false,"isSkynote":true,"skyjudgeNumber":3,"notetype":0,"startJudgeTime":132.696,"endJudgeTime":0.029,"xOffset":0,"speedGroup":0,"draginfolist":[]},{"isFakenote":false,"isSkynote":false,"skyjudgeNumber":0,"notetype":0,"startJudgeTime":115.362,"endJudgeTime":0.029,"xOffset":0.1,"speedGroup":0,"draginfolist":[]},{"isFakenote":false,"isSkynote":false,"skyjudgeNumber":0,"notetype":0,"startJudgeTime":114.029,"endJudgeTime":0.029,"xOffset":0.1,"speedGroup":0,"draginfolist":[]},{"isFakenote":false,"isSkynote":false,"skyjudgeNumber":0,"notetype":0,"startJudgeTime":110.029,"endJudgeTime":0.029,"xOffset":0.9,"speedGroup":0,"draginfolist":[]},{"isFakenote":false,"isSkynote":true,"skyjudgeNumber":4,"notetype":0,"startJudgeTime":125.362,"endJudgeTime":0.029,"xOffset":0,"speedGroup":0,"draginfolist":[]},{"isFakenote":false,"isSkynote":true,"skyjudgeNumber":1,"notetype":3,"startJudgeTime":129.362,"endJudgeTime":0.029,"xOffset":0,"speedGroup":0,"draginfolist":[{"isFakenote":false,"isSkynote":true,"skyjudgeNumber":3,"startJudgeTime":131.696,"xOffset":0,"speedGroup":0},{"isFakenote":false,"isSkynote":true,"skyjudgeNumber":3,"startJudgeTime":131.862,"xOffset":0,"speedGroup":0},{"isFakenote":false,"isSkynote":true,"skyjudgeNumber":3,"startJudgeTime":132.029,"xOffset":0,"speedGroup":0}]},{"isFakenote":false,"isSkynote":true,"skyjudgeNumber":4,"notetype":1,"startJudgeTime":130.362,"endJudgeTime":0.029,"xOffset":0,"speedGroup":0,"draginfolist":[]},{"isFakenote":false,"isSkynote":true,"skyjudgeNumber":4,"notetype":1,"startJudgeTime":131.029,"endJudgeTime":0.029,"xOffset":0,"speedGroup":0,"draginfolist":[]},{"isFakenote":false,"isSkynote":true,"skyjudgeNumber":4,"notetype":1,"startJudgeTime":131.696,"endJudgeTime":0.029,"xOffset":0,"speedGroup":0,"draginfolist":[]},{"isFakenote":false,"isSkynote":true,"skyjudgeNumber":3,"notetype":1,"startJudgeTime":132.362,"endJudgeTime":0.029,"xOffset":0,"speedGroup":0,"draginfolist":[]},{"isFakenote":false,"isSkynote":true,"skyjudgeNumber":3,"notetype":1,"startJudgeTime":133.029,"endJudgeTime":0.029,"xOffset":0,"speedGroup":0,"draginfolist":[]},{"isFakenote":false,"isSkynote":true,"skyjudgeNumber":3,"notetype":0,"startJudgeTime":133.362,"endJudgeTime":0.029,"xOffset":0,"speedGroup":0,"draginfolist":[]},{"isFakenote":false,"isSkynote":true,"skyjudgeNumber":3,"notetype":0,"startJudgeTime":134.029,"endJudgeTime":0.029,"xOffset":0,"speedGroup":0,"draginfolist":[]},{"isFakenote":false,"isSkynote":true,"skyjudgeNumber":3,"notetype":1,"startJudgeTime":133.696,"endJudgeTime":0.029,"xOffset":0,"speedGroup":0,"draginfolist":[]},{"isFakenote":false,"isSkynote":true,"skyjudgeNumber":3,"notetype":1,"startJudgeTime":134.362,"endJudgeTime":0.029,"xOffset":0,"speedGroup":0,"draginfolist":[]},{"isFakenote":false,"isSkynote":true,"skyjudgeNumber":4,"notetype":1,"startJudgeTime":129.696,"endJudgeTime":0.029,"xOffset":0,"speedGroup":2,"draginfolist":[]},{"isFakenote":false,"isSkynote":true,"skyjudgeNumber":4,"notetype":0,"startJudgeTime":135.362,"endJudgeTime":0.029,"xOffset":0,"speedGroup":0,"draginfolist":[]},{"isFakenote":false,"isSkynote":true,"skyjudgeNumber":4,"notetype":0,"startJudgeTime":136.029,"endJudgeTime":0.029,"xOffset":0,"speedGroup":0,"draginfolist":[]},{"isFakenote":false,"isSkynote":true,"skyjudgeNumber":4,"notetype":0,"startJudgeTime":136.696,"endJudgeTime":0.029,"xOffset":0,"speedGroup":0,"draginfolist":[]},{"isFakenote":false,"isSkynote":true,"skyjudgeNumber":4,"notetype":1,"startJudgeTime":137.029,"endJudgeTime":0.029,"xOffset":0,"speedGroup":0,"draginfolist":[]},{"isFakenote":false,"isSkynote":true,"skyjudgeNumber":4,"notetype":1,"startJudgeTime":136.362,"endJudgeTime":0.029,"xOffset":0,"speedGroup":0,"draginfolist":[]},{"isFakenote":false,"isSkynote":true,"skyjudgeNumber":4,"notetype":1,"startJudgeTime":135.696,"endJudgeTime":0.029,"xOffset":0,"speedGroup":0,"draginfolist":[]},{"isFakenote":false,"isSkynote":true,"skyjudgeNumber":4,"notetype":1,"startJudgeTime":135.029,"endJudgeTime":0.029,"xOffset":0,"speedGroup":0,"draginfolist":[]},{"isFakenote":false,"isSkynote":true,"skyjudgeNumber":3,"notetype":1,"startJudgeTime":137.696,"endJudgeTime":0.029,"xOffset":0,"speedGroup":0,"draginfolist":[]},{"isFakenote":false,"isSkynote":true,"skyjudgeNumber":3,"notetype":1,"startJudgeTime":138.362,"endJudgeTime":0.029,"xOffset":0,"speedGroup":0,"draginfolist":[]},{"isFakenote":false,"isSkynote":true,"skyjudgeNumber":3,"notetype":1,"startJudgeTime":139.029,"endJudgeTime":0.029,"xOffset":0,"speedGroup":0,"draginfolist":[]},{"isFakenote":false,"isSkynote":true,"skyjudgeNumber":3,"notetype":0,"startJudgeTime":138.029,"endJudgeTime":0.029,"xOffset":0,"speedGroup":0,"draginfolist":[]},{"isFakenote":false,"isSkynote":true,"skyjudgeNumber":3,"notetype":0,"startJudgeTime":138.696,"endJudgeTime":0.029,"xOffset":0,"speedGroup":0,"draginfolist":[]},{"isFakenote":false,"isSkynote":false,"skyjudgeNumber":0,"notetype":0,"startJudgeTime":140.696,"endJudgeTime":0.029,"xOffset":0.9,"speedGroup":0,"draginfolist":[]},{"isFakenote":false,"isSkynote":false,"skyjudgeNumber":0,"notetype":0,"startJudgeTime":141.362,"endJudgeTime":0.029,"xOffset":0.9,"speedGroup":0,"draginfolist":[]},{"isFakenote":false,"isSkynote":false,"skyjudgeNumber":0,"notetype":0,"startJudgeTime":142.029,"endJudgeTime":0.029,"xOffset":0.9,"speedGroup":0,"draginfolist":[]},{"isFakenote":false,"isSkynote":true,"skyjudgeNumber":4,"notetype":1,"startJudgeTime":141.696,"endJudgeTime":0.029,"xOffset":0,"speedGroup":0,"draginfolist":[]},{"isFakenote":false,"isSkynote":true,"skyjudgeNumber":4,"notetype":1,"startJudgeTime":141.029,"endJudgeTime":0.029,"xOffset":0,"speedGroup":0,"draginfolist":[]},{"isFakenote":false,"isSkynote":true,"skyjudgeNumber":4,"notetype":1,"startJudgeTime":140.362,"endJudgeTime":0.029,"xOffset":0,"speedGroup":0,"draginfolist":[]},{"isFakenote":false,"isSkynote":true,"skyjudgeNumber":4,"notetype":1,"startJudgeTime":142.362,"endJudgeTime":0.029,"xOffset":0,"speedGroup":0,"draginfolist":[]},{"isFakenote":false,"isSkynote":false,"skyjudgeNumber":0,"notetype":0,"startJudgeTime":143.362,"endJudgeTime":0.029,"xOffset":0.1,"speedGroup":0,"draginfolist":[]},{"isFakenote":false,"isSkynote":false,"skyjudgeNumber":0,"notetype":0,"startJudgeTime":144.029,"endJudgeTime":0.029,"xOffset":0.1,"speedGroup":0,"draginfolist":[]},{"isFakenote":false,"isSkynote":false,"skyjudgeNumber":0,"notetype":0,"startJudgeTime":144.696,"endJudgeTime":0.029,"xOffset":0.1,"speedGroup":0,"draginfolist":[]},{"isFakenote":false,"isSkynote":true,"skyjudgeNumber":3,"notetype":1,"startJudgeTime":143.029,"endJudgeTime":0.029,"xOffset":0,"speedGroup":0,"draginfolist":[]},{"isFakenote":false,"isSkynote":true,"skyjudgeNumber":3,"notetype":1,"startJudgeTime":143.696,"endJudgeTime":0.029,"xOffset":0,"speedGroup":0,"draginfolist":[]},{"isFakenote":false,"isSkynote":true,"skyjudgeNumber":3,"notetype":1,"startJudgeTime":144.362,"endJudgeTime":0.029,"xOffset":0,"speedGroup":0,"draginfolist":[]},{"isFakenote":false,"isSkynote":true,"skyjudgeNumber":3,"notetype":1,"startJudgeTime":145.029,"endJudgeTime":0.029,"xOffset":0,"speedGroup":0,"draginfolist":[]},{"isFakenote":false,"isSkynote":true,"skyjudgeNumber":3,"notetype":3,"startJudgeTime":147.904,"endJudgeTime":0.029,"xOffset":0,"speedGroup":0,"draginfolist":[{"isFakenote":false,"isSkynote":true,"skyjudgeNumber":3,"startJudgeTime":147.946,"xOffset":0,"speedGroup":0},{"isFakenote":false,"isSkynote":true,"skyjudgeNumber":3,"startJudgeTime":147.987,"xOffset":0,"speedGroup":0}]},{"isFakenote":false,"isSkynote":true,"skyjudgeNumber":4,"notetype":3,"startJudgeTime":147.904,"endJudgeTime":0.029,"xOffset":0,"speedGroup":0,"draginfolist":[{"isFakenote":false,"isSkynote":true,"skyjudgeNumber":4,"startJudgeTime":147.946,"xOffset":0,"speedGroup":0},{"isFakenote":false,"isSkynote":true,"skyjudgeNumber":4,"startJudgeTime":147.987,"xOffset":0,"speedGroup":0},{"isFakenote":false,"isSkynote":true,"skyjudgeNumber":4,"startJudgeTime":148.029,"xOffset":0,"speedGroup":0},{"isFakenote":false,"isSkynote":true,"skyjudgeNumber":4,"startJudgeTime":148.112,"xOffset":0,"speedGroup":0},{"isFakenote":false,"isSkynote":true,"skyjudgeNumber":4,"startJudgeTime":148.196,"xOffset":0,"speedGroup":0},{"isFakenote":false,"isSkynote":true,"skyjudgeNumber":4,"startJudgeTime":148.279,"xOffset":0,"speedGroup":0}]},{"isFakenote":false,"isSkynote":true,"skyjudgeNumber":3,"notetype":3,"startJudgeTime":148.362,"endJudgeTime":0.029,"xOffset":0,"speedGroup":0,"draginfolist":[{"isFakenote":false,"isSkynote":true,"skyjudgeNumber":3,"startJudgeTime":148.446,"xOffset":0,"speedGroup":0},{"isFakenote":false,"isSkynote":true,"skyjudgeNumber":3,"startJudgeTime":148.529,"xOffset":0,"speedGroup":0},{"isFakenote":false,"isSkynote":true,"skyjudgeNumber":3,"startJudgeTime":148.612,"xOffset":0,"speedGroup":0}]},{"isFakenote":false,"isSkynote":true,"skyjudgeNumber":2,"notetype":3,"startJudgeTime":148.696,"endJudgeTime":0.029,"xOffset":0,"speedGroup":0,"draginfolist":[{"isFakenote":false,"isSkynote":true,"skyjudgeNumber":2,"startJudgeTime":148.779,"xOffset":0,"speedGroup":0},{"isFakenote":false,"isSkynote":true,"skyjudgeNumber":2,"startJudgeTime":148.862,"xOffset":0,"speedGroup":0},{"isFakenote":false,"isSkynote":true,"skyjudgeNumber":2,"startJudgeTime":148.946,"xOffset":0,"speedGroup":0}]},{"isFakenote":false,"isSkynote":true,"skyjudgeNumber":1,"notetype":3,"startJudgeTime":149.029,"endJudgeTime":0.029,"xOffset":0,"speedGroup":0,"draginfolist":[{"isFakenote":false,"isSkynote":true,"skyjudgeNumber":1,"startJudgeTime":149.112,"xOffset":0,"speedGroup":0},{"isFakenote":false,"isSkynote":true,"skyjudgeNumber":1,"startJudgeTime":149.196,"xOffset":0,"speedGroup":0},{"isFakenote":false,"isSkynote":true,"skyjudgeNumber":1,"startJudgeTime":149.279,"xOffset":0,"speedGroup":0},{"isFakenote":false,"isSkynote":true,"skyjudgeNumber":1,"startJudgeTime":149.362,"xOffset":0,"speedGroup":0},{"isFakenote":false,"isSkynote":true,"skyjudgeNumber":1,"startJudgeTime":149.446,"xOffset":0,"speedGroup":0},{"isFakenote":false,"isSkynote":true,"skyjudgeNumber":1,"startJudgeTime":149.529,"xOffset":0,"speedGroup":0},{"isFakenote":false,"isSkynote":true,"skyjudgeNumber":1,"startJudgeTime":149.612,"xOffset":0,"speedGroup":0},{"isFakenote":false,"isSkynote":true,"skyjudgeNumber":1,"startJudgeTime":149.696,"xOffset":0,"speedGroup":0},{"isFakenote":false,"isSkynote":true,"skyjudgeNumber":1,"startJudgeTime":149.779,"xOffset":0,"speedGroup":0},{"isFakenote":false,"isSkynote":true,"skyjudgeNumber":1,"startJudgeTime":149.862,"xOffset":0,"speedGroup":0},{"isFakenote":false,"isSkynote":true,"skyjudgeNumber":1,"startJudgeTime":149.946,"xOffset":0,"speedGroup":0},{"isFakenote":false,"isSkynote":true,"skyjudgeNumber":1,"startJudgeTime":150.029,"xOffset":0,"speedGroup":0},{"isFakenote":false,"isSkynote":true,"skyjudgeNumber":1,"startJudgeTime":150.112,"xOffset":0,"speedGroup":0},{"isFakenote":false,"isSkynote":true,"skyjudgeNumber":1,"startJudgeTime":150.196,"xOffset":0,"speedGroup":0},{"isFakenote":false,"isSkynote":true,"skyjudgeNumber":1,"startJudgeTime":150.279,"xOffset":0,"speedGroup":0}]},{"isFakenote":false,"isSkynote":true,"skyjudgeNumber":2,"notetype":3,"startJudgeTime":149.362,"endJudgeTime":0.029,"xOffset":0,"speedGroup":0,"draginfolist":[{"isFakenote":false,"isSkynote":true,"skyjudgeNumber":2,"startJudgeTime":149.446,"xOffset":0,"speedGroup":0},{"isFakenote":false,"isSkynote":true,"skyjudgeNumber":2,"startJudgeTime":149.529,"xOffset":0,"speedGroup":0},{"isFakenote":false,"isSkynote":true,"skyjudgeNumber":2,"startJudgeTime":149.612,"xOffset":0,"speedGroup":0},{"isFakenote":false,"isSkynote":true,"skyjudgeNumber":2,"startJudgeTime":149.696,"xOffset":0,"speedGroup":0},{"isFakenote":false,"isSkynote":true,"skyjudgeNumber":2,"startJudgeTime":149.779,"xOffset":0,"speedGroup":0},{"isFakenote":false,"isSkynote":true,"skyjudgeNumber":2,"startJudgeTime":149.862,"xOffset":0,"speedGroup":0},{"isFakenote":false,"isSkynote":true,"skyjudgeNumber":2,"startJudgeTime":149.946,"xOffset":0,"speedGroup":0},{"isFakenote":false,"isSkynote":true,"skyjudgeNumber":2,"startJudgeTime":150.029,"xOffset":0,"speedGroup":0},{"isFakenote":false,"isSkynote":true,"skyjudgeNumber":2,"startJudgeTime":150.112,"xOffset":0,"speedGroup":0},{"isFakenote":false,"isSkynote":true,"skyjudgeNumber":2,"startJudgeTime":150.196,"xOffset":0,"speedGroup":0},{"isFakenote":false,"isSkynote":true,"skyjudgeNumber":2,"startJudgeTime":150.279,"xOffset":0,"speedGroup":0}]},{"isFakenote":false,"isSkynote":true,"skyjudgeNumber":1,"notetype":1,"startJudgeTime":150.362,"endJudgeTime":0.029,"xOffset":0,"speedGroup":2,"draginfolist":[]},{"isFakenote":false,"isSkynote":true,"skyjudgeNumber":2,"notetype":1,"startJudgeTime":150.362,"endJudgeTime":0.029,"xOffset":0,"speedGroup":2,"draginfolist":[]},{"isFakenote":false,"isSkynote":true,"skyjudgeNumber":2,"notetype":3,"startJudgeTime":132.029,"endJudgeTime":0.029,"xOffset":0,"speedGroup":0,"draginfolist":[{"isFakenote":false,"isSkynote":true,"skyjudgeNumber":2,"startJudgeTime":132.196,"xOffset":0,"speedGroup":0},{"isFakenote":false,"isSkynote":true,"skyjudgeNumber":2,"startJudgeTime":132.529,"xOffset":0,"speedGroup":0},{"isFakenote":false,"isSkynote":true,"skyjudgeNumber":2,"startJudgeTime":132.862,"xOffset":0,"speedGroup":0},{"isFakenote":false,"isSkynote":true,"skyjudgeNumber":2,"startJudgeTime":133.029,"xOffset":0,"speedGroup":0},{"isFakenote":false,"isSkynote":true,"skyjudgeNumber":2,"startJudgeTime":133.196,"xOffset":0,"speedGroup":0},{"isFakenote":false,"isSkynote":true,"skyjudgeNumber":2,"startJudgeTime":133.529,"xOffset":0,"speedGroup":0},{"isFakenote":false,"isSkynote":true,"skyjudgeNumber":2,"startJudgeTime":133.862,"xOffset":0,"speedGroup":0},{"isFakenote":false,"isSkynote":true,"skyjudgeNumber":2,"startJudgeTime":134.196,"xOffset":0,"speedGroup":0},{"isFakenote":false,"isSkynote":true,"skyjudgeNumber":2,"startJudgeTime":134.529,"xOffset":0,"speedGroup":0},{"isFakenote":false,"isSkynote":true,"skyjudgeNumber":2,"startJudgeTime":134.696,"xOffset":0,"speedGroup":0}]},{"isFakenote":false,"isSkynote":true,"skyjudgeNumber":3,"notetype":0,"startJudgeTime":145.362,"endJudgeTime":0.029,"xOffset":0,"speedGroup":0,"draginfolist":[]},{"isFakenote":false,"isSkynote":true,"skyjudgeNumber":4,"notetype":0,"startJudgeTime":145.696,"endJudgeTime":0.029,"xOffset":0,"speedGroup":0,"draginfolist":[]},{"isFakenote":false,"isSkynote":true,"skyjudgeNumber":4,"notetype":0,"startJudgeTime":146.362,"endJudgeTime":0.029,"xOffset":0,"speedGroup":0,"draginfolist":[]},{"isFakenote":false,"isSkynote":true,"skyjudgeNumber":3,"notetype":2,"startJudgeTime":65.362,"endJudgeTime":66.029,"xOffset":0,"speedGroup":0,"draginfolist":[]},{"isFakenote":false,"isSkynote":true,"skyjudgeNumber":3,"notetype":2,"startJudgeTime":71.529,"endJudgeTime":71.696,"xOffset":0,"speedGroup":0,"draginfolist":[]},{"isFakenote":false,"isSkynote":true,"skyjudgeNumber":3,"notetype":2,"startJudgeTime":72.196,"endJudgeTime":72.529,"xOffset":0,"speedGroup":0,"draginfolist":[]},{"isFakenote":false,"isSkynote":true,"skyjudgeNumber":3,"notetype":2,"startJudgeTime":73.362,"endJudgeTime":73.696,"xOffset":0,"speedGroup":0,"draginfolist":[]},{"isFakenote":false,"isSkynote":true,"skyjudgeNumber":1,"notetype":2,"startJudgeTime":74.362,"endJudgeTime":75.362,"xOffset":0,"speedGroup":0,"draginfolist":[]},{"isFakenote":false,"isSkynote":true,"skyjudgeNumber":3,"notetype":2,"startJudgeTime":77.862,"endJudgeTime":78.029,"xOffset":0,"speedGroup":0,"draginfolist":[]},{"isFakenote":false,"isSkynote":true,"skyjudgeNumber":1,"notetype":2,"startJudgeTime":80.196,"endJudgeTime":80.696,"xOffset":0,"speedGroup":0,"draginfolist":[]},{"isFakenote":false,"isSkynote":true,"skyjudgeNumber":3,"notetype":2,"startJudgeTime":82.529,"endJudgeTime":82.696,"xOffset":0,"speedGroup":0,"draginfolist":[]},{"isFakenote":false,"isSkynote":true,"skyjudgeNumber":4,"notetype":0,"startJudgeTime":65.362,"endJudgeTime":0.029,"xOffset":0,"speedGroup":0,"draginfolist":[]},{"isFakenote":false,"isSkynote":true,"skyjudgeNumber":4,"notetype":2,"startJudgeTime":66.196,"endJudgeTime":66.362,"xOffset":0,"speedGroup":0,"draginfolist":[]},{"isFakenote":false,"isSkynote":true,"skyjudgeNumber":4,"notetype":2,"startJudgeTime":67.529,"endJudgeTime":67.696,"xOffset":0,"speedGroup":0,"draginfolist":[]},{"isFakenote":false,"isSkynote":false,"skyjudgeNumber":0,"notetype":2,"startJudgeTime":67.862,"endJudgeTime":68.696,"xOffset":0.1,"speedGroup":0,"draginfolist":[]},{"isFakenote":false,"isSkynote":true,"skyjudgeNumber":4,"notetype":2,"startJudgeTime":68.862,"endJudgeTime":69.029,"xOffset":0,"speedGroup":0,"draginfolist":[]},{"isFakenote":false,"isSkynote":true,"skyjudgeNumber":3,"notetype":2,"startJudgeTime":69.196,"endJudgeTime":69.529,"xOffset":0,"speedGroup":0,"draginfolist":[]},{"isFakenote":false,"isSkynote":false,"skyjudgeNumber":0,"notetype":2,"startJudgeTime":70.196,"endJudgeTime":70.529,"xOffset":0.1,"speedGroup":0,"draginfolist":[]},{"isFakenote":false,"isSkynote":true,"skyjudgeNumber":4,"notetype":2,"startJudgeTime":69.696,"endJudgeTime":70.029,"xOffset":0,"speedGroup":0,"draginfolist":[]},{"isFakenote":false,"isSkynote":true,"skyjudgeNumber":2,"notetype":2,"startJudgeTime":70.696,"endJudgeTime":71.362,"xOffset":0,"speedGroup":0,"draginfolist":[]},{"isFakenote":false,"isSkynote":false,"skyjudgeNumber":0,"notetype":2,"startJudgeTime":71.862,"endJudgeTime":72.029,"xOffset":0.9,"speedGroup":0,"draginfolist":[]},{"isFakenote":false,"isSkynote":true,"skyjudgeNumber":2,"notetype":2,"startJudgeTime":72.696,"endJudgeTime":73.196,"xOffset":0,"speedGroup":0,"draginfolist":[]},{"isFakenote":false,"isSkynote":true,"skyjudgeNumber":4,"notetype":2,"startJudgeTime":73.862,"endJudgeTime":74.196,"xOffset":0,"speedGroup":0,"draginfolist":[]},{"isFakenote":false,"isSkynote":true,"skyjudgeNumber":4,"notetype":2,"startJudgeTime":76.029,"endJudgeTime":76.696,"xOffset":0,"speedGroup":0,"draginfolist":[]},{"isFakenote":false,"isSkynote":false,"skyjudgeNumber":0,"notetype":2,"startJudgeTime":76.862,"endJudgeTime":77.029,"xOffset":0.1,"speedGroup":0,"draginfolist":[]},{"isFakenote":false,"isSkynote":true,"skyjudgeNumber":2,"notetype":2,"startJudgeTime":77.196,"endJudgeTime":77.696,"xOffset":0,"speedGroup":0,"draginfolist":[]},{"isFakenote":false,"isSkynote":false,"skyjudgeNumber":0,"notetype":2,"startJudgeTime":78.196,"endJudgeTime":78.529,"xOffset":0.9,"speedGroup":0,"draginfolist":[]},{"isFakenote":false,"isSkynote":true,"skyjudgeNumber":4,"notetype":2,"startJudgeTime":79.529,"endJudgeTime":80.029,"xOffset":0,"speedGroup":0,"draginfolist":[]},{"isFakenote":false,"isSkynote":true,"skyjudgeNumber":4,"notetype":2,"startJudgeTime":80.862,"endJudgeTime":81.029,"xOffset":0,"speedGroup":0,"draginfolist":[]},{"isFakenote":false,"isSkynote":true,"skyjudgeNumber":3,"notetype":2,"startJudgeTime":81.196,"endJudgeTime":82.029,"xOffset":0,"speedGroup":0,"draginfolist":[]},{"isFakenote":false,"isSkynote":true,"skyjudgeNumber":4,"notetype":2,"startJudgeTime":82.196,"endJudgeTime":82.362,"xOffset":0,"speedGroup":0,"draginfolist":[]},{"isFakenote":false,"isSkynote":true,"skyjudgeNumber":3,"notetype":0,"startJudgeTime":147.696,"endJudgeTime":0.029,"xOffset":0,"speedGroup":0,"draginfolist":[]},{"isFakenote":false,"isSkynote":true,"skyjudgeNumber":4,"notetype":2,"startJudgeTime":53.362,"endJudgeTime":54.696,"xOffset":0,"speedGroup":0,"draginfolist":[]},{"isFakenote":false,"isSkynote":false,"skyjudgeNumber":0,"notetype":2,"startJudgeTime":48.029,"endJudgeTime":49.362,"xOffset":0.9,"speedGroup":0,"draginfolist":[]},{"isFakenote":false,"isSkynote":false,"skyjudgeNumber":0,"notetype":3,"startJudgeTime":62.696,"endJudgeTime":0.029,"xOffset":0.1,"speedGroup":0,"draginfolist":[{"isFakenote":false,"isSkynote":false,"skyjudgeNumber":0,"startJudgeTime":62.862,"xOffset":0.15,"speedGroup":0},{"isFakenote":false,"isSkynote":false,"skyjudgeNumber":0,"startJudgeTime":63.029,"xOffset":0.2,"speedGroup":0},{"isFakenote":false,"isSkynote":false,"skyjudgeNumber":0,"startJudgeTime":63.196,"xOffset":0.25,"speedGroup":0},{"isFakenote":false,"isSkynote":false,"skyjudgeNumber":0,"startJudgeTime":63.362,"xOffset":0.3,"speedGroup":0},{"isFakenote":false,"isSkynote":false,"skyjudgeNumber":0,"startJudgeTime":63.529,"xOffset":0.35,"speedGroup":0},{"isFakenote":false,"isSkynote":false,"skyjudgeNumber":0,"startJudgeTime":63.696,"xOffset":0.4,"speedGroup":0},{"isFakenote":false,"isSkynote":false,"skyjudgeNumber":0,"startJudgeTime":63.862,"xOffset":0.45,"speedGroup":0},{"isFakenote":false,"isSkynote":false,"skyjudgeNumber":0,"startJudgeTime":64.029,"xOffset":0.4,"speedGroup":0},{"isFakenote":false,"isSkynote":false,"skyjudgeNumber":0,"startJudgeTime":64.196,"xOffset":0.35,"speedGroup":0},{"isFakenote":false,"isSkynote":false,"skyjudgeNumber":0,"startJudgeTime":64.362,"xOffset":0.3,"speedGroup":0},{"isFakenote":false,"isSkynote":false,"skyjudgeNumber":0,"startJudgeTime":64.529,"xOffset":0.25,"speedGroup":0},{"isFakenote":false,"isSkynote":false,"skyjudgeNumber":0,"startJudgeTime":64.696,"xOffset":0.2,"speedGroup":0},{"isFakenote":false,"isSkynote":false,"skyjudgeNumber":0,"startJudgeTime":64.862,"xOffset":0.15,"speedGroup":0},{"isFakenote":false,"isSkynote":false,"skyjudgeNumber":0,"startJudgeTime":65.029,"xOffset":0.1,"speedGroup":0},{"isFakenote":false,"isSkynote":false,"skyjudgeNumber":0,"startJudgeTime":65.112,"xOffset":0.075,"speedGroup":0},{"isFakenote":false,"isSkynote":false,"skyjudgeNumber":0,"startJudgeTime":65.196,"xOffset":0.05,"speedGroup":0}]},{"isFakenote":false,"isSkynote":false,"skyjudgeNumber":0,"notetype":3,"startJudgeTime":104.862,"endJudgeTime":0.029,"xOffset":0.1,"speedGroup":0,"draginfolist":[{"isFakenote":false,"isSkynote":false,"skyjudgeNumber":0,"startJudgeTime":104.904,"xOffset":0.2,"speedGroup":0},{"isFakenote":false,"isSkynote":false,"skyjudgeNumber":0,"startJudgeTime":104.946,"xOffset":0.3,"speedGroup":0}]},{"isFakenote":false,"isSkynote":false,"skyjudgeNumber":0,"notetype":3,"startJudgeTime":105.196,"endJudgeTime":0.029,"xOffset":0.9,"speedGroup":0,"draginfolist":[{"isFakenote":false,"isSkynote":false,"skyjudgeNumber":0,"startJudgeTime":105.237,"xOffset":0.8,"speedGroup":0},{"isFakenote":false,"isSkynote":false,"skyjudgeNumber":0,"startJudgeTime":105.279,"xOffset":0.7,"speedGroup":0}]},{"isFakenote":false,"isSkynote":true,"skyjudgeNumber":4,"notetype":0,"startJudgeTime":33.362,"endJudgeTime":0.029,"xOffset":0,"speedGroup":0,"draginfolist":[]},{"isFakenote":false,"isSkynote":true,"skyjudgeNumber":4,"notetype":3,"startJudgeTime":33.529,"endJudgeTime":0.029,"xOffset":0,"speedGroup":0,"draginfolist":[]},{"isFakenote":false,"isSkynote":true,"skyjudgeNumber":4,"notetype":3,"startJudgeTime":33.696,"endJudgeTime":0.029,"xOffset":0,"speedGroup":0,"draginfolist":[]},{"isFakenote":false,"isSkynote":true,"skyjudgeNumber":4,"notetype":3,"startJudgeTime":33.862,"endJudgeTime":0.029,"xOffset":0,"speedGroup":0,"draginfolist":[]},{"isFakenote":false,"isSkynote":true,"skyjudgeNumber":3,"notetype":3,"startJudgeTime":34.362,"endJudgeTime":0.029,"xOffset":0,"speedGroup":0,"draginfolist":[]},{"isFakenote":false,"isSkynote":true,"skyjudgeNumber":3,"notetype":0,"startJudgeTime":34.196,"endJudgeTime":0.029,"xOffset":0,"speedGroup":0,"draginfolist":[]},{"isFakenote":false,"isSkynote":true,"skyjudgeNumber":3,"notetype":3,"startJudgeTime":34.529,"endJudgeTime":0.029,"xOffset":0,"speedGroup":0,"draginfolist":[]},{"isFakenote":false,"isSkynote":false,"skyjudgeNumber":0,"notetype":0,"startJudgeTime":34.862,"endJudgeTime":0.029,"xOffset":0.9,"speedGroup":0,"draginfolist":[]},{"isFakenote":false,"isSkynote":false,"skyjudgeNumber":0,"notetype":0,"startJudgeTime":35.196,"endJudgeTime":0.029,"xOffset":0.1,"speedGroup":0,"draginfolist":[]},{"isFakenote":false,"isSkynote":false,"skyjudgeNumber":0,"notetype":3,"startJudgeTime":35.529,"endJudgeTime":0.029,"xOffset":0.85,"speedGroup":0,"draginfolist":[]},{"isFakenote":false,"isSkynote":false,"skyjudgeNumber":0,"notetype":3,"startJudgeTime":35.696,"endJudgeTime":0.029,"xOffset":0.6,"speedGroup":0,"draginfolist":[]},{"isFakenote":false,"isSkynote":false,"skyjudgeNumber":0,"notetype":3,"startJudgeTime":35.862,"endJudgeTime":0.029,"xOffset":0.35,"speedGroup":0,"draginfolist":[]},{"isFakenote":false,"isSkynote":true,"skyjudgeNumber":3,"notetype":3,"startJudgeTime":36.362,"endJudgeTime":0.029,"xOffset":0,"speedGroup":0,"draginfolist":[]},{"isFakenote":false,"isSkynote":true,"skyjudgeNumber":3,"notetype":3,"startJudgeTime":36.529,"endJudgeTime":0.029,"xOffset":0,"speedGroup":0,"draginfolist":[]},{"isFakenote":false,"isSkynote":true,"skyjudgeNumber":4,"notetype":0,"startJudgeTime":36.862,"endJudgeTime":0.029,"xOffset":0,"speedGroup":0,"draginfolist":[]},{"isFakenote":false,"isSkynote":true,"skyjudgeNumber":4,"notetype":3,"startJudgeTime":37.029,"endJudgeTime":0.029,"xOffset":0,"speedGroup":0,"draginfolist":[]},{"isFakenote":false,"isSkynote":true,"skyjudgeNumber":4,"notetype":3,"startJudgeTime":37.196,"endJudgeTime":0.029,"xOffset":0,"speedGroup":0,"draginfolist":[{"isFakenote":false,"isSkynote":false,"skyjudgeNumber":0,"startJudgeTime":38.529,"xOffset":0.6,"speedGroup":0}]},{"isFakenote":false,"isSkynote":true,"skyjudgeNumber":3,"notetype":0,"startJudgeTime":38.529,"endJudgeTime":0.029,"xOffset":0,"speedGroup":0,"draginfolist":[]},{"isFakenote":false,"isSkynote":true,"skyjudgeNumber":3,"notetype":3,"startJudgeTime":39.029,"endJudgeTime":0.029,"xOffset":0,"speedGroup":0,"draginfolist":[]},{"isFakenote":false,"isSkynote":true,"skyjudgeNumber":3,"notetype":3,"startJudgeTime":39.196,"endJudgeTime":0.029,"xOffset":0,"speedGroup":0,"draginfolist":[]},{"isFakenote":false,"isSkynote":true,"skyjudgeNumber":4,"notetype":3,"startJudgeTime":39.696,"endJudgeTime":0.029,"xOffset":0,"speedGroup":0,"draginfolist":[]},{"isFakenote":false,"isSkynote":true,"skyjudgeNumber":4,"notetype":3,"startJudgeTime":39.862,"endJudgeTime":0.029,"xOffset":0,"speedGroup":0,"draginfolist":[]},{"isFakenote":false,"isSkynote":true,"skyjudgeNumber":4,"notetype":0,"startJudgeTime":39.529,"endJudgeTime":0.029,"xOffset":0,"speedGroup":0,"draginfolist":[]},{"isFakenote":false,"isSkynote":false,"skyjudgeNumber":0,"notetype":0,"startJudgeTime":40.196,"endJudgeTime":0.029,"xOffset":0.1,"speedGroup":0,"draginfolist":[]},{"isFakenote":false,"isSkynote":false,"skyjudgeNumber":0,"notetype":3,"startJudgeTime":40.362,"endJudgeTime":0.029,"xOffset":0.3,"speedGroup":0,"draginfolist":[]},{"isFakenote":false,"isSkynote":false,"skyjudgeNumber":0,"notetype":3,"startJudgeTime":40.529,"endJudgeTime":0.029,"xOffset":0.5,"speedGroup":0,"draginfolist":[]},{"isFakenote":false,"isSkynote":false,"skyjudgeNumber":0,"notetype":0,"startJudgeTime":40.862,"endJudgeTime":0.029,"xOffset":0.9,"speedGroup":0,"draginfolist":[]},{"isFakenote":false,"isSkynote":false,"skyjudgeNumber":0,"notetype":3,"startJudgeTime":41.029,"endJudgeTime":0.029,"xOffset":0.7,"speedGroup":0,"draginfolist":[]},{"isFakenote":false,"isSkynote":false,"skyjudgeNumber":0,"notetype":3,"startJudgeTime":41.196,"endJudgeTime":0.029,"xOffset":0.5,"speedGroup":0,"draginfolist":[]},{"isFakenote":false,"isSkynote":true,"skyjudgeNumber":3,"notetype":0,"startJudgeTime":38.862,"endJudgeTime":0.029,"xOffset":0,"speedGroup":0,"draginfolist":[]},{"isFakenote":false,"isSkynote":true,"skyjudgeNumber":3,"notetype":0,"startJudgeTime":41.362,"endJudgeTime":0.029,"xOffset":0,"speedGroup":0,"draginfolist":[]},{"isFakenote":false,"isSkynote":true,"skyjudgeNumber":3,"notetype":3,"startJudgeTime":41.529,"endJudgeTime":0.029,"xOffset":0,"speedGroup":0,"draginfolist":[]},{"isFakenote":false,"isSkynote":true,"skyjudgeNumber":4,"notetype":0,"startJudgeTime":41.696,"endJudgeTime":0.029,"xOffset":0,"speedGroup":0,"draginfolist":[]},{"isFakenote":false,"isSkynote":true,"skyjudgeNumber":4,"notetype":3,"startJudgeTime":41.862,"endJudgeTime":0.029,"xOffset":0,"speedGroup":0,"draginfolist":[]},{"isFakenote":false,"isSkynote":false,"skyjudgeNumber":0,"notetype":0,"startJudgeTime":42.196,"endJudgeTime":0.029,"xOffset":0.1,"speedGroup":0,"draginfolist":[]},{"isFakenote":false,"isSkynote":false,"skyjudgeNumber":0,"notetype":3,"startJudgeTime":42.362,"endJudgeTime":0.029,"xOffset":0.3,"speedGroup":0,"draginfolist":[]},{"isFakenote":false,"isSkynote":false,"skyjudgeNumber":0,"notetype":3,"startJudgeTime":42.529,"endJudgeTime":0.029,"xOffset":0.5,"speedGroup":0,"draginfolist":[]},{"isFakenote":false,"isSkynote":false,"skyjudgeNumber":0,"notetype":3,"startJudgeTime":42.696,"endJudgeTime":0.029,"xOffset":0.7,"speedGroup":0,"draginfolist":[]},{"isFakenote":false,"isSkynote":true,"skyjudgeNumber":1,"notetype":2,"startJudgeTime":78.696,"endJudgeTime":79.196,"xOffset":0,"speedGroup":0,"draginfolist":[]},{"isFakenote":false,"isSkynote":true,"skyjudgeNumber":1,"notetype":2,"startJudgeTime":66.529,"endJudgeTime":67.362,"xOffset":0,"speedGroup":0,"draginfolist":[]},{"isFakenote":false,"isSkynote":true,"skyjudgeNumber":3,"notetype":0,"startJudgeTime":124.029,"endJudgeTime":0.029,"xOffset":0,"speedGroup":0,"draginfolist":[]},{"isFakenote":false,"isSkynote":true,"skyjudgeNumber":3,"notetype":0,"startJudgeTime":124.696,"endJudgeTime":0.029,"xOffset":0,"speedGroup":0,"draginfolist":[]},{"isFakenote":false,"isSkynote":true,"skyjudgeNumber":3,"notetype":0,"startJudgeTime":125.029,"endJudgeTime":0.029,"xOffset":0,"speedGroup":0,"draginfolist":[]},{"isFakenote":false,"isSkynote":true,"skyjudgeNumber":2,"notetype":1,"startJudgeTime":125.029,"endJudgeTime":0.029,"xOffset":0,"speedGroup":0,"draginfolist":[]},{"isFakenote":false,"isSkynote":true,"skyjudgeNumber":1,"notetype":1,"startJudgeTime":125.696,"endJudgeTime":0.029,"xOffset":0,"speedGroup":0,"draginfolist":[]},{"isFakenote":false,"isSkynote":true,"skyjudgeNumber":4,"notetype":0,"startJudgeTime":125.696,"endJudgeTime":0.029,"xOffset":0,"speedGroup":0,"draginfolist":[]},{"isFakenote":false,"isSkynote":true,"skyjudgeNumber":1,"notetype":3,"startJudgeTime":134.696,"endJudgeTime":0.029,"xOffset":0,"speedGroup":0,"draginfolist":[{"isFakenote":false,"isSkynote":true,"skyjudgeNumber":1,"startJudgeTime":135.196,"xOffset":0,"speedGroup":0},{"isFakenote":false,"isSkynote":true,"skyjudgeNumber":1,"startJudgeTime":135.862,"xOffset":0,"speedGroup":0},{"isFakenote":false,"isSkynote":true,"skyjudgeNumber":1,"startJudgeTime":136.196,"xOffset":0,"speedGroup":0},{"isFakenote":false,"isSkynote":true,"skyjudgeNumber":1,"startJudgeTime":136.529,"xOffset":0,"speedGroup":0},{"isFakenote":false,"isSkynote":true,"skyjudgeNumber":1,"startJudgeTime":136.862,"xOffset":0,"speedGroup":0},{"isFakenote":false,"isSkynote":true,"skyjudgeNumber":1,"startJudgeTime":137.196,"xOffset":0,"speedGroup":0},{"isFakenote":false,"isSkynote":true,"skyjudgeNumber":1,"startJudgeTime":137.362,"xOffset":0,"speedGroup":0}]},{"isFakenote":false,"isSkynote":true,"skyjudgeNumber":1,"notetype":3,"startJudgeTime":140.029,"endJudgeTime":0.029,"xOffset":0,"speedGroup":0,"draginfolist":[{"isFakenote":false,"isSkynote":true,"skyjudgeNumber":1,"startJudgeTime":140.696,"xOffset":0,"speedGroup":0},{"isFakenote":false,"isSkynote":true,"skyjudgeNumber":1,"startJudgeTime":140.862,"xOffset":0,"speedGroup":0},{"isFakenote":false,"isSkynote":true,"skyjudgeNumber":1,"startJudgeTime":141.029,"xOffset":0,"speedGroup":0},{"isFakenote":false,"isSkynote":true,"skyjudgeNumber":1,"startJudgeTime":141.196,"xOffset":0,"speedGroup":0},{"isFakenote":false,"isSkynote":true,"skyjudgeNumber":1,"startJudgeTime":142.362,"xOffset":0,"speedGroup":0},{"isFakenote":false,"isSkynote":true,"skyjudgeNumber":1,"startJudgeTime":142.529,"xOffset":0,"speedGroup":0},{"isFakenote":false,"isSkynote":true,"skyjudgeNumber":1,"startJudgeTime":142.696,"xOffset":0,"speedGroup":0}]},{"isFakenote":false,"isSkynote":true,"skyjudgeNumber":2,"notetype":3,"startJudgeTime":142.696,"endJudgeTime":0.029,"xOffset":0,"speedGroup":0,"draginfolist":[{"isFakenote":false,"isSkynote":true,"skyjudgeNumber":2,"startJudgeTime":143.196,"xOffset":0,"speedGroup":0},{"isFakenote":false,"isSkynote":true,"skyjudgeNumber":2,"startJudgeTime":143.862,"xOffset":0,"speedGroup":0},{"isFakenote":false,"isSkynote":true,"skyjudgeNumber":2,"startJudgeTime":144.529,"xOffset":0,"speedGroup":0},{"isFakenote":false,"isSkynote":true,"skyjudgeNumber":2,"startJudgeTime":145.029,"xOffset":0,"speedGroup":0},{"isFakenote":false,"isSkynote":true,"skyjudgeNumber":2,"startJudgeTime":145.112,"xOffset":0,"speedGroup":0},{"isFakenote":false,"isSkynote":true,"skyjudgeNumber":2,"startJudgeTime":145.196,"xOffset":0,"speedGroup":0},{"isFakenote":false,"isSkynote":true,"skyjudgeNumber":2,"startJudgeTime":145.279,"xOffset":0,"speedGroup":0},{"isFakenote":false,"isSkynote":true,"skyjudgeNumber":2,"startJudgeTime":145.362,"xOffset":0,"speedGroup":0}]},{"isFakenote":false,"isSkynote":true,"skyjudgeNumber":3,"notetype":0,"startJudgeTime":146.029,"endJudgeTime":0.029,"xOffset":0,"speedGroup":0,"draginfolist":[]},{"isFakenote":false,"isSkynote":true,"skyjudgeNumber":3,"notetype":0,"startJudgeTime":146.529,"endJudgeTime":0.029,"xOffset":0,"speedGroup":0,"draginfolist":[]},{"isFakenote":false,"isSkynote":true,"skyjudgeNumber":4,"notetype":0,"startJudgeTime":147.362,"endJudgeTime":0.029,"xOffset":0,"speedGroup":0,"draginfolist":[]},{"isFakenote":false,"isSkynote":true,"skyjudgeNumber":4,"notetype":1,"startJudgeTime":119.029,"endJudgeTime":0.029,"xOffset":0,"speedGroup":0,"draginfolist":[]},{"isFakenote":false,"isSkynote":true,"skyjudgeNumber":3,"notetype":1,"startJudgeTime":121.696,"endJudgeTime":0.029,"xOffset":0,"speedGroup":0,"draginfolist":[]},{"isFakenote":false,"isSkynote":true,"skyjudgeNumber":4,"notetype":0,"startJudgeTime":146.696,"endJudgeTime":0.029,"xOffset":0,"speedGroup":0,"draginfolist":[]},{"isFakenote":false,"isSkynote":true,"skyjudgeNumber":3,"notetype":0,"startJudgeTime":147.029,"endJudgeTime":0.029,"xOffset":0,"speedGroup":0,"draginfolist":[]},{"isFakenote":false,"isSkynote":false,"skyjudgeNumber":0,"notetype":3,"startJudgeTime":84.029,"endJudgeTime":0.029,"xOffset":0.6,"speedGroup":0,"draginfolist":[{"isFakenote":false,"isSkynote":false,"skyjudgeNumber":0,"startJudgeTime":84.529,"xOffset":0.4,"speedGroup":0},{"isFakenote":false,"isSkynote":false,"skyjudgeNumber":0,"startJudgeTime":85.029,"xOffset":0.2,"speedGroup":0}]},{"isFakenote":false,"isSkynote":true,"skyjudgeNumber":3,"notetype":3,"startJudgeTime":36.196,"endJudgeTime":0.029,"xOffset":0,"speedGroup":0,"draginfolist":[]},{"isFakenote":false,"isSkynote":true,"skyjudgeNumber":3,"notetype":0,"startJudgeTime":36.029,"endJudgeTime":0.029,"xOffset":0,"speedGroup":0,"draginfolist":[]},{"isFakenote":false,"isSkynote":false,"skyjudgeNumber":0,"notetype":3,"startJudgeTime":43.196,"endJudgeTime":0.029,"xOffset":0.1,"speedGroup":0,"draginfolist":[]},{"isFakenote":false,"isSkynote":true,"skyjudgeNumber":3,"notetype":3,"startJudgeTime":86.696,"endJudgeTime":0.029,"xOffset":0,"speedGroup":0,"draginfolist":[{"isFakenote":false,"isSkynote":false,"skyjudgeNumber":0,"startJudgeTime":88.029,"xOffset":0,"speedGroup":0}]},{"isFakenote":false,"isSkynote":true,"skyjudgeNumber":4,"notetype":3,"startJudgeTime":88.029,"endJudgeTime":0.029,"xOffset":0,"speedGroup":0,"draginfolist":[{"isFakenote":false,"isSkynote":false,"skyjudgeNumber":0,"startJudgeTime":89.362,"xOffset":1,"speedGroup":0}]},{"isFakenote":false,"isSkynote":true,"skyjudgeNumber":3,"notetype":3,"startJudgeTime":89.362,"endJudgeTime":0.029,"xOffset":0,"speedGroup":0,"draginfolist":[{"isFakenote":false,"isSkynote":false,"skyjudgeNumber":0,"startJudgeTime":90.696,"xOffset":0.3,"speedGroup":0}]},{"isFakenote":false,"isSkynote":true,"skyjudgeNumber":4,"notetype":3,"startJudgeTime":90.696,"endJudgeTime":0.029,"xOffset":0,"speedGroup":0,"draginfolist":[{"isFakenote":false,"isSkynote":false,"skyjudgeNumber":0,"startJudgeTime":92.029,"xOffset":0.7,"speedGroup":0}]},{"isFakenote":false,"isSkynote":true,"skyjudgeNumber":3,"notetype":3,"startJudgeTime":92.029,"endJudgeTime":0.029,"xOffset":0,"speedGroup":0,"draginfolist":[{"isFakenote":false,"isSkynote":false,"skyjudgeNumber":0,"startJudgeTime":93.362,"xOffset":0.5,"speedGroup":0}]},{"isFakenote":false,"isSkynote":true,"skyjudgeNumber":4,"notetype":3,"startJudgeTime":93.362,"endJudgeTime":0.029,"xOffset":0,"speedGroup":0,"draginfolist":[{"isFakenote":false,"isSkynote":false,"skyjudgeNumber":0,"startJudgeTime":94.696,"xOffset":0.5,"speedGroup":0}]},{"isFakenote":false,"isSkynote":true,"skyjudgeNumber":3,"notetype":3,"startJudgeTime":94.696,"endJudgeTime":0.029,"xOffset":0,"speedGroup":0,"draginfolist":[{"isFakenote":false,"isSkynote":false,"skyjudgeNumber":0,"startJudgeTime":96.029,"xOffset":0.6,"speedGroup":0},{"isFakenote":false,"isSkynote":true,"skyjudgeNumber":1,"startJudgeTime":97.362,"xOffset":0,"speedGroup":0}]},{"isFakenote":false,"isSkynote":true,"skyjudgeNumber":2,"notetype":3,"startJudgeTime":97.362,"endJudgeTime":0.029,"xOffset":0,"speedGroup":0,"draginfolist":[{"isFakenote":false,"isSkynote":false,"skyjudgeNumber":0,"startJudgeTime":98.696,"xOffset":1,"speedGroup":0}]},{"isFakenote":false,"isSkynote":true,"skyjudgeNumber":1,"notetype":3,"startJudgeTime":98.696,"endJudgeTime":0.029,"xOffset":0,"speedGroup":0,"draginfolist":[{"isFakenote":false,"isSkynote":false,"skyjudgeNumber":0,"startJudgeTime":100.029,"xOffset":0,"speedGroup":0}]},{"isFakenote":false,"isSkynote":true,"skyjudgeNumber":2,"notetype":3,"startJudgeTime":100.029,"endJudgeTime":0.029,"xOffset":0,"speedGroup":0,"draginfolist":[{"isFakenote":false,"isSkynote":false,"skyjudgeNumber":0,"startJudgeTime":101.362,"xOffset":0.7,"speedGroup":0}]},{"isFakenote":false,"isSkynote":true,"skyjudgeNumber":1,"notetype":3,"startJudgeTime":101.362,"endJudgeTime":0.029,"xOffset":0,"speedGroup":0,"draginfolist":[{"isFakenote":false,"isSkynote":false,"skyjudgeNumber":0,"startJudgeTime":102.696,"xOffset":0.3,"speedGroup":0}]},{"isFakenote":false,"isSkynote":true,"skyjudgeNumber":4,"notetype":3,"startJudgeTime":137.362,"endJudgeTime":0.029,"xOffset":0,"speedGroup":0,"draginfolist":[{"isFakenote":false,"isSkynote":true,"skyjudgeNumber":2,"startJudgeTime":138.029,"xOffset":0,"speedGroup":0},{"isFakenote":false,"isSkynote":true,"skyjudgeNumber":4,"startJudgeTime":139.362,"xOffset":0,"speedGroup":0}]},{"isFakenote":false,"isSkynote":true,"skyjudgeNumber":4,"notetype":3,"startJudgeTime":139.529,"endJudgeTime":0.029,"xOffset":0,"speedGroup":0,"draginfolist":[]},{"isFakenote":false,"isSkynote":true,"skyjudgeNumber":4,"notetype":3,"startJudgeTime":139.696,"endJudgeTime":0.029,"xOffset":0,"speedGroup":0,"draginfolist":[]},{"isFakenote":false,"isSkynote":true,"skyjudgeNumber":4,"notetype":3,"startJudgeTime":139.862,"endJudgeTime":0.029,"xOffset":0,"speedGroup":0,"draginfolist":[]},{"isFakenote":false,"isSkynote":true,"skyjudgeNumber":4,"notetype":3,"startJudgeTime":139.904,"endJudgeTime":0.029,"xOffset":0,"speedGroup":0,"draginfolist":[]},{"isFakenote":false,"isSkynote":true,"skyjudgeNumber":4,"notetype":3,"startJudgeTime":139.946,"endJudgeTime":0.029,"xOffset":0,"speedGroup":0,"draginfolist":[]},{"isFakenote":false,"isSkynote":true,"skyjudgeNumber":4,"notetype":3,"startJudgeTime":139.987,"endJudgeTime":0.029,"xOffset":0,"speedGroup":0,"draginfolist":[]},{"isFakenote":false,"isSkynote":true,"skyjudgeNumber":3,"notetype":3,"startJudgeTime":118.362,"endJudgeTime":0.029,"xOffset":0,"speedGroup":0,"draginfolist":[]},{"isFakenote":false,"isSkynote":true,"skyjudgeNumber":3,"notetype":3,"startJudgeTime":118.529,"endJudgeTime":0.029,"xOffset":0,"speedGroup":0,"draginfolist":[]},{"isFakenote":false,"isSkynote":true,"skyjudgeNumber":3,"notetype":3,"startJudgeTime":118.571,"endJudgeTime":0.029,"xOffset":0,"speedGroup":0,"draginfolist":[]},{"isFakenote":false,"isSkynote":true,"skyjudgeNumber":3,"notetype":3,"startJudgeTime":118.612,"endJudgeTime":0.029,"xOffset":0,"speedGroup":0,"draginfolist":[]},{"isFakenote":false,"isSkynote":true,"skyjudgeNumber":3,"notetype":3,"startJudgeTime":118.654,"endJudgeTime":0.029,"xOffset":0,"speedGroup":0,"draginfolist":[]},{"isFakenote":false,"isSkynote":true,"skyjudgeNumber":3,"notetype":3,"startJudgeTime":118.696,"endJudgeTime":0.029,"xOffset":0,"speedGroup":0,"draginfolist":[]}],"speedGroupInGames":[{"speedGroupNumber":0,"time":[0.029,21.362,21.362,22.696,103.696,106.362,106.696,107.696,126.696,129.029,129.362,148.029,150.362,114514],"speed":[10,10,-5,10,10,10,10,10,10,20,10,10,20,20]},{"speedGroupNumber":1,"time":[0.029,101.862,105.362,106.696,107.696,114514],"speed":[10,10,10,15,20,20]},{"speedGroupNumber":2,"time":[0.029,104.029,106.696,106.696,108.029,108.196,108.196,128.029,128.029,129.696,129.696,149.362,149.362,150.362,114514],"speed":[10,-100,-100,-10,10,10,-100,-100,-10,10,-100,-100,-30,30,30]},{"speedGroupNumber":3,"time":[0.029,84.029,84.029,84.529,84.529,85.029,85.029,86.696,114514],"speed":[10,-100,-17.037078857421875,5,-10,5,-10,11,11]}]}