{"chartInfos":{"levelName":"Don't stop","bpm":"174","composer":"izumu_ku","designer":"TetraCepra vs L.m.n.v","level":"FL","chartID":"10306"},"noteLists":[{"isFakenote":false,"isSkynote":true,"skyjudgeNumber":2,"notetype":0,"startJudgeTime":1.408,"endJudgeTime":0.029,"xOffset":0,"speedGroup":0,"draginfolist":[]},{"isFakenote":false,"isSkynote":true,"skyjudgeNumber":1,"notetype":3,"startJudgeTime":2.098,"endJudgeTime":0.029,"xOffset":0,"speedGroup":0,"draginfolist":[{"isFakenote":false,"isSkynote":true,"skyjudgeNumber":3,"startJudgeTime":2.27,"xOffset":0,"speedGroup":0},{"isFakenote":false,"isSkynote":true,"skyjudgeNumber":3,"startJudgeTime":2.443,"xOffset":0,"speedGroup":0},{"isFakenote":false,"isSkynote":true,"skyjudgeNumber":3,"startJudgeTime":2.615,"xOffset":0,"speedGroup":0}]},{"isFakenote":false,"isSkynote":false,"skyjudgeNumber":0,"notetype":3,"startJudgeTime":2.788,"endJudgeTime":0.029,"xOffset":1,"speedGroup":0,"draginfolist":[{"isFakenote":false,"isSkynote":true,"skyjudgeNumber":4,"startJudgeTime":3.305,"xOffset":0,"speedGroup":0}]},{"isFakenote":false,"isSkynote":false,"skyjudgeNumber":0,"notetype":3,"startJudgeTime":3.65,"endJudgeTime":0.029,"xOffset":0,"speedGroup":0,"draginfolist":[{"isFakenote":false,"isSkynote":true,"skyjudgeNumber":3,"startJudgeTime":3.822,"xOffset":0,"speedGroup":0},{"isFakenote":false,"isSkynote":true,"skyjudgeNumber":3,"startJudgeTime":3.995,"xOffset":0,"speedGroup":0}]},{"isFakenote":false,"isSkynote":true,"skyjudgeNumber":4,"notetype":3,"startJudgeTime":1.753,"endJudgeTime":0.029,"xOffset":0,"speedGroup":0,"draginfolist":[{"isFakenote":false,"isSkynote":true,"skyjudgeNumber":4,"startJudgeTime":1.926,"xOffset":0,"speedGroup":0}]},{"isFakenote":false,"isSkynote":true,"skyjudgeNumber":4,"notetype":3,"startJudgeTime":4.857,"endJudgeTime":0.029,"xOffset":0,"speedGroup":0,"draginfolist":[{"isFakenote":false,"isSkynote":true,"skyjudgeNumber":2,"startJudgeTime":5.029,"xOffset":0,"speedGroup":0},{"isFakenote":false,"isSkynote":true,"skyjudgeNumber":2,"startJudgeTime":5.201,"xOffset":0,"speedGroup":0},{"isFakenote":false,"isSkynote":true,"skyjudgeNumber":2,"startJudgeTime":5.374,"xOffset":0,"speedGroup":0}]},{"isFakenote":false,"isSkynote":true,"skyjudgeNumber":3,"notetype":3,"startJudgeTime":5.546,"endJudgeTime":0.029,"xOffset":0,"speedGroup":0,"draginfolist":[{"isFakenote":false,"isSkynote":false,"skyjudgeNumber":0,"startJudgeTime":6.063,"xOffset":0,"speedGroup":0}]},{"isFakenote":false,"isSkynote":true,"skyjudgeNumber":4,"notetype":3,"startJudgeTime":6.236,"endJudgeTime":0.029,"xOffset":0,"speedGroup":0,"draginfolist":[{"isFakenote":false,"isSkynote":false,"skyjudgeNumber":0,"startJudgeTime":6.408,"xOffset":1,"speedGroup":0},{"isFakenote":false,"isSkynote":false,"skyjudgeNumber":0,"startJudgeTime":6.581,"xOffset":1,"speedGroup":0},{"isFakenote":false,"isSkynote":false,"skyjudgeNumber":0,"startJudgeTime":6.753,"xOffset":1,"speedGroup":0}]},{"isFakenote":false,"isSkynote":true,"skyjudgeNumber":2,"notetype":3,"startJudgeTime":7.615,"endJudgeTime":0.029,"xOffset":0,"speedGroup":0,"draginfolist":[{"isFakenote":false,"isSkynote":true,"skyjudgeNumber":4,"startJudgeTime":7.788,"xOffset":0,"speedGroup":0},{"isFakenote":false,"isSkynote":true,"skyjudgeNumber":4,"startJudgeTime":7.96,"xOffset":0,"speedGroup":0},{"isFakenote":false,"isSkynote":true,"skyjudgeNumber":4,"startJudgeTime":8.132,"xOffset":0,"speedGroup":0}]},{"isFakenote":false,"isSkynote":false,"skyjudgeNumber":0,"notetype":3,"startJudgeTime":8.305,"endJudgeTime":0.029,"xOffset":0,"speedGroup":0,"draginfolist":[{"isFakenote":false,"isSkynote":true,"skyjudgeNumber":3,"startJudgeTime":8.822,"xOffset":0,"speedGroup":0}]},{"isFakenote":false,"isSkynote":false,"skyjudgeNumber":0,"notetype":3,"startJudgeTime":9.167,"endJudgeTime":0.029,"xOffset":1,"speedGroup":0,"draginfolist":[{"isFakenote":false,"isSkynote":true,"skyjudgeNumber":4,"startJudgeTime":9.512,"xOffset":0,"speedGroup":0},{"isFakenote":false,"isSkynote":true,"skyjudgeNumber":2,"startJudgeTime":10.029,"xOffset":0,"speedGroup":0}]},{"isFakenote":false,"isSkynote":true,"skyjudgeNumber":3,"notetype":3,"startJudgeTime":10.374,"endJudgeTime":0.029,"xOffset":0,"speedGroup":0,"draginfolist":[{"isFakenote":false,"isSkynote":true,"skyjudgeNumber":1,"startJudgeTime":10.719,"xOffset":0,"speedGroup":0},{"isFakenote":false,"isSkynote":true,"skyjudgeNumber":1,"startJudgeTime":10.891,"xOffset":0,"speedGroup":0},{"isFakenote":false,"isSkynote":true,"skyjudgeNumber":1,"startJudgeTime":10.977,"xOffset":0,"speedGroup":0}]},{"isFakenote":false,"isSkynote":true,"skyjudgeNumber":3,"notetype":3,"startJudgeTime":11.753,"endJudgeTime":0.029,"xOffset":0,"speedGroup":0,"draginfolist":[{"isFakenote":false,"isSkynote":false,"skyjudgeNumber":0,"startJudgeTime":11.926,"xOffset":0,"speedGroup":0},{"isFakenote":false,"isSkynote":false,"skyjudgeNumber":0,"startJudgeTime":12.012,"xOffset":0,"speedGroup":0},{"isFakenote":false,"isSkynote":false,"skyjudgeNumber":0,"startJudgeTime":12.098,"xOffset":0,"speedGroup":0},{"isFakenote":false,"isSkynote":false,"skyjudgeNumber":0,"startJudgeTime":12.27,"xOffset":0,"speedGroup":0}]},{"isFakenote":false,"isSkynote":true,"skyjudgeNumber":4,"notetype":3,"startJudgeTime":11.063,"endJudgeTime":0.029,"xOffset":0,"speedGroup":0,"draginfolist":[{"isFakenote":false,"isSkynote":false,"skyjudgeNumber":0,"startJudgeTime":11.581,"xOffset":1,"speedGroup":0}]},{"isFakenote":false,"isSkynote":true,"skyjudgeNumber":4,"notetype":2,"startJudgeTime":12.443,"endJudgeTime":13.132,"xOffset":0,"speedGroup":0,"draginfolist":[]},{"isFakenote":false,"isSkynote":true,"skyjudgeNumber":4,"notetype":3,"startJudgeTime":13.132,"endJudgeTime":0.029,"xOffset":0,"speedGroup":0,"draginfolist":[{"isFakenote":false,"isSkynote":true,"skyjudgeNumber":2,"startJudgeTime":13.822,"xOffset":0,"speedGroup":0},{"isFakenote":false,"isSkynote":true,"skyjudgeNumber":4,"startJudgeTime":14.512,"xOffset":0,"speedGroup":0}]},{"isFakenote":false,"isSkynote":false,"skyjudgeNumber":0,"notetype":3,"startJudgeTime":12.443,"endJudgeTime":0.029,"xOffset":0,"speedGroup":0,"draginfolist":[{"isFakenote":false,"isSkynote":false,"skyjudgeNumber":0,"startJudgeTime":12.615,"xOffset":0,"speedGroup":0},{"isFakenote":false,"isSkynote":false,"skyjudgeNumber":0,"startJudgeTime":12.788,"xOffset":0,"speedGroup":0},{"isFakenote":false,"isSkynote":true,"skyjudgeNumber":3,"startJudgeTime":12.96,"xOffset":0,"speedGroup":0},{"isFakenote":false,"isSkynote":true,"skyjudgeNumber":1,"startJudgeTime":13.132,"xOffset":0,"speedGroup":0},{"isFakenote":false,"isSkynote":true,"skyjudgeNumber":1,"startJudgeTime":13.305,"xOffset":0,"speedGroup":0},{"isFakenote":false,"isSkynote":true,"skyjudgeNumber":3,"startJudgeTime":13.477,"xOffset":0,"speedGroup":0},{"isFakenote":false,"isSkynote":true,"skyjudgeNumber":3,"startJudgeTime":13.65,"xOffset":0,"speedGroup":0},{"isFakenote":false,"isSkynote":false,"skyjudgeNumber":0,"startJudgeTime":13.822,"xOffset":0,"speedGroup":0},{"isFakenote":false,"isSkynote":false,"skyjudgeNumber":0,"startJudgeTime":14.339,"xOffset":0,"speedGroup":0},{"isFakenote":false,"isSkynote":true,"skyjudgeNumber":1,"startJudgeTime":14.684,"xOffset":0,"speedGroup":0},{"isFakenote":false,"isSkynote":true,"skyjudgeNumber":3,"startJudgeTime":14.857,"xOffset":0,"speedGroup":0},{"isFakenote":false,"isSkynote":true,"skyjudgeNumber":3,"startJudgeTime":15.029,"xOffset":0,"speedGroup":0}]},{"isFakenote":false,"isSkynote":true,"skyjudgeNumber":3,"notetype":2,"startJudgeTime":15.201,"endJudgeTime":15.891,"xOffset":0,"speedGroup":0,"draginfolist":[]},{"isFakenote":false,"isSkynote":true,"skyjudgeNumber":3,"notetype":3,"startJudgeTime":15.891,"endJudgeTime":0.029,"xOffset":0,"speedGroup":0,"draginfolist":[{"isFakenote":false,"isSkynote":true,"skyjudgeNumber":1,"startJudgeTime":16.581,"xOffset":0,"speedGroup":0},{"isFakenote":false,"isSkynote":true,"skyjudgeNumber":3,"startJudgeTime":17.27,"xOffset":0,"speedGroup":0}]},{"isFakenote":false,"isSkynote":false,"skyjudgeNumber":0,"notetype":3,"startJudgeTime":15.201,"endJudgeTime":0.029,"xOffset":1,"speedGroup":0,"draginfolist":[{"isFakenote":false,"isSkynote":false,"skyjudgeNumber":0,"startJudgeTime":15.891,"xOffset":1,"speedGroup":0},{"isFakenote":false,"isSkynote":true,"skyjudgeNumber":4,"startJudgeTime":16.063,"xOffset":0,"speedGroup":0},{"isFakenote":false,"isSkynote":true,"skyjudgeNumber":2,"startJudgeTime":16.236,"xOffset":0,"speedGroup":0},{"isFakenote":false,"isSkynote":true,"skyjudgeNumber":4,"startJudgeTime":16.408,"xOffset":0,"speedGroup":0},{"isFakenote":false,"isSkynote":false,"skyjudgeNumber":0,"startJudgeTime":16.581,"xOffset":1,"speedGroup":0},{"isFakenote":false,"isSkynote":true,"skyjudgeNumber":4,"startJudgeTime":17.098,"xOffset":0,"speedGroup":0},{"isFakenote":false,"isSkynote":true,"skyjudgeNumber":2,"startJudgeTime":17.27,"xOffset":0,"speedGroup":0},{"isFakenote":false,"isSkynote":true,"skyjudgeNumber":2,"startJudgeTime":17.443,"xOffset":0,"speedGroup":0},{"isFakenote":false,"isSkynote":true,"skyjudgeNumber":4,"startJudgeTime":17.615,"xOffset":0,"speedGroup":0},{"isFakenote":false,"isSkynote":true,"skyjudgeNumber":4,"startJudgeTime":17.788,"xOffset":0,"speedGroup":0}]},{"isFakenote":false,"isSkynote":true,"skyjudgeNumber":4,"notetype":2,"startJudgeTime":17.96,"endJudgeTime":18.65,"xOffset":0,"speedGroup":0,"draginfolist":[]},{"isFakenote":false,"isSkynote":true,"skyjudgeNumber":4,"notetype":3,"startJudgeTime":18.65,"endJudgeTime":0.029,"xOffset":0,"speedGroup":0,"draginfolist":[{"isFakenote":false,"isSkynote":true,"skyjudgeNumber":2,"startJudgeTime":19.339,"xOffset":0,"speedGroup":0},{"isFakenote":false,"isSkynote":true,"skyjudgeNumber":4,"startJudgeTime":20.029,"xOffset":0,"speedGroup":0}]},{"isFakenote":false,"isSkynote":false,"skyjudgeNumber":0,"notetype":3,"startJudgeTime":17.96,"endJudgeTime":0.029,"xOffset":0,"speedGroup":0,"draginfolist":[{"isFakenote":false,"isSkynote":false,"skyjudgeNumber":0,"startJudgeTime":18.65,"xOffset":0,"speedGroup":0},{"isFakenote":false,"isSkynote":true,"skyjudgeNumber":3,"startJudgeTime":18.822,"xOffset":0,"speedGroup":0},{"isFakenote":false,"isSkynote":true,"skyjudgeNumber":1,"startJudgeTime":18.995,"xOffset":0,"speedGroup":0},{"isFakenote":false,"isSkynote":true,"skyjudgeNumber":3,"startJudgeTime":19.167,"xOffset":0,"speedGroup":0},{"isFakenote":false,"isSkynote":false,"skyjudgeNumber":0,"startJudgeTime":19.339,"xOffset":0,"speedGroup":0},{"isFakenote":false,"isSkynote":false,"skyjudgeNumber":0,"startJudgeTime":19.857,"xOffset":0,"speedGroup":0},{"isFakenote":false,"isSkynote":true,"skyjudgeNumber":1,"startJudgeTime":20.201,"xOffset":0,"speedGroup":0},{"isFakenote":false,"isSkynote":true,"skyjudgeNumber":3,"startJudgeTime":20.546,"xOffset":0,"speedGroup":0}]},{"isFakenote":false,"isSkynote":true,"skyjudgeNumber":3,"notetype":2,"startJudgeTime":20.719,"endJudgeTime":21.408,"xOffset":0,"speedGroup":0,"draginfolist":[]},{"isFakenote":false,"isSkynote":true,"skyjudgeNumber":3,"notetype":3,"startJudgeTime":21.408,"endJudgeTime":0.029,"xOffset":0,"speedGroup":0,"draginfolist":[{"isFakenote":false,"isSkynote":true,"skyjudgeNumber":1,"startJudgeTime":22.098,"xOffset":0,"speedGroup":0},{"isFakenote":false,"isSkynote":true,"skyjudgeNumber":1,"startJudgeTime":22.615,"xOffset":0,"speedGroup":0},{"isFakenote":false,"isSkynote":true,"skyjudgeNumber":3,"startJudgeTime":23.132,"xOffset":0,"speedGroup":0}]},{"isFakenote":false,"isSkynote":false,"skyjudgeNumber":0,"notetype":3,"startJudgeTime":20.719,"endJudgeTime":0.029,"xOffset":1,"speedGroup":0,"draginfolist":[{"isFakenote":false,"isSkynote":false,"skyjudgeNumber":0,"startJudgeTime":21.408,"xOffset":1,"speedGroup":0},{"isFakenote":false,"isSkynote":true,"skyjudgeNumber":4,"startJudgeTime":21.581,"xOffset":0,"speedGroup":0},{"isFakenote":false,"isSkynote":true,"skyjudgeNumber":2,"startJudgeTime":21.753,"xOffset":0,"speedGroup":0},{"isFakenote":false,"isSkynote":true,"skyjudgeNumber":4,"startJudgeTime":21.926,"xOffset":0,"speedGroup":0},{"isFakenote":false,"isSkynote":false,"skyjudgeNumber":0,"startJudgeTime":22.615,"xOffset":1,"speedGroup":0},{"isFakenote":false,"isSkynote":true,"skyjudgeNumber":4,"startJudgeTime":22.96,"xOffset":0,"speedGroup":0},{"isFakenote":false,"isSkynote":true,"skyjudgeNumber":4,"startJudgeTime":23.132,"xOffset":0,"speedGroup":0}]},{"isFakenote":false,"isSkynote":true,"skyjudgeNumber":1,"notetype":3,"startJudgeTime":24.857,"endJudgeTime":0.029,"xOffset":0,"speedGroup":0,"draginfolist":[{"isFakenote":false,"isSkynote":false,"skyjudgeNumber":0,"startJudgeTime":25.201,"xOffset":0.5,"speedGroup":0}]},{"isFakenote":false,"isSkynote":true,"skyjudgeNumber":4,"notetype":0,"startJudgeTime":24.857,"endJudgeTime":0.029,"xOffset":0,"speedGroup":0,"draginfolist":[]},{"isFakenote":false,"isSkynote":true,"skyjudgeNumber":4,"notetype":1,"startJudgeTime":25.201,"endJudgeTime":0.029,"xOffset":0,"speedGroup":0,"draginfolist":[]},{"isFakenote":false,"isSkynote":true,"skyjudgeNumber":3,"notetype":3,"startJudgeTime":25.719,"endJudgeTime":0.029,"xOffset":0,"speedGroup":0,"draginfolist":[{"isFakenote":false,"isSkynote":false,"skyjudgeNumber":0,"startJudgeTime":25.891,"xOffset":0.5,"speedGroup":0}]},{"isFakenote":false,"isSkynote":true,"skyjudgeNumber":4,"notetype":0,"startJudgeTime":25.719,"endJudgeTime":0.029,"xOffset":0,"speedGroup":0,"draginfolist":[]},{"isFakenote":false,"isSkynote":true,"skyjudgeNumber":4,"notetype":1,"startJudgeTime":25.891,"endJudgeTime":0.029,"xOffset":0,"speedGroup":0,"draginfolist":[]},{"isFakenote":false,"isSkynote":false,"skyjudgeNumber":0,"notetype":3,"startJudgeTime":26.408,"endJudgeTime":0.029,"xOffset":1,"speedGroup":0,"draginfolist":[{"isFakenote":false,"isSkynote":false,"skyjudgeNumber":0,"startJudgeTime":26.581,"xOffset":0.5,"speedGroup":0}]},{"isFakenote":false,"isSkynote":true,"skyjudgeNumber":3,"notetype":0,"startJudgeTime":26.408,"endJudgeTime":0.029,"xOffset":0,"speedGroup":0,"draginfolist":[]},{"isFakenote":false,"isSkynote":true,"skyjudgeNumber":3,"notetype":1,"startJudgeTime":26.581,"endJudgeTime":0.029,"xOffset":0,"speedGroup":0,"draginfolist":[]},{"isFakenote":false,"isSkynote":true,"skyjudgeNumber":4,"notetype":0,"startJudgeTime":27.098,"endJudgeTime":0.029,"xOffset":0,"speedGroup":0,"draginfolist":[]},{"isFakenote":false,"isSkynote":true,"skyjudgeNumber":4,"notetype":1,"startJudgeTime":27.27,"endJudgeTime":0.029,"xOffset":0,"speedGroup":0,"draginfolist":[]},{"isFakenote":false,"isSkynote":false,"skyjudgeNumber":0,"notetype":3,"startJudgeTime":27.098,"endJudgeTime":0.029,"xOffset":0.5,"speedGroup":0,"draginfolist":[{"isFakenote":false,"isSkynote":false,"skyjudgeNumber":0,"startJudgeTime":27.27,"xOffset":0,"speedGroup":0}]},{"isFakenote":false,"isSkynote":true,"skyjudgeNumber":3,"notetype":0,"startJudgeTime":27.615,"endJudgeTime":0.029,"xOffset":0,"speedGroup":0,"draginfolist":[]},{"isFakenote":false,"isSkynote":true,"skyjudgeNumber":3,"notetype":1,"startJudgeTime":27.96,"endJudgeTime":0.029,"xOffset":0,"speedGroup":0,"draginfolist":[]},{"isFakenote":false,"isSkynote":true,"skyjudgeNumber":3,"notetype":1,"startJudgeTime":28.65,"endJudgeTime":0.029,"xOffset":0,"speedGroup":0,"draginfolist":[]},{"isFakenote":false,"isSkynote":true,"skyjudgeNumber":4,"notetype":1,"startJudgeTime":29.339,"endJudgeTime":0.029,"xOffset":0,"speedGroup":0,"draginfolist":[]},{"isFakenote":false,"isSkynote":true,"skyjudgeNumber":3,"notetype":1,"startJudgeTime":30.029,"endJudgeTime":0.029,"xOffset":0,"speedGroup":0,"draginfolist":[]},{"isFakenote":false,"isSkynote":true,"skyjudgeNumber":3,"notetype":0,"startJudgeTime":28.477,"endJudgeTime":0.029,"xOffset":0,"speedGroup":0,"draginfolist":[]},{"isFakenote":false,"isSkynote":true,"skyjudgeNumber":4,"notetype":0,"startJudgeTime":29.167,"endJudgeTime":0.029,"xOffset":0,"speedGroup":0,"draginfolist":[]},{"isFakenote":false,"isSkynote":true,"skyjudgeNumber":3,"notetype":0,"startJudgeTime":29.857,"endJudgeTime":0.029,"xOffset":0,"speedGroup":0,"draginfolist":[]},{"isFakenote":false,"isSkynote":true,"skyjudgeNumber":2,"notetype":3,"startJudgeTime":27.615,"endJudgeTime":0.029,"xOffset":0,"speedGroup":0,"draginfolist":[{"isFakenote":false,"isSkynote":false,"skyjudgeNumber":0,"startJudgeTime":27.96,"xOffset":0.5,"speedGroup":0}]},{"isFakenote":false,"isSkynote":true,"skyjudgeNumber":4,"notetype":3,"startJudgeTime":28.477,"endJudgeTime":0.029,"xOffset":0,"speedGroup":0,"draginfolist":[{"isFakenote":false,"isSkynote":false,"skyjudgeNumber":0,"startJudgeTime":28.65,"xOffset":0.5,"speedGroup":0}]},{"isFakenote":false,"isSkynote":false,"skyjudgeNumber":0,"notetype":3,"startJudgeTime":29.167,"endJudgeTime":0.029,"xOffset":0,"speedGroup":0,"draginfolist":[{"isFakenote":false,"isSkynote":false,"skyjudgeNumber":0,"startJudgeTime":29.339,"xOffset":0.5,"speedGroup":0}]},{"isFakenote":false,"isSkynote":false,"skyjudgeNumber":0,"notetype":3,"startJudgeTime":29.857,"endJudgeTime":0.029,"xOffset":0.5,"speedGroup":0,"draginfolist":[{"isFakenote":false,"isSkynote":false,"skyjudgeNumber":0,"startJudgeTime":30.029,"xOffset":1,"speedGroup":0}]},{"isFakenote":false,"isSkynote":true,"skyjudgeNumber":2,"notetype":0,"startJudgeTime":30.374,"endJudgeTime":0.029,"xOffset":0,"speedGroup":0,"draginfolist":[]},{"isFakenote":false,"isSkynote":true,"skyjudgeNumber":2,"notetype":1,"startJudgeTime":30.719,"endJudgeTime":0.029,"xOffset":0,"speedGroup":0,"draginfolist":[]},{"isFakenote":false,"isSkynote":true,"skyjudgeNumber":2,"notetype":1,"startJudgeTime":31.408,"endJudgeTime":0.029,"xOffset":0,"speedGroup":0,"draginfolist":[]},{"isFakenote":false,"isSkynote":true,"skyjudgeNumber":1,"notetype":1,"startJudgeTime":32.098,"endJudgeTime":0.029,"xOffset":0,"speedGroup":0,"draginfolist":[]},{"isFakenote":false,"isSkynote":true,"skyjudgeNumber":2,"notetype":1,"startJudgeTime":32.788,"endJudgeTime":0.029,"xOffset":0,"speedGroup":0,"draginfolist":[]},{"isFakenote":false,"isSkynote":true,"skyjudgeNumber":1,"notetype":1,"startJudgeTime":33.477,"endJudgeTime":0.029,"xOffset":0,"speedGroup":0,"draginfolist":[]},{"isFakenote":false,"isSkynote":true,"skyjudgeNumber":1,"notetype":1,"startJudgeTime":34.167,"endJudgeTime":0.029,"xOffset":0,"speedGroup":0,"draginfolist":[]},{"isFakenote":false,"isSkynote":true,"skyjudgeNumber":2,"notetype":1,"startJudgeTime":34.857,"endJudgeTime":0.029,"xOffset":0,"speedGroup":0,"draginfolist":[]},{"isFakenote":false,"isSkynote":true,"skyjudgeNumber":2,"notetype":0,"startJudgeTime":31.236,"endJudgeTime":0.029,"xOffset":0,"speedGroup":0,"draginfolist":[]},{"isFakenote":false,"isSkynote":true,"skyjudgeNumber":1,"notetype":0,"startJudgeTime":31.926,"endJudgeTime":0.029,"xOffset":0,"speedGroup":0,"draginfolist":[]},{"isFakenote":false,"isSkynote":true,"skyjudgeNumber":2,"notetype":0,"startJudgeTime":32.615,"endJudgeTime":0.029,"xOffset":0,"speedGroup":0,"draginfolist":[]},{"isFakenote":false,"isSkynote":true,"skyjudgeNumber":1,"notetype":0,"startJudgeTime":33.132,"endJudgeTime":0.029,"xOffset":0,"speedGroup":0,"draginfolist":[]},{"isFakenote":false,"isSkynote":true,"skyjudgeNumber":1,"notetype":0,"startJudgeTime":33.995,"endJudgeTime":0.029,"xOffset":0,"speedGroup":0,"draginfolist":[]},{"isFakenote":false,"isSkynote":true,"skyjudgeNumber":2,"notetype":0,"startJudgeTime":34.684,"endJudgeTime":0.029,"xOffset":0,"speedGroup":0,"draginfolist":[]},{"isFakenote":false,"isSkynote":false,"skyjudgeNumber":0,"notetype":3,"startJudgeTime":30.374,"endJudgeTime":0.029,"xOffset":0.5,"speedGroup":0,"draginfolist":[{"isFakenote":false,"isSkynote":true,"skyjudgeNumber":1,"startJudgeTime":30.719,"xOffset":0,"speedGroup":0}]},{"isFakenote":false,"isSkynote":false,"skyjudgeNumber":0,"notetype":3,"startJudgeTime":31.236,"endJudgeTime":0.029,"xOffset":0,"speedGroup":0,"draginfolist":[{"isFakenote":false,"isSkynote":true,"skyjudgeNumber":1,"startJudgeTime":31.408,"xOffset":0,"speedGroup":0}]},{"isFakenote":false,"isSkynote":true,"skyjudgeNumber":4,"notetype":3,"startJudgeTime":31.926,"endJudgeTime":0.029,"xOffset":0,"speedGroup":0,"draginfolist":[{"isFakenote":false,"isSkynote":true,"skyjudgeNumber":2,"startJudgeTime":32.098,"xOffset":0,"speedGroup":0}]},{"isFakenote":false,"isSkynote":true,"skyjudgeNumber":1,"notetype":3,"startJudgeTime":32.615,"endJudgeTime":0.029,"xOffset":0,"speedGroup":0,"draginfolist":[{"isFakenote":false,"isSkynote":true,"skyjudgeNumber":3,"startJudgeTime":32.788,"xOffset":0,"speedGroup":0}]},{"isFakenote":false,"isSkynote":false,"skyjudgeNumber":0,"notetype":3,"startJudgeTime":33.132,"endJudgeTime":0.029,"xOffset":0.5,"speedGroup":0,"draginfolist":[{"isFakenote":false,"isSkynote":true,"skyjudgeNumber":2,"startJudgeTime":33.477,"xOffset":0,"speedGroup":0}]},{"isFakenote":false,"isSkynote":false,"skyjudgeNumber":0,"notetype":3,"startJudgeTime":33.995,"endJudgeTime":0.029,"xOffset":1,"speedGroup":0,"draginfolist":[{"isFakenote":false,"isSkynote":true,"skyjudgeNumber":2,"startJudgeTime":34.167,"xOffset":0,"speedGroup":0}]},{"isFakenote":false,"isSkynote":true,"skyjudgeNumber":3,"notetype":3,"startJudgeTime":34.684,"endJudgeTime":0.029,"xOffset":0,"speedGroup":0,"draginfolist":[{"isFakenote":false,"isSkynote":true,"skyjudgeNumber":1,"startJudgeTime":34.857,"xOffset":0,"speedGroup":0}]},{"isFakenote":false,"isSkynote":true,"skyjudgeNumber":4,"notetype":3,"startJudgeTime":35.201,"endJudgeTime":0.029,"xOffset":0,"speedGroup":0,"draginfolist":[{"isFakenote":false,"isSkynote":true,"skyjudgeNumber":4,"startJudgeTime":35.288,"xOffset":0,"speedGroup":0},{"isFakenote":false,"isSkynote":false,"skyjudgeNumber":0,"startJudgeTime":35.546,"xOffset":0.5,"speedGroup":0}]},{"isFakenote":false,"isSkynote":true,"skyjudgeNumber":3,"notetype":3,"startJudgeTime":35.201,"endJudgeTime":0.029,"xOffset":0,"speedGroup":0,"draginfolist":[{"isFakenote":false,"isSkynote":true,"skyjudgeNumber":3,"startJudgeTime":35.288,"xOffset":0,"speedGroup":0},{"isFakenote":false,"isSkynote":false,"skyjudgeNumber":0,"startJudgeTime":35.546,"xOffset":0.5,"speedGroup":0}]},{"isFakenote":false,"isSkynote":true,"skyjudgeNumber":2,"notetype":3,"startJudgeTime":35.891,"endJudgeTime":0.029,"xOffset":0,"speedGroup":0,"draginfolist":[{"isFakenote":false,"isSkynote":false,"skyjudgeNumber":0,"startJudgeTime":36.236,"xOffset":0.5,"speedGroup":0},{"isFakenote":false,"isSkynote":false,"skyjudgeNumber":0,"startJudgeTime":36.753,"xOffset":0.5,"speedGroup":0},{"isFakenote":false,"isSkynote":false,"skyjudgeNumber":0,"startJudgeTime":36.926,"xOffset":1,"speedGroup":0},{"isFakenote":false,"isSkynote":false,"skyjudgeNumber":0,"startJudgeTime":37.443,"xOffset":1,"speedGroup":0},{"isFakenote":false,"isSkynote":true,"skyjudgeNumber":4,"startJudgeTime":37.615,"xOffset":0,"speedGroup":0},{"isFakenote":false,"isSkynote":true,"skyjudgeNumber":4,"startJudgeTime":38.132,"xOffset":0,"speedGroup":0},{"isFakenote":false,"isSkynote":false,"skyjudgeNumber":0,"startJudgeTime":38.305,"xOffset":1,"speedGroup":0},{"isFakenote":false,"isSkynote":false,"skyjudgeNumber":0,"startJudgeTime":38.65,"xOffset":1,"speedGroup":0},{"isFakenote":false,"isSkynote":true,"skyjudgeNumber":2,"startJudgeTime":38.995,"xOffset":0,"speedGroup":0},{"isFakenote":false,"isSkynote":true,"skyjudgeNumber":2,"startJudgeTime":39.512,"xOffset":0,"speedGroup":0},{"isFakenote":false,"isSkynote":true,"skyjudgeNumber":4,"startJudgeTime":39.684,"xOffset":0,"speedGroup":0},{"isFakenote":false,"isSkynote":true,"skyjudgeNumber":4,"startJudgeTime":40.201,"xOffset":0,"speedGroup":0},{"isFakenote":false,"isSkynote":true,"skyjudgeNumber":2,"startJudgeTime":40.374,"xOffset":0,"speedGroup":0},{"isFakenote":false,"isSkynote":true,"skyjudgeNumber":2,"startJudgeTime":40.891,"xOffset":0,"speedGroup":0},{"isFakenote":false,"isSkynote":true,"skyjudgeNumber":4,"startJudgeTime":41.063,"xOffset":0,"speedGroup":0}]},{"isFakenote":false,"isSkynote":true,"skyjudgeNumber":3,"notetype":0,"startJudgeTime":35.891,"endJudgeTime":0.029,"xOffset":0,"speedGroup":0,"draginfolist":[]},{"isFakenote":false,"isSkynote":true,"skyjudgeNumber":3,"notetype":0,"startJudgeTime":36.753,"endJudgeTime":0.029,"xOffset":0,"speedGroup":0,"draginfolist":[]},{"isFakenote":false,"isSkynote":true,"skyjudgeNumber":3,"notetype":0,"startJudgeTime":37.443,"endJudgeTime":0.029,"xOffset":0,"speedGroup":0,"draginfolist":[]},{"isFakenote":false,"isSkynote":true,"skyjudgeNumber":3,"notetype":0,"startJudgeTime":38.132,"endJudgeTime":0.029,"xOffset":0,"speedGroup":0,"draginfolist":[]},{"isFakenote":false,"isSkynote":true,"skyjudgeNumber":1,"notetype":0,"startJudgeTime":38.65,"endJudgeTime":0.029,"xOffset":0,"speedGroup":0,"draginfolist":[]},{"isFakenote":false,"isSkynote":true,"skyjudgeNumber":1,"notetype":0,"startJudgeTime":39.512,"endJudgeTime":0.029,"xOffset":0,"speedGroup":0,"draginfolist":[]},{"isFakenote":false,"isSkynote":true,"skyjudgeNumber":1,"notetype":0,"startJudgeTime":40.201,"endJudgeTime":0.029,"xOffset":0,"speedGroup":0,"draginfolist":[]},{"isFakenote":false,"isSkynote":true,"skyjudgeNumber":1,"notetype":0,"startJudgeTime":40.891,"endJudgeTime":0.029,"xOffset":0,"speedGroup":0,"draginfolist":[]},{"isFakenote":false,"isSkynote":true,"skyjudgeNumber":3,"notetype":1,"startJudgeTime":36.236,"endJudgeTime":0.029,"xOffset":0,"speedGroup":0,"draginfolist":[]},{"isFakenote":false,"isSkynote":true,"skyjudgeNumber":3,"notetype":1,"startJudgeTime":36.926,"endJudgeTime":0.029,"xOffset":0,"speedGroup":0,"draginfolist":[]},{"isFakenote":false,"isSkynote":true,"skyjudgeNumber":3,"notetype":1,"startJudgeTime":37.615,"endJudgeTime":0.029,"xOffset":0,"speedGroup":0,"draginfolist":[]},{"isFakenote":false,"isSkynote":true,"skyjudgeNumber":3,"notetype":1,"startJudgeTime":38.305,"endJudgeTime":0.029,"xOffset":0,"speedGroup":0,"draginfolist":[]},{"isFakenote":false,"isSkynote":true,"skyjudgeNumber":1,"notetype":1,"startJudgeTime":38.995,"endJudgeTime":0.029,"xOffset":0,"speedGroup":0,"draginfolist":[]},{"isFakenote":false,"isSkynote":true,"skyjudgeNumber":1,"notetype":1,"startJudgeTime":39.684,"endJudgeTime":0.029,"xOffset":0,"speedGroup":0,"draginfolist":[]},{"isFakenote":false,"isSkynote":true,"skyjudgeNumber":1,"notetype":1,"startJudgeTime":40.374,"endJudgeTime":0.029,"xOffset":0,"speedGroup":0,"draginfolist":[]},{"isFakenote":false,"isSkynote":true,"skyjudgeNumber":1,"notetype":1,"startJudgeTime":41.063,"endJudgeTime":0.029,"xOffset":0,"speedGroup":0,"draginfolist":[]},{"isFakenote":false,"isSkynote":true,"skyjudgeNumber":4,"notetype":0,"startJudgeTime":41.408,"endJudgeTime":0.029,"xOffset":0,"speedGroup":0,"draginfolist":[]},{"isFakenote":false,"isSkynote":true,"skyjudgeNumber":4,"notetype":1,"startJudgeTime":41.753,"endJudgeTime":0.029,"xOffset":0,"speedGroup":0,"draginfolist":[]},{"isFakenote":false,"isSkynote":true,"skyjudgeNumber":4,"notetype":1,"startJudgeTime":42.443,"endJudgeTime":0.029,"xOffset":0,"speedGroup":0,"draginfolist":[]},{"isFakenote":false,"isSkynote":true,"skyjudgeNumber":4,"notetype":1,"startJudgeTime":43.132,"endJudgeTime":0.029,"xOffset":0,"speedGroup":0,"draginfolist":[]},{"isFakenote":false,"isSkynote":true,"skyjudgeNumber":4,"notetype":1,"startJudgeTime":43.822,"endJudgeTime":0.029,"xOffset":0,"speedGroup":0,"draginfolist":[]},{"isFakenote":false,"isSkynote":true,"skyjudgeNumber":2,"notetype":1,"startJudgeTime":44.512,"endJudgeTime":0.029,"xOffset":0,"speedGroup":0,"draginfolist":[]},{"isFakenote":false,"isSkynote":true,"skyjudgeNumber":2,"notetype":1,"startJudgeTime":45.201,"endJudgeTime":0.029,"xOffset":0,"speedGroup":0,"draginfolist":[]},{"isFakenote":false,"isSkynote":true,"skyjudgeNumber":2,"notetype":1,"startJudgeTime":45.891,"endJudgeTime":0.029,"xOffset":0,"speedGroup":0,"draginfolist":[]},{"isFakenote":false,"isSkynote":true,"skyjudgeNumber":4,"notetype":0,"startJudgeTime":42.27,"endJudgeTime":0.029,"xOffset":0,"speedGroup":0,"draginfolist":[]},{"isFakenote":false,"isSkynote":true,"skyjudgeNumber":4,"notetype":0,"startJudgeTime":42.96,"endJudgeTime":0.029,"xOffset":0,"speedGroup":0,"draginfolist":[]},{"isFakenote":false,"isSkynote":true,"skyjudgeNumber":4,"notetype":0,"startJudgeTime":43.65,"endJudgeTime":0.029,"xOffset":0,"speedGroup":0,"draginfolist":[]},{"isFakenote":false,"isSkynote":true,"skyjudgeNumber":2,"notetype":0,"startJudgeTime":44.167,"endJudgeTime":0.029,"xOffset":0,"speedGroup":0,"draginfolist":[]},{"isFakenote":false,"isSkynote":true,"skyjudgeNumber":2,"notetype":0,"startJudgeTime":45.029,"endJudgeTime":0.029,"xOffset":0,"speedGroup":0,"draginfolist":[]},{"isFakenote":false,"isSkynote":true,"skyjudgeNumber":2,"notetype":0,"startJudgeTime":45.719,"endJudgeTime":0.029,"xOffset":0,"speedGroup":0,"draginfolist":[]},{"isFakenote":false,"isSkynote":true,"skyjudgeNumber":1,"notetype":3,"startJudgeTime":41.408,"endJudgeTime":0.029,"xOffset":0,"speedGroup":0,"draginfolist":[{"isFakenote":false,"isSkynote":false,"skyjudgeNumber":0,"startJudgeTime":41.753,"xOffset":0.5,"speedGroup":0},{"isFakenote":false,"isSkynote":false,"skyjudgeNumber":0,"startJudgeTime":42.27,"xOffset":0.5,"speedGroup":0},{"isFakenote":false,"isSkynote":false,"skyjudgeNumber":0,"startJudgeTime":42.443,"xOffset":0,"speedGroup":0},{"isFakenote":false,"isSkynote":false,"skyjudgeNumber":0,"startJudgeTime":42.96,"xOffset":0,"speedGroup":0},{"isFakenote":false,"isSkynote":true,"skyjudgeNumber":3,"startJudgeTime":43.132,"xOffset":0,"speedGroup":0},{"isFakenote":false,"isSkynote":true,"skyjudgeNumber":3,"startJudgeTime":43.65,"xOffset":0,"speedGroup":0},{"isFakenote":false,"isSkynote":false,"skyjudgeNumber":0,"startJudgeTime":43.822,"xOffset":0,"speedGroup":0},{"isFakenote":false,"isSkynote":false,"skyjudgeNumber":0,"startJudgeTime":44.167,"xOffset":0,"speedGroup":0},{"isFakenote":false,"isSkynote":true,"skyjudgeNumber":1,"startJudgeTime":44.512,"xOffset":0,"speedGroup":0},{"isFakenote":false,"isSkynote":true,"skyjudgeNumber":1,"startJudgeTime":45.029,"xOffset":0,"speedGroup":0},{"isFakenote":false,"isSkynote":true,"skyjudgeNumber":3,"startJudgeTime":45.201,"xOffset":0,"speedGroup":0},{"isFakenote":false,"isSkynote":true,"skyjudgeNumber":3,"startJudgeTime":45.719,"xOffset":0,"speedGroup":0},{"isFakenote":false,"isSkynote":true,"skyjudgeNumber":1,"startJudgeTime":45.891,"xOffset":0,"speedGroup":0}]},{"isFakenote":false,"isSkynote":true,"skyjudgeNumber":2,"notetype":3,"startJudgeTime":35.029,"endJudgeTime":0.029,"xOffset":0,"speedGroup":0,"draginfolist":[]},{"isFakenote":false,"isSkynote":true,"skyjudgeNumber":2,"notetype":3,"startJudgeTime":46.063,"endJudgeTime":0.029,"xOffset":0,"speedGroup":0,"draginfolist":[]},{"isFakenote":false,"isSkynote":true,"skyjudgeNumber":2,"notetype":3,"startJudgeTime":46.236,"endJudgeTime":0.029,"xOffset":0,"speedGroup":0,"draginfolist":[{"isFakenote":false,"isSkynote":true,"skyjudgeNumber":2,"startJudgeTime":46.322,"xOffset":0,"speedGroup":0},{"isFakenote":false,"isSkynote":true,"skyjudgeNumber":4,"startJudgeTime":46.581,"xOffset":0,"speedGroup":0},{"isFakenote":false,"isSkynote":false,"skyjudgeNumber":0,"startJudgeTime":46.839,"xOffset":0.5,"speedGroup":0}]},{"isFakenote":false,"isSkynote":true,"skyjudgeNumber":1,"notetype":3,"startJudgeTime":46.236,"endJudgeTime":0.029,"xOffset":0,"speedGroup":0,"draginfolist":[{"isFakenote":false,"isSkynote":true,"skyjudgeNumber":1,"startJudgeTime":46.322,"xOffset":0,"speedGroup":0},{"isFakenote":false,"isSkynote":true,"skyjudgeNumber":3,"startJudgeTime":46.581,"xOffset":0,"speedGroup":0},{"isFakenote":false,"isSkynote":false,"skyjudgeNumber":0,"startJudgeTime":46.839,"xOffset":0.5,"speedGroup":0}]},{"isFakenote":false,"isSkynote":false,"skyjudgeNumber":0,"notetype":1,"startJudgeTime":46.926,"endJudgeTime":0.029,"xOffset":0.5,"speedGroup":1,"draginfolist":[]},{"isFakenote":false,"isSkynote":true,"skyjudgeNumber":4,"notetype":0,"startJudgeTime":50.891,"endJudgeTime":0.029,"xOffset":0,"speedGroup":0,"draginfolist":[]},{"isFakenote":false,"isSkynote":true,"skyjudgeNumber":2,"notetype":1,"startJudgeTime":51.926,"endJudgeTime":0.029,"xOffset":0,"speedGroup":0,"draginfolist":[]},{"isFakenote":false,"isSkynote":true,"skyjudgeNumber":3,"notetype":3,"startJudgeTime":51.063,"endJudgeTime":0.029,"xOffset":0,"speedGroup":0,"draginfolist":[{"isFakenote":false,"isSkynote":false,"skyjudgeNumber":0,"startJudgeTime":51.926,"xOffset":0.5,"speedGroup":0}]},{"isFakenote":false,"isSkynote":false,"skyjudgeNumber":0,"notetype":3,"startJudgeTime":52.098,"endJudgeTime":0.029,"xOffset":0.5,"speedGroup":0,"draginfolist":[]},{"isFakenote":false,"isSkynote":false,"skyjudgeNumber":0,"notetype":3,"startJudgeTime":52.27,"endJudgeTime":0.029,"xOffset":0.5,"speedGroup":0,"draginfolist":[]},{"isFakenote":false,"isSkynote":false,"skyjudgeNumber":0,"notetype":1,"startJudgeTime":52.443,"endJudgeTime":0.029,"xOffset":0.5,"speedGroup":0,"draginfolist":[]},{"isFakenote":false,"isSkynote":true,"skyjudgeNumber":1,"notetype":1,"startJudgeTime":55.891,"endJudgeTime":0.029,"xOffset":0,"speedGroup":1,"draginfolist":[]},{"isFakenote":false,"isSkynote":true,"skyjudgeNumber":4,"notetype":3,"startJudgeTime":55.374,"endJudgeTime":0.029,"xOffset":0,"speedGroup":2,"draginfolist":[{"isFakenote":false,"isSkynote":false,"skyjudgeNumber":0,"startJudgeTime":55.891,"xOffset":0.5,"speedGroup":2}]},{"isFakenote":false,"isSkynote":true,"skyjudgeNumber":3,"notetype":0,"startJudgeTime":55.201,"endJudgeTime":0.029,"xOffset":0,"speedGroup":3,"draginfolist":[]},{"isFakenote":false,"isSkynote":true,"skyjudgeNumber":4,"notetype":0,"startJudgeTime":56.408,"endJudgeTime":0.029,"xOffset":0,"speedGroup":0,"draginfolist":[]},{"isFakenote":false,"isSkynote":true,"skyjudgeNumber":3,"notetype":3,"startJudgeTime":56.581,"endJudgeTime":0.029,"xOffset":0,"speedGroup":0,"draginfolist":[{"isFakenote":false,"isSkynote":false,"skyjudgeNumber":0,"startJudgeTime":57.27,"xOffset":0.5,"speedGroup":0}]},{"isFakenote":false,"isSkynote":false,"skyjudgeNumber":0,"notetype":3,"startJudgeTime":57.443,"endJudgeTime":0.029,"xOffset":0.5,"speedGroup":0,"draginfolist":[]},{"isFakenote":false,"isSkynote":false,"skyjudgeNumber":0,"notetype":3,"startJudgeTime":57.615,"endJudgeTime":0.029,"xOffset":0.5,"speedGroup":0,"draginfolist":[]},{"isFakenote":false,"isSkynote":true,"skyjudgeNumber":2,"notetype":1,"startJudgeTime":57.27,"endJudgeTime":0.029,"xOffset":0,"speedGroup":0,"draginfolist":[]},{"isFakenote":false,"isSkynote":false,"skyjudgeNumber":0,"notetype":1,"startJudgeTime":57.96,"endJudgeTime":0.029,"xOffset":0.5,"speedGroup":4,"draginfolist":[]},{"isFakenote":false,"isSkynote":true,"skyjudgeNumber":4,"notetype":1,"startJudgeTime":58.305,"endJudgeTime":0.029,"xOffset":0,"speedGroup":0,"draginfolist":[]},{"isFakenote":false,"isSkynote":true,"skyjudgeNumber":3,"notetype":0,"startJudgeTime":49.684,"endJudgeTime":0.029,"xOffset":0,"speedGroup":5,"draginfolist":[]},{"isFakenote":false,"isSkynote":true,"skyjudgeNumber":1,"notetype":1,"startJudgeTime":50.374,"endJudgeTime":0.029,"xOffset":0,"speedGroup":5,"draginfolist":[]},{"isFakenote":false,"isSkynote":true,"skyjudgeNumber":2,"notetype":0,"startJudgeTime":58.822,"endJudgeTime":0.029,"xOffset":0,"speedGroup":0,"draginfolist":[]},{"isFakenote":false,"isSkynote":true,"skyjudgeNumber":2,"notetype":1,"startJudgeTime":58.995,"endJudgeTime":0.029,"xOffset":0,"speedGroup":0,"draginfolist":[]},{"isFakenote":false,"isSkynote":true,"skyjudgeNumber":4,"notetype":1,"startJudgeTime":59.684,"endJudgeTime":0.029,"xOffset":0,"speedGroup":0,"draginfolist":[]},{"isFakenote":false,"isSkynote":true,"skyjudgeNumber":2,"notetype":1,"startJudgeTime":60.374,"endJudgeTime":0.029,"xOffset":0,"speedGroup":0,"draginfolist":[]},{"isFakenote":false,"isSkynote":true,"skyjudgeNumber":4,"notetype":1,"startJudgeTime":61.063,"endJudgeTime":0.029,"xOffset":0,"speedGroup":0,"draginfolist":[]},{"isFakenote":false,"isSkynote":true,"skyjudgeNumber":4,"notetype":1,"startJudgeTime":61.753,"endJudgeTime":0.029,"xOffset":0,"speedGroup":0,"draginfolist":[]},{"isFakenote":false,"isSkynote":true,"skyjudgeNumber":2,"notetype":1,"startJudgeTime":62.443,"endJudgeTime":0.029,"xOffset":0,"speedGroup":0,"draginfolist":[]},{"isFakenote":false,"isSkynote":true,"skyjudgeNumber":4,"notetype":0,"startJudgeTime":59.339,"endJudgeTime":0.029,"xOffset":0,"speedGroup":0,"draginfolist":[]},{"isFakenote":false,"isSkynote":true,"skyjudgeNumber":2,"notetype":0,"startJudgeTime":60.201,"endJudgeTime":0.029,"xOffset":0,"speedGroup":0,"draginfolist":[]},{"isFakenote":false,"isSkynote":false,"skyjudgeNumber":0,"notetype":0,"startJudgeTime":60.719,"endJudgeTime":0.029,"xOffset":1,"speedGroup":0,"draginfolist":[]},{"isFakenote":false,"isSkynote":false,"skyjudgeNumber":0,"notetype":0,"startJudgeTime":61.581,"endJudgeTime":0.029,"xOffset":1,"speedGroup":0,"draginfolist":[]},{"isFakenote":false,"isSkynote":true,"skyjudgeNumber":4,"notetype":0,"startJudgeTime":62.098,"endJudgeTime":0.029,"xOffset":0,"speedGroup":0,"draginfolist":[]},{"isFakenote":false,"isSkynote":true,"skyjudgeNumber":4,"notetype":3,"startJudgeTime":62.615,"endJudgeTime":0.029,"xOffset":0,"speedGroup":0,"draginfolist":[]},{"isFakenote":false,"isSkynote":true,"skyjudgeNumber":2,"notetype":1,"startJudgeTime":62.874,"endJudgeTime":0.029,"xOffset":0,"speedGroup":0,"draginfolist":[]},{"isFakenote":false,"isSkynote":true,"skyjudgeNumber":2,"notetype":1,"startJudgeTime":63.132,"endJudgeTime":0.029,"xOffset":0,"speedGroup":0,"draginfolist":[]},{"isFakenote":false,"isSkynote":true,"skyjudgeNumber":1,"notetype":3,"startJudgeTime":58.305,"endJudgeTime":0.029,"xOffset":0,"speedGroup":0,"draginfolist":[{"isFakenote":false,"isSkynote":true,"skyjudgeNumber":1,"startJudgeTime":59.684,"xOffset":0,"speedGroup":0},{"isFakenote":false,"isSkynote":true,"skyjudgeNumber":3,"startJudgeTime":60.029,"xOffset":0,"speedGroup":0},{"isFakenote":false,"isSkynote":false,"skyjudgeNumber":0,"startJudgeTime":60.374,"xOffset":0,"speedGroup":0},{"isFakenote":false,"isSkynote":true,"skyjudgeNumber":3,"startJudgeTime":60.719,"xOffset":0,"speedGroup":0},{"isFakenote":false,"isSkynote":true,"skyjudgeNumber":3,"startJudgeTime":61.926,"xOffset":0,"speedGroup":0},{"isFakenote":false,"isSkynote":true,"skyjudgeNumber":3,"startJudgeTime":62.012,"xOffset":0,"speedGroup":0},{"isFakenote":false,"isSkynote":true,"skyjudgeNumber":3,"startJudgeTime":62.098,"xOffset":0,"speedGroup":0},{"isFakenote":false,"isSkynote":false,"skyjudgeNumber":0,"startJudgeTime":62.615,"xOffset":0,"speedGroup":0},{"isFakenote":false,"isSkynote":true,"skyjudgeNumber":3,"startJudgeTime":62.96,"xOffset":0,"speedGroup":0}]},{"isFakenote":false,"isSkynote":true,"skyjudgeNumber":3,"notetype":0,"startJudgeTime":63.477,"endJudgeTime":0.029,"xOffset":0,"speedGroup":0,"draginfolist":[]},{"isFakenote":false,"isSkynote":true,"skyjudgeNumber":3,"notetype":1,"startJudgeTime":63.822,"endJudgeTime":0.029,"xOffset":0,"speedGroup":0,"draginfolist":[]},{"isFakenote":false,"isSkynote":true,"skyjudgeNumber":1,"notetype":1,"startJudgeTime":64.512,"endJudgeTime":0.029,"xOffset":0,"speedGroup":0,"draginfolist":[]},{"isFakenote":false,"isSkynote":true,"skyjudgeNumber":3,"notetype":1,"startJudgeTime":65.201,"endJudgeTime":0.029,"xOffset":0,"speedGroup":0,"draginfolist":[]},{"isFakenote":false,"isSkynote":true,"skyjudgeNumber":1,"notetype":1,"startJudgeTime":65.891,"endJudgeTime":0.029,"xOffset":0,"speedGroup":0,"draginfolist":[]},{"isFakenote":false,"isSkynote":true,"skyjudgeNumber":1,"notetype":0,"startJudgeTime":65.719,"endJudgeTime":0.029,"xOffset":0,"speedGroup":0,"draginfolist":[]},{"isFakenote":false,"isSkynote":true,"skyjudgeNumber":3,"notetype":0,"startJudgeTime":64.857,"endJudgeTime":0.029,"xOffset":0,"speedGroup":0,"draginfolist":[]},{"isFakenote":false,"isSkynote":true,"skyjudgeNumber":1,"notetype":0,"startJudgeTime":64.339,"endJudgeTime":0.029,"xOffset":0,"speedGroup":0,"draginfolist":[]},{"isFakenote":false,"isSkynote":true,"skyjudgeNumber":2,"notetype":3,"startJudgeTime":63.477,"endJudgeTime":0.029,"xOffset":0,"speedGroup":0,"draginfolist":[{"isFakenote":false,"isSkynote":true,"skyjudgeNumber":2,"startJudgeTime":65.201,"xOffset":0,"speedGroup":0},{"isFakenote":false,"isSkynote":false,"skyjudgeNumber":0,"startJudgeTime":65.546,"xOffset":1,"speedGroup":0},{"isFakenote":false,"isSkynote":true,"skyjudgeNumber":4,"startJudgeTime":65.891,"xOffset":0,"speedGroup":0},{"isFakenote":false,"isSkynote":true,"skyjudgeNumber":2,"startJudgeTime":66.236,"xOffset":0,"speedGroup":0}]},{"isFakenote":false,"isSkynote":true,"skyjudgeNumber":3,"notetype":0,"startJudgeTime":66.236,"endJudgeTime":0.029,"xOffset":0,"speedGroup":0,"draginfolist":[]},{"isFakenote":false,"isSkynote":true,"skyjudgeNumber":1,"notetype":1,"startJudgeTime":66.581,"endJudgeTime":0.029,"xOffset":0,"speedGroup":0,"draginfolist":[]},{"isFakenote":false,"isSkynote":true,"skyjudgeNumber":4,"notetype":0,"startJudgeTime":66.753,"endJudgeTime":0.029,"xOffset":0,"speedGroup":0,"draginfolist":[]},{"isFakenote":false,"isSkynote":false,"skyjudgeNumber":0,"notetype":0,"startJudgeTime":67.27,"endJudgeTime":0.029,"xOffset":0,"speedGroup":0,"draginfolist":[]},{"isFakenote":false,"isSkynote":false,"skyjudgeNumber":0,"notetype":0,"startJudgeTime":67.788,"endJudgeTime":0.029,"xOffset":1,"speedGroup":0,"draginfolist":[]},{"isFakenote":false,"isSkynote":true,"skyjudgeNumber":2,"notetype":1,"startJudgeTime":67.098,"endJudgeTime":0.029,"xOffset":0,"speedGroup":0,"draginfolist":[]},{"isFakenote":false,"isSkynote":true,"skyjudgeNumber":1,"notetype":1,"startJudgeTime":67.615,"endJudgeTime":0.029,"xOffset":0,"speedGroup":0,"draginfolist":[]},{"isFakenote":false,"isSkynote":true,"skyjudgeNumber":2,"notetype":1,"startJudgeTime":68.132,"endJudgeTime":0.029,"xOffset":0,"speedGroup":0,"draginfolist":[]},{"isFakenote":false,"isSkynote":true,"skyjudgeNumber":1,"notetype":3,"startJudgeTime":66.753,"endJudgeTime":0.029,"xOffset":0,"speedGroup":0,"draginfolist":[]},{"isFakenote":false,"isSkynote":true,"skyjudgeNumber":2,"notetype":3,"startJudgeTime":67.27,"endJudgeTime":0.029,"xOffset":0,"speedGroup":0,"draginfolist":[]},{"isFakenote":false,"isSkynote":true,"skyjudgeNumber":1,"notetype":3,"startJudgeTime":67.788,"endJudgeTime":0.029,"xOffset":0,"speedGroup":0,"draginfolist":[]},{"isFakenote":false,"isSkynote":true,"skyjudgeNumber":2,"notetype":3,"startJudgeTime":68.305,"endJudgeTime":0.029,"xOffset":0,"speedGroup":0,"draginfolist":[{"isFakenote":false,"isSkynote":true,"skyjudgeNumber":4,"startJudgeTime":68.65,"xOffset":0,"speedGroup":0}]},{"isFakenote":false,"isSkynote":true,"skyjudgeNumber":3,"notetype":0,"startJudgeTime":68.305,"endJudgeTime":0.029,"xOffset":0,"speedGroup":0,"draginfolist":[]},{"isFakenote":false,"isSkynote":true,"skyjudgeNumber":1,"notetype":1,"startJudgeTime":68.477,"endJudgeTime":0.029,"xOffset":0,"speedGroup":0,"draginfolist":[]},{"isFakenote":false,"isSkynote":true,"skyjudgeNumber":1,"notetype":1,"startJudgeTime":68.65,"endJudgeTime":0.029,"xOffset":0,"speedGroup":0,"draginfolist":[]},{"isFakenote":false,"isSkynote":true,"skyjudgeNumber":1,"notetype":3,"startJudgeTime":68.822,"endJudgeTime":0.029,"xOffset":0,"speedGroup":0,"draginfolist":[]},{"isFakenote":false,"isSkynote":true,"skyjudgeNumber":1,"notetype":3,"startJudgeTime":68.995,"endJudgeTime":0.029,"xOffset":0,"speedGroup":0,"draginfolist":[{"isFakenote":false,"isSkynote":true,"skyjudgeNumber":1,"startJudgeTime":70.719,"xOffset":0,"speedGroup":0},{"isFakenote":false,"isSkynote":false,"skyjudgeNumber":0,"startJudgeTime":71.063,"xOffset":0,"speedGroup":0},{"isFakenote":false,"isSkynote":true,"skyjudgeNumber":3,"startJudgeTime":71.408,"xOffset":0,"speedGroup":0},{"isFakenote":false,"isSkynote":true,"skyjudgeNumber":1,"startJudgeTime":71.753,"xOffset":0,"speedGroup":0}]},{"isFakenote":false,"isSkynote":true,"skyjudgeNumber":4,"notetype":0,"startJudgeTime":68.995,"endJudgeTime":0.029,"xOffset":0,"speedGroup":0,"draginfolist":[]},{"isFakenote":false,"isSkynote":true,"skyjudgeNumber":4,"notetype":1,"startJudgeTime":69.339,"endJudgeTime":0.029,"xOffset":0,"speedGroup":0,"draginfolist":[]},{"isFakenote":false,"isSkynote":true,"skyjudgeNumber":2,"notetype":1,"startJudgeTime":70.029,"endJudgeTime":0.029,"xOffset":0,"speedGroup":0,"draginfolist":[]},{"isFakenote":false,"isSkynote":true,"skyjudgeNumber":4,"notetype":1,"startJudgeTime":70.719,"endJudgeTime":0.029,"xOffset":0,"speedGroup":0,"draginfolist":[]},{"isFakenote":false,"isSkynote":true,"skyjudgeNumber":2,"notetype":1,"startJudgeTime":71.408,"endJudgeTime":0.029,"xOffset":0,"speedGroup":0,"draginfolist":[]},{"isFakenote":false,"isSkynote":true,"skyjudgeNumber":2,"notetype":0,"startJudgeTime":69.857,"endJudgeTime":0.029,"xOffset":0,"speedGroup":0,"draginfolist":[]},{"isFakenote":false,"isSkynote":true,"skyjudgeNumber":4,"notetype":0,"startJudgeTime":70.374,"endJudgeTime":0.029,"xOffset":0,"speedGroup":0,"draginfolist":[]},{"isFakenote":false,"isSkynote":true,"skyjudgeNumber":4,"notetype":3,"startJudgeTime":70.546,"endJudgeTime":0.029,"xOffset":0,"speedGroup":0,"draginfolist":[]},{"isFakenote":false,"isSkynote":true,"skyjudgeNumber":2,"notetype":0,"startJudgeTime":71.236,"endJudgeTime":0.029,"xOffset":0,"speedGroup":0,"draginfolist":[]},{"isFakenote":false,"isSkynote":true,"skyjudgeNumber":2,"notetype":3,"startJudgeTime":71.495,"endJudgeTime":0.029,"xOffset":0,"speedGroup":0,"draginfolist":[]},{"isFakenote":false,"isSkynote":true,"skyjudgeNumber":2,"notetype":0,"startJudgeTime":71.753,"endJudgeTime":0.029,"xOffset":0,"speedGroup":0,"draginfolist":[]},{"isFakenote":false,"isSkynote":true,"skyjudgeNumber":2,"notetype":0,"startJudgeTime":71.926,"endJudgeTime":0.029,"xOffset":0,"speedGroup":0,"draginfolist":[]},{"isFakenote":false,"isSkynote":true,"skyjudgeNumber":1,"notetype":1,"startJudgeTime":72.27,"endJudgeTime":0.029,"xOffset":0,"speedGroup":0,"draginfolist":[]},{"isFakenote":false,"isSkynote":true,"skyjudgeNumber":4,"notetype":0,"startJudgeTime":72.788,"endJudgeTime":0.029,"xOffset":0,"speedGroup":0,"draginfolist":[]},{"isFakenote":false,"isSkynote":true,"skyjudgeNumber":4,"notetype":0,"startJudgeTime":72.615,"endJudgeTime":0.029,"xOffset":0,"speedGroup":0,"draginfolist":[]},{"isFakenote":false,"isSkynote":true,"skyjudgeNumber":3,"notetype":0,"startJudgeTime":73.132,"endJudgeTime":0.029,"xOffset":0,"speedGroup":0,"draginfolist":[]},{"isFakenote":false,"isSkynote":true,"skyjudgeNumber":3,"notetype":1,"startJudgeTime":73.305,"endJudgeTime":0.029,"xOffset":0,"speedGroup":0,"draginfolist":[]},{"isFakenote":false,"isSkynote":false,"skyjudgeNumber":0,"notetype":0,"startJudgeTime":73.65,"endJudgeTime":0.029,"xOffset":1,"speedGroup":0,"draginfolist":[]},{"isFakenote":false,"isSkynote":false,"skyjudgeNumber":0,"notetype":0,"startJudgeTime":73.822,"endJudgeTime":0.029,"xOffset":0,"speedGroup":0,"draginfolist":[]},{"isFakenote":false,"isSkynote":false,"skyjudgeNumber":0,"notetype":1,"startJudgeTime":74.167,"endJudgeTime":0.029,"xOffset":0.5,"speedGroup":0,"draginfolist":[]},{"isFakenote":false,"isSkynote":true,"skyjudgeNumber":2,"notetype":3,"startJudgeTime":74.512,"endJudgeTime":0.029,"xOffset":0,"speedGroup":0,"draginfolist":[{"isFakenote":false,"isSkynote":true,"skyjudgeNumber":4,"startJudgeTime":75.719,"xOffset":0,"speedGroup":0},{"isFakenote":false,"isSkynote":true,"skyjudgeNumber":4,"startJudgeTime":75.805,"xOffset":0,"speedGroup":0},{"isFakenote":false,"isSkynote":true,"skyjudgeNumber":4,"startJudgeTime":75.891,"xOffset":0,"speedGroup":0},{"isFakenote":false,"isSkynote":false,"skyjudgeNumber":0,"startJudgeTime":76.581,"xOffset":1,"speedGroup":0},{"isFakenote":false,"isSkynote":true,"skyjudgeNumber":2,"startJudgeTime":77.27,"xOffset":0,"speedGroup":0}]},{"isFakenote":false,"isSkynote":true,"skyjudgeNumber":3,"notetype":0,"startJudgeTime":74.512,"endJudgeTime":0.029,"xOffset":0,"speedGroup":0,"draginfolist":[]},{"isFakenote":false,"isSkynote":true,"skyjudgeNumber":3,"notetype":1,"startJudgeTime":74.857,"endJudgeTime":0.029,"xOffset":0,"speedGroup":0,"draginfolist":[]},{"isFakenote":false,"isSkynote":true,"skyjudgeNumber":1,"notetype":1,"startJudgeTime":75.546,"endJudgeTime":0.029,"xOffset":0,"speedGroup":0,"draginfolist":[]},{"isFakenote":false,"isSkynote":true,"skyjudgeNumber":3,"notetype":1,"startJudgeTime":76.236,"endJudgeTime":0.029,"xOffset":0,"speedGroup":0,"draginfolist":[]},{"isFakenote":false,"isSkynote":true,"skyjudgeNumber":1,"notetype":1,"startJudgeTime":76.926,"endJudgeTime":0.029,"xOffset":0,"speedGroup":0,"draginfolist":[]},{"isFakenote":false,"isSkynote":true,"skyjudgeNumber":1,"notetype":0,"startJudgeTime":75.374,"endJudgeTime":0.029,"xOffset":0,"speedGroup":0,"draginfolist":[]},{"isFakenote":false,"isSkynote":true,"skyjudgeNumber":3,"notetype":0,"startJudgeTime":75.891,"endJudgeTime":0.029,"xOffset":0,"speedGroup":0,"draginfolist":[]},{"isFakenote":false,"isSkynote":true,"skyjudgeNumber":3,"notetype":3,"startJudgeTime":76.408,"endJudgeTime":0.029,"xOffset":0,"speedGroup":0,"draginfolist":[]},{"isFakenote":false,"isSkynote":true,"skyjudgeNumber":1,"notetype":3,"startJudgeTime":76.753,"endJudgeTime":0.029,"xOffset":0,"speedGroup":0,"draginfolist":[]},{"isFakenote":false,"isSkynote":true,"skyjudgeNumber":3,"notetype":0,"startJudgeTime":77.27,"endJudgeTime":0.029,"xOffset":0,"speedGroup":0,"draginfolist":[]},{"isFakenote":false,"isSkynote":true,"skyjudgeNumber":4,"notetype":0,"startJudgeTime":77.788,"endJudgeTime":0.029,"xOffset":0,"speedGroup":0,"draginfolist":[]},{"isFakenote":false,"isSkynote":false,"skyjudgeNumber":0,"notetype":0,"startJudgeTime":78.305,"endJudgeTime":0.029,"xOffset":0,"speedGroup":0,"draginfolist":[]},{"isFakenote":false,"isSkynote":true,"skyjudgeNumber":1,"notetype":1,"startJudgeTime":77.615,"endJudgeTime":0.029,"xOffset":0,"speedGroup":0,"draginfolist":[]},{"isFakenote":false,"isSkynote":true,"skyjudgeNumber":2,"notetype":1,"startJudgeTime":78.132,"endJudgeTime":0.029,"xOffset":0,"speedGroup":0,"draginfolist":[]},{"isFakenote":false,"isSkynote":true,"skyjudgeNumber":1,"notetype":1,"startJudgeTime":78.65,"endJudgeTime":0.029,"xOffset":0,"speedGroup":0,"draginfolist":[]},{"isFakenote":false,"isSkynote":true,"skyjudgeNumber":2,"notetype":1,"startJudgeTime":79.167,"endJudgeTime":0.029,"xOffset":0,"speedGroup":0,"draginfolist":[]},{"isFakenote":false,"isSkynote":false,"skyjudgeNumber":0,"notetype":3,"startJudgeTime":78.995,"endJudgeTime":0.029,"xOffset":1,"speedGroup":0,"draginfolist":[]},{"isFakenote":false,"isSkynote":true,"skyjudgeNumber":1,"notetype":3,"startJudgeTime":77.788,"endJudgeTime":0.029,"xOffset":0,"speedGroup":0,"draginfolist":[]},{"isFakenote":false,"isSkynote":true,"skyjudgeNumber":2,"notetype":3,"startJudgeTime":78.305,"endJudgeTime":0.029,"xOffset":0,"speedGroup":0,"draginfolist":[]},{"isFakenote":false,"isSkynote":false,"skyjudgeNumber":0,"notetype":3,"startJudgeTime":78.822,"endJudgeTime":0.029,"xOffset":1,"speedGroup":0,"draginfolist":[]},{"isFakenote":false,"isSkynote":false,"skyjudgeNumber":0,"notetype":0,"startJudgeTime":78.65,"endJudgeTime":0.029,"xOffset":1,"speedGroup":0,"draginfolist":[]},{"isFakenote":false,"isSkynote":false,"skyjudgeNumber":0,"notetype":0,"startJudgeTime":79.339,"endJudgeTime":0.029,"xOffset":0.5,"speedGroup":0,"draginfolist":[]},{"isFakenote":false,"isSkynote":false,"skyjudgeNumber":0,"notetype":3,"startJudgeTime":79.426,"endJudgeTime":0.029,"xOffset":0.5,"speedGroup":0,"draginfolist":[]},{"isFakenote":false,"isSkynote":false,"skyjudgeNumber":0,"notetype":3,"startJudgeTime":79.512,"endJudgeTime":0.029,"xOffset":0.5,"speedGroup":0,"draginfolist":[]},{"isFakenote":false,"isSkynote":false,"skyjudgeNumber":0,"notetype":3,"startJudgeTime":79.684,"endJudgeTime":0.029,"xOffset":0.5,"speedGroup":0,"draginfolist":[]},{"isFakenote":false,"isSkynote":false,"skyjudgeNumber":0,"notetype":1,"startJudgeTime":79.857,"endJudgeTime":0.029,"xOffset":0.5,"speedGroup":0,"draginfolist":[]},{"isFakenote":false,"isSkynote":false,"skyjudgeNumber":0,"notetype":1,"startJudgeTime":80.029,"endJudgeTime":0.029,"xOffset":0.5,"speedGroup":1,"draginfolist":[]},{"isFakenote":false,"isSkynote":true,"skyjudgeNumber":1,"notetype":3,"startJudgeTime":6.926,"endJudgeTime":0.029,"xOffset":0,"speedGroup":0,"draginfolist":[]},{"isFakenote":false,"isSkynote":true,"skyjudgeNumber":4,"notetype":3,"startJudgeTime":49.857,"endJudgeTime":0.029,"xOffset":0,"speedGroup":5,"draginfolist":[{"isFakenote":false,"isSkynote":false,"skyjudgeNumber":0,"startJudgeTime":50.374,"xOffset":0.5,"speedGroup":5}]},{"isFakenote":false,"isSkynote":true,"skyjudgeNumber":1,"notetype":3,"startJudgeTime":82.788,"endJudgeTime":0.029,"xOffset":0,"speedGroup":0,"draginfolist":[{"isFakenote":false,"isSkynote":false,"skyjudgeNumber":0,"startJudgeTime":85.546,"xOffset":0,"speedGroup":0}]},{"isFakenote":false,"isSkynote":true,"skyjudgeNumber":2,"notetype":3,"startJudgeTime":85.546,"endJudgeTime":0.029,"xOffset":0,"speedGroup":0,"draginfolist":[{"isFakenote":false,"isSkynote":false,"skyjudgeNumber":0,"startJudgeTime":88.305,"xOffset":1,"speedGroup":0}]},{"isFakenote":false,"isSkynote":false,"skyjudgeNumber":0,"notetype":3,"startJudgeTime":88.305,"endJudgeTime":0.029,"xOffset":0.5,"speedGroup":0,"draginfolist":[{"isFakenote":false,"isSkynote":false,"skyjudgeNumber":0,"startJudgeTime":90.201,"xOffset":0.5,"speedGroup":0}]},{"isFakenote":false,"isSkynote":false,"skyjudgeNumber":0,"notetype":3,"startJudgeTime":90.288,"endJudgeTime":0.029,"xOffset":0.5,"speedGroup":0,"draginfolist":[]},{"isFakenote":false,"isSkynote":false,"skyjudgeNumber":0,"notetype":3,"startJudgeTime":90.374,"endJudgeTime":0.029,"xOffset":0.5,"speedGroup":0,"draginfolist":[]},{"isFakenote":false,"isSkynote":false,"skyjudgeNumber":0,"notetype":1,"startJudgeTime":90.546,"endJudgeTime":0.029,"xOffset":0.5,"speedGroup":0,"draginfolist":[]},{"isFakenote":false,"isSkynote":true,"skyjudgeNumber":3,"notetype":3,"startJudgeTime":90.891,"endJudgeTime":0.029,"xOffset":0,"speedGroup":0,"draginfolist":[]},{"isFakenote":false,"isSkynote":true,"skyjudgeNumber":3,"notetype":3,"startJudgeTime":90.977,"endJudgeTime":0.029,"xOffset":0,"speedGroup":0,"draginfolist":[]},{"isFakenote":false,"isSkynote":true,"skyjudgeNumber":4,"notetype":3,"startJudgeTime":90.977,"endJudgeTime":0.029,"xOffset":0,"speedGroup":0,"draginfolist":[]},{"isFakenote":false,"isSkynote":true,"skyjudgeNumber":4,"notetype":3,"startJudgeTime":90.891,"endJudgeTime":0.029,"xOffset":0,"speedGroup":0,"draginfolist":[]},{"isFakenote":false,"isSkynote":true,"skyjudgeNumber":3,"notetype":1,"startJudgeTime":91.063,"endJudgeTime":0.029,"xOffset":0,"speedGroup":0,"draginfolist":[]},{"isFakenote":false,"isSkynote":true,"skyjudgeNumber":4,"notetype":1,"startJudgeTime":91.063,"endJudgeTime":0.029,"xOffset":0,"speedGroup":0,"draginfolist":[]},{"isFakenote":false,"isSkynote":true,"skyjudgeNumber":3,"notetype":1,"startJudgeTime":91.408,"endJudgeTime":0.029,"xOffset":0,"speedGroup":0,"draginfolist":[]},{"isFakenote":false,"isSkynote":true,"skyjudgeNumber":1,"notetype":1,"startJudgeTime":91.926,"endJudgeTime":0.029,"xOffset":0,"speedGroup":0,"draginfolist":[]},{"isFakenote":false,"isSkynote":true,"skyjudgeNumber":4,"notetype":0,"startJudgeTime":91.581,"endJudgeTime":0.029,"xOffset":0,"speedGroup":0,"draginfolist":[]},{"isFakenote":false,"isSkynote":false,"skyjudgeNumber":0,"notetype":0,"startJudgeTime":92.098,"endJudgeTime":0.029,"xOffset":1,"speedGroup":0,"draginfolist":[]},{"isFakenote":false,"isSkynote":true,"skyjudgeNumber":4,"notetype":1,"startJudgeTime":92.615,"endJudgeTime":0.029,"xOffset":0,"speedGroup":0,"draginfolist":[]},{"isFakenote":false,"isSkynote":true,"skyjudgeNumber":3,"notetype":0,"startJudgeTime":93.132,"endJudgeTime":0.029,"xOffset":0,"speedGroup":0,"draginfolist":[]},{"isFakenote":false,"isSkynote":true,"skyjudgeNumber":3,"notetype":0,"startJudgeTime":93.477,"endJudgeTime":0.029,"xOffset":0,"speedGroup":0,"draginfolist":[]},{"isFakenote":false,"isSkynote":true,"skyjudgeNumber":2,"notetype":3,"startJudgeTime":93.305,"endJudgeTime":0.029,"xOffset":0,"speedGroup":0,"draginfolist":[]},{"isFakenote":false,"isSkynote":true,"skyjudgeNumber":2,"notetype":3,"startJudgeTime":93.65,"endJudgeTime":0.029,"xOffset":0,"speedGroup":0,"draginfolist":[]},{"isFakenote":false,"isSkynote":true,"skyjudgeNumber":1,"notetype":0,"startJudgeTime":93.822,"endJudgeTime":0.029,"xOffset":0,"speedGroup":0,"draginfolist":[]},{"isFakenote":false,"isSkynote":true,"skyjudgeNumber":4,"notetype":1,"startJudgeTime":94.167,"endJudgeTime":0.029,"xOffset":0,"speedGroup":0,"draginfolist":[]},{"isFakenote":false,"isSkynote":true,"skyjudgeNumber":2,"notetype":1,"startJudgeTime":94.684,"endJudgeTime":0.029,"xOffset":0,"speedGroup":0,"draginfolist":[]},{"isFakenote":false,"isSkynote":true,"skyjudgeNumber":3,"notetype":0,"startJudgeTime":94.339,"endJudgeTime":0.029,"xOffset":0,"speedGroup":0,"draginfolist":[]},{"isFakenote":false,"isSkynote":false,"skyjudgeNumber":0,"notetype":0,"startJudgeTime":94.857,"endJudgeTime":0.029,"xOffset":0,"speedGroup":0,"draginfolist":[]},{"isFakenote":false,"isSkynote":true,"skyjudgeNumber":3,"notetype":1,"startJudgeTime":95.374,"endJudgeTime":0.029,"xOffset":0,"speedGroup":0,"draginfolist":[]},{"isFakenote":false,"isSkynote":true,"skyjudgeNumber":4,"notetype":0,"startJudgeTime":95.891,"endJudgeTime":0.029,"xOffset":0,"speedGroup":0,"draginfolist":[]},{"isFakenote":false,"isSkynote":true,"skyjudgeNumber":1,"notetype":1,"startJudgeTime":96.063,"endJudgeTime":0.029,"xOffset":0,"speedGroup":0,"draginfolist":[]},{"isFakenote":false,"isSkynote":false,"skyjudgeNumber":0,"notetype":3,"startJudgeTime":96.236,"endJudgeTime":0.029,"xOffset":0.5,"speedGroup":0,"draginfolist":[]},{"isFakenote":false,"isSkynote":false,"skyjudgeNumber":0,"notetype":3,"startJudgeTime":96.408,"endJudgeTime":0.029,"xOffset":0.5,"speedGroup":0,"draginfolist":[]},{"isFakenote":false,"isSkynote":true,"skyjudgeNumber":2,"notetype":0,"startJudgeTime":96.581,"endJudgeTime":0.029,"xOffset":0,"speedGroup":0,"draginfolist":[]},{"isFakenote":false,"isSkynote":true,"skyjudgeNumber":4,"notetype":0,"startJudgeTime":97.098,"endJudgeTime":0.029,"xOffset":0,"speedGroup":0,"draginfolist":[]},{"isFakenote":false,"isSkynote":false,"skyjudgeNumber":0,"notetype":0,"startJudgeTime":97.615,"endJudgeTime":0.029,"xOffset":1,"speedGroup":0,"draginfolist":[]},{"isFakenote":false,"isSkynote":true,"skyjudgeNumber":3,"notetype":1,"startJudgeTime":96.926,"endJudgeTime":0.029,"xOffset":0,"speedGroup":0,"draginfolist":[]},{"isFakenote":false,"isSkynote":true,"skyjudgeNumber":1,"notetype":1,"startJudgeTime":97.443,"endJudgeTime":0.029,"xOffset":0,"speedGroup":0,"draginfolist":[]},{"isFakenote":false,"isSkynote":true,"skyjudgeNumber":4,"notetype":1,"startJudgeTime":98.132,"endJudgeTime":0.029,"xOffset":0,"speedGroup":0,"draginfolist":[]},{"isFakenote":false,"isSkynote":true,"skyjudgeNumber":3,"notetype":0,"startJudgeTime":98.65,"endJudgeTime":0.029,"xOffset":0,"speedGroup":0,"draginfolist":[]},{"isFakenote":false,"isSkynote":true,"skyjudgeNumber":3,"notetype":0,"startJudgeTime":98.995,"endJudgeTime":0.029,"xOffset":0,"speedGroup":0,"draginfolist":[]},{"isFakenote":false,"isSkynote":false,"skyjudgeNumber":0,"notetype":2,"startJudgeTime":99.339,"endJudgeTime":103.477,"xOffset":0.5,"speedGroup":0,"draginfolist":[]},{"isFakenote":false,"isSkynote":false,"skyjudgeNumber":0,"notetype":3,"startJudgeTime":103.477,"endJudgeTime":0.029,"xOffset":0.5,"speedGroup":0,"draginfolist":[]},{"isFakenote":false,"isSkynote":true,"skyjudgeNumber":2,"notetype":3,"startJudgeTime":99.167,"endJudgeTime":0.029,"xOffset":0,"speedGroup":0,"draginfolist":[]},{"isFakenote":false,"isSkynote":true,"skyjudgeNumber":2,"notetype":3,"startJudgeTime":98.822,"endJudgeTime":0.029,"xOffset":0,"speedGroup":0,"draginfolist":[]},{"isFakenote":false,"isSkynote":false,"skyjudgeNumber":0,"notetype":3,"startJudgeTime":103.995,"endJudgeTime":0.029,"xOffset":0.5,"speedGroup":0,"draginfolist":[]},{"isFakenote":false,"isSkynote":false,"skyjudgeNumber":0,"notetype":3,"startJudgeTime":104.081,"endJudgeTime":0.029,"xOffset":0.5,"speedGroup":0,"draginfolist":[]},{"isFakenote":false,"isSkynote":false,"skyjudgeNumber":0,"notetype":3,"startJudgeTime":104.167,"endJudgeTime":0.029,"xOffset":0.5,"speedGroup":0,"draginfolist":[]},{"isFakenote":false,"isSkynote":false,"skyjudgeNumber":0,"notetype":1,"startJudgeTime":104.339,"endJudgeTime":0.029,"xOffset":0.5,"speedGroup":0,"draginfolist":[]},{"isFakenote":false,"isSkynote":true,"skyjudgeNumber":2,"notetype":2,"startJudgeTime":104.857,"endJudgeTime":105.201,"xOffset":0,"speedGroup":0,"draginfolist":[]},{"isFakenote":false,"isSkynote":true,"skyjudgeNumber":3,"notetype":3,"startJudgeTime":105.201,"endJudgeTime":0.029,"xOffset":0,"speedGroup":0,"draginfolist":[{"isFakenote":false,"isSkynote":true,"skyjudgeNumber":3,"startJudgeTime":105.374,"xOffset":0,"speedGroup":0}]},{"isFakenote":false,"isSkynote":true,"skyjudgeNumber":4,"notetype":3,"startJudgeTime":105.374,"endJudgeTime":0.029,"xOffset":0,"speedGroup":0,"draginfolist":[{"isFakenote":false,"isSkynote":true,"skyjudgeNumber":4,"startJudgeTime":105.719,"xOffset":0,"speedGroup":0}]},{"isFakenote":false,"isSkynote":true,"skyjudgeNumber":1,"notetype":3,"startJudgeTime":105.719,"endJudgeTime":0.029,"xOffset":0,"speedGroup":0,"draginfolist":[{"isFakenote":false,"isSkynote":true,"skyjudgeNumber":1,"startJudgeTime":106.063,"xOffset":0,"speedGroup":0}]},{"isFakenote":false,"isSkynote":false,"skyjudgeNumber":0,"notetype":2,"startJudgeTime":106.063,"endJudgeTime":107.615,"xOffset":1,"speedGroup":0,"draginfolist":[]},{"isFakenote":false,"isSkynote":true,"skyjudgeNumber":1,"notetype":2,"startJudgeTime":107.615,"endJudgeTime":107.96,"xOffset":0,"speedGroup":0,"draginfolist":[]},{"isFakenote":false,"isSkynote":true,"skyjudgeNumber":4,"notetype":3,"startJudgeTime":107.96,"endJudgeTime":0.029,"xOffset":0,"speedGroup":0,"draginfolist":[{"isFakenote":false,"isSkynote":true,"skyjudgeNumber":4,"startJudgeTime":108.132,"xOffset":0,"speedGroup":0}]},{"isFakenote":false,"isSkynote":true,"skyjudgeNumber":3,"notetype":3,"startJudgeTime":108.132,"endJudgeTime":0.029,"xOffset":0,"speedGroup":0,"draginfolist":[{"isFakenote":false,"isSkynote":true,"skyjudgeNumber":3,"startJudgeTime":108.477,"xOffset":0,"speedGroup":0}]},{"isFakenote":false,"isSkynote":true,"skyjudgeNumber":2,"notetype":3,"startJudgeTime":108.477,"endJudgeTime":0.029,"xOffset":0,"speedGroup":0,"draginfolist":[{"isFakenote":false,"isSkynote":true,"skyjudgeNumber":2,"startJudgeTime":108.822,"xOffset":0,"speedGroup":0}]},{"isFakenote":false,"isSkynote":false,"skyjudgeNumber":0,"notetype":2,"startJudgeTime":108.822,"endJudgeTime":109.512,"xOffset":0,"speedGroup":0,"draginfolist":[]},{"isFakenote":false,"isSkynote":false,"skyjudgeNumber":0,"notetype":3,"startJudgeTime":109.512,"endJudgeTime":0.029,"xOffset":0,"speedGroup":0,"draginfolist":[{"isFakenote":false,"isSkynote":false,"skyjudgeNumber":0,"startJudgeTime":109.598,"xOffset":0,"speedGroup":0}]},{"isFakenote":false,"isSkynote":true,"skyjudgeNumber":2,"notetype":3,"startJudgeTime":109.684,"endJudgeTime":0.029,"xOffset":0,"speedGroup":0,"draginfolist":[{"isFakenote":false,"isSkynote":true,"skyjudgeNumber":2,"startJudgeTime":109.77,"xOffset":0,"speedGroup":0}]},{"isFakenote":false,"isSkynote":true,"skyjudgeNumber":3,"notetype":3,"startJudgeTime":109.857,"endJudgeTime":0.029,"xOffset":0,"speedGroup":0,"draginfolist":[{"isFakenote":false,"isSkynote":true,"skyjudgeNumber":3,"startJudgeTime":109.943,"xOffset":0,"speedGroup":0}]},{"isFakenote":false,"isSkynote":true,"skyjudgeNumber":4,"notetype":3,"startJudgeTime":110.029,"endJudgeTime":0.029,"xOffset":0,"speedGroup":0,"draginfolist":[{"isFakenote":false,"isSkynote":true,"skyjudgeNumber":4,"startJudgeTime":110.115,"xOffset":0,"speedGroup":0}]},{"isFakenote":false,"isSkynote":true,"skyjudgeNumber":1,"notetype":3,"startJudgeTime":110.201,"endJudgeTime":0.029,"xOffset":0,"speedGroup":0,"draginfolist":[{"isFakenote":false,"isSkynote":true,"skyjudgeNumber":1,"startJudgeTime":110.288,"xOffset":0,"speedGroup":0}]},{"isFakenote":false,"isSkynote":true,"skyjudgeNumber":2,"notetype":2,"startJudgeTime":110.374,"endJudgeTime":110.719,"xOffset":0,"speedGroup":0,"draginfolist":[]},{"isFakenote":false,"isSkynote":true,"skyjudgeNumber":3,"notetype":3,"startJudgeTime":110.719,"endJudgeTime":0.029,"xOffset":0,"speedGroup":0,"draginfolist":[{"isFakenote":false,"isSkynote":true,"skyjudgeNumber":3,"startJudgeTime":110.891,"xOffset":0,"speedGroup":0}]},{"isFakenote":false,"isSkynote":true,"skyjudgeNumber":4,"notetype":3,"startJudgeTime":110.891,"endJudgeTime":0.029,"xOffset":0,"speedGroup":0,"draginfolist":[{"isFakenote":false,"isSkynote":true,"skyjudgeNumber":4,"startJudgeTime":111.236,"xOffset":0,"speedGroup":0}]},{"isFakenote":false,"isSkynote":true,"skyjudgeNumber":1,"notetype":3,"startJudgeTime":111.236,"endJudgeTime":0.029,"xOffset":0,"speedGroup":0,"draginfolist":[{"isFakenote":false,"isSkynote":true,"skyjudgeNumber":1,"startJudgeTime":111.581,"xOffset":0,"speedGroup":0}]},{"isFakenote":false,"isSkynote":false,"skyjudgeNumber":0,"notetype":2,"startJudgeTime":111.581,"endJudgeTime":113.132,"xOffset":1,"speedGroup":0,"draginfolist":[]},{"isFakenote":false,"isSkynote":true,"skyjudgeNumber":1,"notetype":2,"startJudgeTime":113.132,"endJudgeTime":113.477,"xOffset":0,"speedGroup":0,"draginfolist":[]},{"isFakenote":false,"isSkynote":true,"skyjudgeNumber":4,"notetype":3,"startJudgeTime":113.477,"endJudgeTime":0.029,"xOffset":0,"speedGroup":0,"draginfolist":[{"isFakenote":false,"isSkynote":true,"skyjudgeNumber":4,"startJudgeTime":113.65,"xOffset":0,"speedGroup":0}]},{"isFakenote":false,"isSkynote":true,"skyjudgeNumber":3,"notetype":3,"startJudgeTime":113.65,"endJudgeTime":0.029,"xOffset":0,"speedGroup":0,"draginfolist":[{"isFakenote":false,"isSkynote":true,"skyjudgeNumber":3,"startJudgeTime":113.995,"xOffset":0,"speedGroup":0}]},{"isFakenote":false,"isSkynote":true,"skyjudgeNumber":2,"notetype":3,"startJudgeTime":113.995,"endJudgeTime":0.029,"xOffset":0,"speedGroup":0,"draginfolist":[{"isFakenote":false,"isSkynote":true,"skyjudgeNumber":2,"startJudgeTime":114.167,"xOffset":0,"speedGroup":0},{"isFakenote":false,"isSkynote":true,"skyjudgeNumber":2,"startJudgeTime":114.339,"xOffset":0,"speedGroup":0}]},{"isFakenote":false,"isSkynote":false,"skyjudgeNumber":0,"notetype":2,"startJudgeTime":114.339,"endJudgeTime":114.857,"xOffset":0,"speedGroup":0,"draginfolist":[]},{"isFakenote":false,"isSkynote":false,"skyjudgeNumber":0,"notetype":3,"startJudgeTime":114.857,"endJudgeTime":0.029,"xOffset":0,"speedGroup":0,"draginfolist":[{"isFakenote":false,"isSkynote":false,"skyjudgeNumber":0,"startJudgeTime":114.943,"xOffset":0,"speedGroup":0}]},{"isFakenote":false,"isSkynote":true,"skyjudgeNumber":2,"notetype":3,"startJudgeTime":115.029,"endJudgeTime":0.029,"xOffset":0,"speedGroup":0,"draginfolist":[{"isFakenote":false,"isSkynote":true,"skyjudgeNumber":2,"startJudgeTime":115.115,"xOffset":0,"speedGroup":0}]},{"isFakenote":false,"isSkynote":true,"skyjudgeNumber":3,"notetype":3,"startJudgeTime":115.201,"endJudgeTime":0.029,"xOffset":0,"speedGroup":0,"draginfolist":[{"isFakenote":false,"isSkynote":true,"skyjudgeNumber":3,"startJudgeTime":115.288,"xOffset":0,"speedGroup":0}]},{"isFakenote":false,"isSkynote":true,"skyjudgeNumber":4,"notetype":3,"startJudgeTime":115.374,"endJudgeTime":0.029,"xOffset":0,"speedGroup":0,"draginfolist":[{"isFakenote":false,"isSkynote":true,"skyjudgeNumber":4,"startJudgeTime":115.46,"xOffset":0,"speedGroup":0}]},{"isFakenote":false,"isSkynote":true,"skyjudgeNumber":1,"notetype":3,"startJudgeTime":115.546,"endJudgeTime":0.029,"xOffset":0,"speedGroup":0,"draginfolist":[{"isFakenote":false,"isSkynote":true,"skyjudgeNumber":1,"startJudgeTime":115.632,"xOffset":0,"speedGroup":0}]},{"isFakenote":false,"isSkynote":false,"skyjudgeNumber":0,"notetype":3,"startJudgeTime":115.719,"endJudgeTime":0.029,"xOffset":1,"speedGroup":0,"draginfolist":[{"isFakenote":false,"isSkynote":false,"skyjudgeNumber":0,"startJudgeTime":115.805,"xOffset":1,"speedGroup":0}]},{"isFakenote":false,"isSkynote":true,"skyjudgeNumber":1,"notetype":2,"startJudgeTime":115.891,"endJudgeTime":116.236,"xOffset":0,"speedGroup":0,"draginfolist":[]},{"isFakenote":false,"isSkynote":true,"skyjudgeNumber":4,"notetype":2,"startJudgeTime":116.236,"endJudgeTime":116.408,"xOffset":0,"speedGroup":0,"draginfolist":[]},{"isFakenote":false,"isSkynote":true,"skyjudgeNumber":3,"notetype":2,"startJudgeTime":116.408,"endJudgeTime":116.753,"xOffset":0,"speedGroup":0,"draginfolist":[]},{"isFakenote":false,"isSkynote":true,"skyjudgeNumber":2,"notetype":2,"startJudgeTime":116.753,"endJudgeTime":117.098,"xOffset":0,"speedGroup":0,"draginfolist":[]},{"isFakenote":false,"isSkynote":false,"skyjudgeNumber":0,"notetype":2,"startJudgeTime":117.098,"endJudgeTime":117.788,"xOffset":0,"speedGroup":0,"draginfolist":[]},{"isFakenote":false,"isSkynote":false,"skyjudgeNumber":0,"notetype":3,"startJudgeTime":117.788,"endJudgeTime":0.029,"xOffset":0,"speedGroup":0,"draginfolist":[{"isFakenote":false,"isSkynote":false,"skyjudgeNumber":0,"startJudgeTime":117.874,"xOffset":0,"speedGroup":0}]},{"isFakenote":false,"isSkynote":true,"skyjudgeNumber":2,"notetype":3,"startJudgeTime":117.96,"endJudgeTime":0.029,"xOffset":0,"speedGroup":0,"draginfolist":[{"isFakenote":false,"isSkynote":true,"skyjudgeNumber":2,"startJudgeTime":118.046,"xOffset":0,"speedGroup":0}]},{"isFakenote":false,"isSkynote":true,"skyjudgeNumber":3,"notetype":3,"startJudgeTime":118.132,"endJudgeTime":0.029,"xOffset":0,"speedGroup":0,"draginfolist":[{"isFakenote":false,"isSkynote":true,"skyjudgeNumber":3,"startJudgeTime":118.219,"xOffset":0,"speedGroup":0}]},{"isFakenote":false,"isSkynote":true,"skyjudgeNumber":4,"notetype":3,"startJudgeTime":118.305,"endJudgeTime":0.029,"xOffset":0,"speedGroup":0,"draginfolist":[{"isFakenote":false,"isSkynote":true,"skyjudgeNumber":4,"startJudgeTime":118.477,"xOffset":0,"speedGroup":0}]},{"isFakenote":false,"isSkynote":true,"skyjudgeNumber":1,"notetype":3,"startJudgeTime":118.477,"endJudgeTime":0.029,"xOffset":0,"speedGroup":0,"draginfolist":[{"isFakenote":false,"isSkynote":true,"skyjudgeNumber":1,"startJudgeTime":118.65,"xOffset":0,"speedGroup":0}]},{"isFakenote":false,"isSkynote":true,"skyjudgeNumber":2,"notetype":2,"startJudgeTime":118.65,"endJudgeTime":118.995,"xOffset":0,"speedGroup":0,"draginfolist":[]},{"isFakenote":false,"isSkynote":true,"skyjudgeNumber":3,"notetype":2,"startJudgeTime":118.995,"endJudgeTime":119.167,"xOffset":0,"speedGroup":0,"draginfolist":[]},{"isFakenote":false,"isSkynote":true,"skyjudgeNumber":4,"notetype":2,"startJudgeTime":119.167,"endJudgeTime":119.512,"xOffset":0,"speedGroup":0,"draginfolist":[]},{"isFakenote":false,"isSkynote":true,"skyjudgeNumber":1,"notetype":2,"startJudgeTime":119.512,"endJudgeTime":119.857,"xOffset":0,"speedGroup":0,"draginfolist":[]},{"isFakenote":false,"isSkynote":false,"skyjudgeNumber":0,"notetype":2,"startJudgeTime":119.857,"endJudgeTime":120.374,"xOffset":1,"speedGroup":0,"draginfolist":[]},{"isFakenote":false,"isSkynote":false,"skyjudgeNumber":0,"notetype":3,"startJudgeTime":120.374,"endJudgeTime":0.029,"xOffset":1,"speedGroup":0,"draginfolist":[{"isFakenote":false,"isSkynote":false,"skyjudgeNumber":0,"startJudgeTime":120.46,"xOffset":1,"speedGroup":0}]},{"isFakenote":false,"isSkynote":true,"skyjudgeNumber":1,"notetype":3,"startJudgeTime":120.546,"endJudgeTime":0.029,"xOffset":0,"speedGroup":0,"draginfolist":[{"isFakenote":false,"isSkynote":true,"skyjudgeNumber":1,"startJudgeTime":120.632,"xOffset":0,"speedGroup":0}]},{"isFakenote":false,"isSkynote":true,"skyjudgeNumber":4,"notetype":3,"startJudgeTime":120.719,"endJudgeTime":0.029,"xOffset":0,"speedGroup":0,"draginfolist":[{"isFakenote":false,"isSkynote":true,"skyjudgeNumber":4,"startJudgeTime":120.805,"xOffset":0,"speedGroup":0}]},{"isFakenote":false,"isSkynote":true,"skyjudgeNumber":3,"notetype":3,"startJudgeTime":120.891,"endJudgeTime":0.029,"xOffset":0,"speedGroup":0,"draginfolist":[{"isFakenote":false,"isSkynote":true,"skyjudgeNumber":3,"startJudgeTime":120.977,"xOffset":0,"speedGroup":0}]},{"isFakenote":false,"isSkynote":true,"skyjudgeNumber":2,"notetype":3,"startJudgeTime":121.063,"endJudgeTime":0.029,"xOffset":0,"speedGroup":0,"draginfolist":[{"isFakenote":false,"isSkynote":true,"skyjudgeNumber":2,"startJudgeTime":121.15,"xOffset":0,"speedGroup":0}]},{"isFakenote":false,"isSkynote":false,"skyjudgeNumber":0,"notetype":3,"startJudgeTime":121.236,"endJudgeTime":0.029,"xOffset":0,"speedGroup":0,"draginfolist":[{"isFakenote":false,"isSkynote":false,"skyjudgeNumber":0,"startJudgeTime":121.322,"xOffset":0,"speedGroup":0}]},{"isFakenote":false,"isSkynote":false,"skyjudgeNumber":0,"notetype":1,"startJudgeTime":121.408,"endJudgeTime":0.029,"xOffset":0,"speedGroup":0,"draginfolist":[]},{"isFakenote":false,"isSkynote":true,"skyjudgeNumber":2,"notetype":0,"startJudgeTime":121.408,"endJudgeTime":0.029,"xOffset":0,"speedGroup":0,"draginfolist":[]},{"isFakenote":false,"isSkynote":true,"skyjudgeNumber":2,"notetype":1,"startJudgeTime":121.926,"endJudgeTime":0.029,"xOffset":0,"speedGroup":0,"draginfolist":[]},{"isFakenote":false,"isSkynote":true,"skyjudgeNumber":3,"notetype":1,"startJudgeTime":122.443,"endJudgeTime":0.029,"xOffset":0,"speedGroup":0,"draginfolist":[]},{"isFakenote":false,"isSkynote":true,"skyjudgeNumber":4,"notetype":1,"startJudgeTime":122.96,"endJudgeTime":0.029,"xOffset":0,"speedGroup":0,"draginfolist":[]},{"isFakenote":false,"isSkynote":true,"skyjudgeNumber":1,"notetype":1,"startJudgeTime":123.477,"endJudgeTime":0.029,"xOffset":0,"speedGroup":0,"draginfolist":[]},{"isFakenote":false,"isSkynote":false,"skyjudgeNumber":0,"notetype":1,"startJudgeTime":123.995,"endJudgeTime":0.029,"xOffset":1,"speedGroup":0,"draginfolist":[]},{"isFakenote":false,"isSkynote":true,"skyjudgeNumber":3,"notetype":1,"startJudgeTime":124.512,"endJudgeTime":0.029,"xOffset":0,"speedGroup":0,"draginfolist":[]},{"isFakenote":false,"isSkynote":true,"skyjudgeNumber":4,"notetype":1,"startJudgeTime":125.029,"endJudgeTime":0.029,"xOffset":0,"speedGroup":0,"draginfolist":[]},{"isFakenote":false,"isSkynote":true,"skyjudgeNumber":3,"notetype":1,"startJudgeTime":125.374,"endJudgeTime":0.029,"xOffset":0,"speedGroup":0,"draginfolist":[]},{"isFakenote":false,"isSkynote":true,"skyjudgeNumber":3,"notetype":0,"startJudgeTime":121.926,"endJudgeTime":0.029,"xOffset":0,"speedGroup":0,"draginfolist":[]},{"isFakenote":false,"isSkynote":true,"skyjudgeNumber":4,"notetype":0,"startJudgeTime":122.443,"endJudgeTime":0.029,"xOffset":0,"speedGroup":0,"draginfolist":[]},{"isFakenote":false,"isSkynote":true,"skyjudgeNumber":1,"notetype":0,"startJudgeTime":122.96,"endJudgeTime":0.029,"xOffset":0,"speedGroup":0,"draginfolist":[]},{"isFakenote":false,"isSkynote":false,"skyjudgeNumber":0,"notetype":0,"startJudgeTime":123.477,"endJudgeTime":0.029,"xOffset":1,"speedGroup":0,"draginfolist":[]},{"isFakenote":false,"isSkynote":true,"skyjudgeNumber":3,"notetype":0,"startJudgeTime":123.995,"endJudgeTime":0.029,"xOffset":0,"speedGroup":0,"draginfolist":[]},{"isFakenote":false,"isSkynote":true,"skyjudgeNumber":4,"notetype":0,"startJudgeTime":124.512,"endJudgeTime":0.029,"xOffset":0,"speedGroup":0,"draginfolist":[]},{"isFakenote":false,"isSkynote":true,"skyjudgeNumber":3,"notetype":0,"startJudgeTime":125.029,"endJudgeTime":0.029,"xOffset":0,"speedGroup":0,"draginfolist":[]},{"isFakenote":false,"isSkynote":true,"skyjudgeNumber":4,"notetype":0,"startJudgeTime":125.374,"endJudgeTime":0.029,"xOffset":0,"speedGroup":0,"draginfolist":[]},{"isFakenote":false,"isSkynote":true,"skyjudgeNumber":2,"notetype":3,"startJudgeTime":121.581,"endJudgeTime":0.029,"xOffset":0,"speedGroup":0,"draginfolist":[]},{"isFakenote":false,"isSkynote":true,"skyjudgeNumber":2,"notetype":3,"startJudgeTime":121.753,"endJudgeTime":0.029,"xOffset":0,"speedGroup":0,"draginfolist":[]},{"isFakenote":false,"isSkynote":true,"skyjudgeNumber":3,"notetype":3,"startJudgeTime":122.098,"endJudgeTime":0.029,"xOffset":0,"speedGroup":0,"draginfolist":[]},{"isFakenote":false,"isSkynote":true,"skyjudgeNumber":3,"notetype":3,"startJudgeTime":122.27,"endJudgeTime":0.029,"xOffset":0,"speedGroup":0,"draginfolist":[]},{"isFakenote":false,"isSkynote":true,"skyjudgeNumber":4,"notetype":3,"startJudgeTime":122.615,"endJudgeTime":0.029,"xOffset":0,"speedGroup":0,"draginfolist":[]},{"isFakenote":false,"isSkynote":true,"skyjudgeNumber":4,"notetype":3,"startJudgeTime":122.788,"endJudgeTime":0.029,"xOffset":0,"speedGroup":0,"draginfolist":[]},{"isFakenote":false,"isSkynote":true,"skyjudgeNumber":1,"notetype":3,"startJudgeTime":123.132,"endJudgeTime":0.029,"xOffset":0,"speedGroup":0,"draginfolist":[]},{"isFakenote":false,"isSkynote":true,"skyjudgeNumber":1,"notetype":3,"startJudgeTime":123.305,"endJudgeTime":0.029,"xOffset":0,"speedGroup":0,"draginfolist":[]},{"isFakenote":false,"isSkynote":false,"skyjudgeNumber":0,"notetype":3,"startJudgeTime":123.65,"endJudgeTime":0.029,"xOffset":1,"speedGroup":0,"draginfolist":[]},{"isFakenote":false,"isSkynote":false,"skyjudgeNumber":0,"notetype":3,"startJudgeTime":123.822,"endJudgeTime":0.029,"xOffset":1,"speedGroup":0,"draginfolist":[]},{"isFakenote":false,"isSkynote":true,"skyjudgeNumber":3,"notetype":3,"startJudgeTime":124.167,"endJudgeTime":0.029,"xOffset":0,"speedGroup":0,"draginfolist":[]},{"isFakenote":false,"isSkynote":true,"skyjudgeNumber":3,"notetype":3,"startJudgeTime":124.339,"endJudgeTime":0.029,"xOffset":0,"speedGroup":0,"draginfolist":[]},{"isFakenote":false,"isSkynote":true,"skyjudgeNumber":4,"notetype":3,"startJudgeTime":124.684,"endJudgeTime":0.029,"xOffset":0,"speedGroup":0,"draginfolist":[]},{"isFakenote":false,"isSkynote":true,"skyjudgeNumber":3,"notetype":3,"startJudgeTime":125.201,"endJudgeTime":0.029,"xOffset":0,"speedGroup":0,"draginfolist":[]},{"isFakenote":false,"isSkynote":true,"skyjudgeNumber":4,"notetype":3,"startJudgeTime":124.77,"endJudgeTime":0.029,"xOffset":0,"speedGroup":0,"draginfolist":[]},{"isFakenote":false,"isSkynote":true,"skyjudgeNumber":4,"notetype":3,"startJudgeTime":124.857,"endJudgeTime":0.029,"xOffset":0,"speedGroup":0,"draginfolist":[]},{"isFakenote":false,"isSkynote":true,"skyjudgeNumber":1,"notetype":3,"startJudgeTime":126.926,"endJudgeTime":0.029,"xOffset":0,"speedGroup":0,"draginfolist":[{"isFakenote":false,"isSkynote":true,"skyjudgeNumber":1,"startJudgeTime":127.098,"xOffset":0,"speedGroup":0},{"isFakenote":false,"isSkynote":true,"skyjudgeNumber":1,"startJudgeTime":127.27,"xOffset":0,"speedGroup":0},{"isFakenote":false,"isSkynote":true,"skyjudgeNumber":1,"startJudgeTime":127.443,"xOffset":0,"speedGroup":0},{"isFakenote":false,"isSkynote":true,"skyjudgeNumber":3,"startJudgeTime":127.788,"xOffset":0,"speedGroup":0},{"isFakenote":false,"isSkynote":true,"skyjudgeNumber":3,"startJudgeTime":127.96,"xOffset":0,"speedGroup":0},{"isFakenote":false,"isSkynote":true,"skyjudgeNumber":3,"startJudgeTime":128.132,"xOffset":0,"speedGroup":0},{"isFakenote":false,"isSkynote":false,"skyjudgeNumber":0,"startJudgeTime":129.167,"xOffset":0,"speedGroup":0},{"isFakenote":false,"isSkynote":false,"skyjudgeNumber":0,"startJudgeTime":129.339,"xOffset":0,"speedGroup":0},{"isFakenote":false,"isSkynote":false,"skyjudgeNumber":0,"startJudgeTime":129.512,"xOffset":0,"speedGroup":0}]},{"isFakenote":false,"isSkynote":true,"skyjudgeNumber":2,"notetype":3,"startJudgeTime":129.684,"endJudgeTime":0.029,"xOffset":0,"speedGroup":0,"draginfolist":[{"isFakenote":false,"isSkynote":true,"skyjudgeNumber":2,"startJudgeTime":129.857,"xOffset":0,"speedGroup":0},{"isFakenote":false,"isSkynote":true,"skyjudgeNumber":2,"startJudgeTime":130.029,"xOffset":0,"speedGroup":0},{"isFakenote":false,"isSkynote":true,"skyjudgeNumber":2,"startJudgeTime":130.201,"xOffset":0,"speedGroup":0},{"isFakenote":false,"isSkynote":true,"skyjudgeNumber":4,"startJudgeTime":130.546,"xOffset":0,"speedGroup":0},{"isFakenote":false,"isSkynote":true,"skyjudgeNumber":4,"startJudgeTime":130.719,"xOffset":0,"speedGroup":0},{"isFakenote":false,"isSkynote":true,"skyjudgeNumber":4,"startJudgeTime":130.891,"xOffset":0,"speedGroup":0},{"isFakenote":false,"isSkynote":false,"skyjudgeNumber":0,"startJudgeTime":131.926,"xOffset":1,"speedGroup":0},{"isFakenote":false,"isSkynote":false,"skyjudgeNumber":0,"startJudgeTime":132.098,"xOffset":1,"speedGroup":0},{"isFakenote":false,"isSkynote":false,"skyjudgeNumber":0,"startJudgeTime":132.27,"xOffset":1,"speedGroup":0}]},{"isFakenote":false,"isSkynote":true,"skyjudgeNumber":1,"notetype":3,"startJudgeTime":132.443,"endJudgeTime":0.029,"xOffset":0,"speedGroup":0,"draginfolist":[{"isFakenote":false,"isSkynote":true,"skyjudgeNumber":1,"startJudgeTime":132.615,"xOffset":0,"speedGroup":0},{"isFakenote":false,"isSkynote":true,"skyjudgeNumber":1,"startJudgeTime":132.788,"xOffset":0,"speedGroup":0},{"isFakenote":false,"isSkynote":true,"skyjudgeNumber":1,"startJudgeTime":132.96,"xOffset":0,"speedGroup":0},{"isFakenote":false,"isSkynote":true,"skyjudgeNumber":3,"startJudgeTime":133.305,"xOffset":0,"speedGroup":0},{"isFakenote":false,"isSkynote":true,"skyjudgeNumber":3,"startJudgeTime":133.477,"xOffset":0,"speedGroup":0},{"isFakenote":false,"isSkynote":true,"skyjudgeNumber":3,"startJudgeTime":133.65,"xOffset":0,"speedGroup":0},{"isFakenote":false,"isSkynote":false,"skyjudgeNumber":0,"startJudgeTime":134.684,"xOffset":0,"speedGroup":0},{"isFakenote":false,"isSkynote":false,"skyjudgeNumber":0,"startJudgeTime":134.857,"xOffset":0,"speedGroup":0},{"isFakenote":false,"isSkynote":false,"skyjudgeNumber":0,"startJudgeTime":135.029,"xOffset":0,"speedGroup":0}]},{"isFakenote":false,"isSkynote":true,"skyjudgeNumber":2,"notetype":3,"startJudgeTime":135.201,"endJudgeTime":0.029,"xOffset":0,"speedGroup":0,"draginfolist":[{"isFakenote":false,"isSkynote":true,"skyjudgeNumber":2,"startJudgeTime":137.96,"xOffset":0,"speedGroup":0}]}],"speedGroupInGames":[{"speedGroupNumber":0,"time":[0.029,23.477,23.477,24.857,24.857,46.926,46.926,52.443,52.443,57.96,57.96,58.132,58.132,58.305,58.305,66.236,66.581,66.581,66.753,67.098,67.098,67.27,67.615,67.615,67.788,68.132,68.132,71.753,72.27,72.27,72.615,72.615,73.132,73.132,73.65,73.65,74.167,74.167,80.029,80.029,89.684,91.063,125.374,126.926,135.201,135.201,114514],"speed":[7.5,7.5,2.5,2.5,10,10,7.5,7.5,10,10,20,20,5,0,10,10,2.5,10,10,2.5,10,10,2.5,10,10,2.5,10,10,2.5,10,2.5,10,2.5,10,2.5,10,2.5,10,10,5,5,10,10,5,5,1,1]},{"speedGroupNumber":1,"time":[0.029,46.236,46.926,46.926,52.443,55.891,55.891,79.339,80.029,114514],"speed":[-10,-10,10,-10,-10,10,-10,-10,10,10]},{"speedGroupNumber":2,"time":[0.029,52.96,55.374,114514],"speed":[-10,-10,10,10]},{"speedGroupNumber":3,"time":[0.029,53.477,55.201,114514],"speed":[-10,-10,10,10]},{"speedGroupNumber":4,"time":[0.029,57.615,57.615,57.96,114514],"speed":[10,10,-10,20,20]},{"speedGroupNumber":5,"time":[0.029,46.926,46.926,49.684,49.684,114514],"speed":[10,10,-2.5,2.5,7.5,7.5]}]}