{"chartInfos":{"levelName":"if(爱>365)","bpm":"110","composer":"闫东炜","designer":"Haski","level":"FL","chartID":"90901"},"noteLists":[{"isFakenote":false,"isSkynote":true,"skyjudgeNumber":3,"notetype":2,"startJudgeTime":0.029,"endJudgeTime":2.211,"xOffset":0,"speedGroup":0,"draginfolist":[]},{"isFakenote":false,"isSkynote":true,"skyjudgeNumber":3,"notetype":3,"startJudgeTime":0.574,"endJudgeTime":0.029,"xOffset":0,"speedGroup":0,"draginfolist":[]},{"isFakenote":false,"isSkynote":true,"skyjudgeNumber":3,"notetype":3,"startJudgeTime":1.393,"endJudgeTime":0.029,"xOffset":0,"speedGroup":0,"draginfolist":[]},{"isFakenote":false,"isSkynote":true,"skyjudgeNumber":3,"notetype":3,"startJudgeTime":1.12,"endJudgeTime":0.029,"xOffset":0,"speedGroup":0,"draginfolist":[]},{"isFakenote":false,"isSkynote":true,"skyjudgeNumber":3,"notetype":3,"startJudgeTime":1.938,"endJudgeTime":0.029,"xOffset":0,"speedGroup":0,"draginfolist":[]},{"isFakenote":false,"isSkynote":true,"skyjudgeNumber":1,"notetype":3,"startJudgeTime":43.665,"endJudgeTime":0.029,"xOffset":0,"speedGroup":0,"draginfolist":[{"isFakenote":false,"isSkynote":true,"skyjudgeNumber":1,"startJudgeTime":43.938,"xOffset":0,"speedGroup":0},{"isFakenote":false,"isSkynote":true,"skyjudgeNumber":1,"startJudgeTime":44.211,"xOffset":0,"speedGroup":0},{"isFakenote":false,"isSkynote":true,"skyjudgeNumber":3,"startJudgeTime":45.574,"xOffset":0,"speedGroup":0},{"isFakenote":false,"isSkynote":true,"skyjudgeNumber":1,"startJudgeTime":45.847,"xOffset":0,"speedGroup":0},{"isFakenote":false,"isSkynote":true,"skyjudgeNumber":1,"startJudgeTime":46.256,"xOffset":0,"speedGroup":0},{"isFakenote":false,"isSkynote":true,"skyjudgeNumber":3,"startJudgeTime":48.029,"xOffset":0,"speedGroup":0},{"isFakenote":false,"isSkynote":true,"skyjudgeNumber":1,"startJudgeTime":49.12,"xOffset":0,"speedGroup":0},{"isFakenote":false,"isSkynote":true,"skyjudgeNumber":1,"startJudgeTime":49.484,"xOffset":0,"speedGroup":0},{"isFakenote":false,"isSkynote":true,"skyjudgeNumber":1,"startJudgeTime":49.847,"xOffset":0,"speedGroup":0},{"isFakenote":false,"isSkynote":true,"skyjudgeNumber":1,"startJudgeTime":50.211,"xOffset":0,"speedGroup":0},{"isFakenote":false,"isSkynote":true,"skyjudgeNumber":3,"startJudgeTime":52.393,"xOffset":0,"speedGroup":0},{"isFakenote":false,"isSkynote":false,"skyjudgeNumber":0,"startJudgeTime":52.938,"xOffset":0,"speedGroup":0},{"isFakenote":false,"isSkynote":false,"skyjudgeNumber":0,"startJudgeTime":53.211,"xOffset":0,"speedGroup":0},{"isFakenote":false,"isSkynote":true,"skyjudgeNumber":3,"startJudgeTime":53.484,"xOffset":0,"speedGroup":0},{"isFakenote":false,"isSkynote":true,"skyjudgeNumber":3,"startJudgeTime":53.893,"xOffset":0,"speedGroup":0},{"isFakenote":false,"isSkynote":true,"skyjudgeNumber":3,"startJudgeTime":54.302,"xOffset":0,"speedGroup":0},{"isFakenote":false,"isSkynote":true,"skyjudgeNumber":1,"startJudgeTime":54.574,"xOffset":0,"speedGroup":0},{"isFakenote":false,"isSkynote":true,"skyjudgeNumber":3,"startJudgeTime":55.393,"xOffset":0,"speedGroup":0},{"isFakenote":false,"isSkynote":true,"skyjudgeNumber":1,"startJudgeTime":56.484,"xOffset":0,"speedGroup":0},{"isFakenote":false,"isSkynote":true,"skyjudgeNumber":3,"startJudgeTime":56.756,"xOffset":0,"speedGroup":0},{"isFakenote":false,"isSkynote":false,"skyjudgeNumber":0,"startJudgeTime":57.165,"xOffset":0,"speedGroup":0},{"isFakenote":false,"isSkynote":true,"skyjudgeNumber":3,"startJudgeTime":57.574,"xOffset":0,"speedGroup":0},{"isFakenote":false,"isSkynote":false,"skyjudgeNumber":0,"startJudgeTime":57.847,"xOffset":0,"speedGroup":0},{"isFakenote":false,"isSkynote":false,"skyjudgeNumber":0,"startJudgeTime":58.393,"xOffset":0,"speedGroup":0}]},{"isFakenote":false,"isSkynote":true,"skyjudgeNumber":2,"notetype":3,"startJudgeTime":44.484,"endJudgeTime":0.029,"xOffset":0,"speedGroup":0,"draginfolist":[{"isFakenote":false,"isSkynote":true,"skyjudgeNumber":2,"startJudgeTime":44.756,"xOffset":0,"speedGroup":0},{"isFakenote":false,"isSkynote":true,"skyjudgeNumber":4,"startJudgeTime":45.165,"xOffset":0,"speedGroup":0},{"isFakenote":false,"isSkynote":true,"skyjudgeNumber":4,"startJudgeTime":45.574,"xOffset":0,"speedGroup":0},{"isFakenote":false,"isSkynote":true,"skyjudgeNumber":4,"startJudgeTime":45.574,"xOffset":0,"speedGroup":0},{"isFakenote":false,"isSkynote":true,"skyjudgeNumber":2,"startJudgeTime":45.847,"xOffset":0,"speedGroup":0},{"isFakenote":false,"isSkynote":true,"skyjudgeNumber":2,"startJudgeTime":46.256,"xOffset":0,"speedGroup":0},{"isFakenote":false,"isSkynote":true,"skyjudgeNumber":4,"startJudgeTime":48.029,"xOffset":0,"speedGroup":0}]},{"isFakenote":false,"isSkynote":true,"skyjudgeNumber":4,"notetype":2,"startJudgeTime":2.211,"endJudgeTime":4.393,"xOffset":0,"speedGroup":0,"draginfolist":[]},{"isFakenote":false,"isSkynote":true,"skyjudgeNumber":4,"notetype":3,"startJudgeTime":2.756,"endJudgeTime":0.029,"xOffset":0,"speedGroup":0,"draginfolist":[]},{"isFakenote":false,"isSkynote":true,"skyjudgeNumber":1,"notetype":2,"startJudgeTime":4.393,"endJudgeTime":6.574,"xOffset":0,"speedGroup":0,"draginfolist":[]},{"isFakenote":false,"isSkynote":true,"skyjudgeNumber":2,"notetype":2,"startJudgeTime":6.574,"endJudgeTime":8.756,"xOffset":0,"speedGroup":0,"draginfolist":[]},{"isFakenote":false,"isSkynote":true,"skyjudgeNumber":3,"notetype":3,"startJudgeTime":8.756,"endJudgeTime":0.029,"xOffset":0,"speedGroup":0,"draginfolist":[{"isFakenote":false,"isSkynote":true,"skyjudgeNumber":1,"startJudgeTime":9.302,"xOffset":0,"speedGroup":0},{"isFakenote":false,"isSkynote":true,"skyjudgeNumber":1,"startJudgeTime":9.847,"xOffset":0,"speedGroup":0},{"isFakenote":false,"isSkynote":true,"skyjudgeNumber":1,"startJudgeTime":10.12,"xOffset":0,"speedGroup":0},{"isFakenote":false,"isSkynote":true,"skyjudgeNumber":1,"startJudgeTime":10.665,"xOffset":0,"speedGroup":0},{"isFakenote":false,"isSkynote":true,"skyjudgeNumber":1,"startJudgeTime":10.938,"xOffset":0,"speedGroup":0},{"isFakenote":false,"isSkynote":true,"skyjudgeNumber":3,"startJudgeTime":13.12,"xOffset":0,"speedGroup":0},{"isFakenote":false,"isSkynote":true,"skyjudgeNumber":3,"startJudgeTime":14.211,"xOffset":0,"speedGroup":0}]},{"isFakenote":false,"isSkynote":true,"skyjudgeNumber":4,"notetype":3,"startJudgeTime":10.938,"endJudgeTime":0.029,"xOffset":0,"speedGroup":0,"draginfolist":[{"isFakenote":false,"isSkynote":true,"skyjudgeNumber":2,"startJudgeTime":11.484,"xOffset":0,"speedGroup":0},{"isFakenote":false,"isSkynote":true,"skyjudgeNumber":2,"startJudgeTime":13.12,"xOffset":0,"speedGroup":0},{"isFakenote":false,"isSkynote":true,"skyjudgeNumber":4,"startJudgeTime":14.211,"xOffset":0,"speedGroup":0}]},{"isFakenote":false,"isSkynote":true,"skyjudgeNumber":3,"notetype":2,"startJudgeTime":15.302,"endJudgeTime":16.12,"xOffset":0,"speedGroup":0,"draginfolist":[]},{"isFakenote":false,"isSkynote":true,"skyjudgeNumber":4,"notetype":2,"startJudgeTime":15.302,"endJudgeTime":16.12,"xOffset":0,"speedGroup":0,"draginfolist":[]},{"isFakenote":false,"isSkynote":false,"skyjudgeNumber":0,"notetype":2,"startJudgeTime":16.393,"endJudgeTime":17.211,"xOffset":0,"speedGroup":0,"draginfolist":[]},{"isFakenote":false,"isSkynote":false,"skyjudgeNumber":0,"notetype":2,"startJudgeTime":16.393,"endJudgeTime":17.211,"xOffset":1,"speedGroup":0,"draginfolist":[]},{"isFakenote":false,"isSkynote":false,"skyjudgeNumber":0,"notetype":3,"startJudgeTime":16.484,"endJudgeTime":0.029,"xOffset":0,"speedGroup":0,"draginfolist":[]},{"isFakenote":false,"isSkynote":false,"skyjudgeNumber":0,"notetype":3,"startJudgeTime":16.574,"endJudgeTime":0.029,"xOffset":0,"speedGroup":0,"draginfolist":[]},{"isFakenote":false,"isSkynote":false,"skyjudgeNumber":0,"notetype":3,"startJudgeTime":16.665,"endJudgeTime":0.029,"xOffset":0,"speedGroup":0,"draginfolist":[]},{"isFakenote":false,"isSkynote":false,"skyjudgeNumber":0,"notetype":3,"startJudgeTime":16.756,"endJudgeTime":0.029,"xOffset":0,"speedGroup":0,"draginfolist":[]},{"isFakenote":false,"isSkynote":false,"skyjudgeNumber":0,"notetype":3,"startJudgeTime":16.847,"endJudgeTime":0.029,"xOffset":0,"speedGroup":0,"draginfolist":[]},{"isFakenote":false,"isSkynote":false,"skyjudgeNumber":0,"notetype":3,"startJudgeTime":16.938,"endJudgeTime":0.029,"xOffset":0,"speedGroup":0,"draginfolist":[]},{"isFakenote":false,"isSkynote":false,"skyjudgeNumber":0,"notetype":3,"startJudgeTime":17.029,"endJudgeTime":0.029,"xOffset":0,"speedGroup":0,"draginfolist":[]},{"isFakenote":false,"isSkynote":false,"skyjudgeNumber":0,"notetype":3,"startJudgeTime":17.12,"endJudgeTime":0.029,"xOffset":0,"speedGroup":0,"draginfolist":[]},{"isFakenote":false,"isSkynote":false,"skyjudgeNumber":0,"notetype":3,"startJudgeTime":16.484,"endJudgeTime":0.029,"xOffset":1,"speedGroup":0,"draginfolist":[]},{"isFakenote":false,"isSkynote":false,"skyjudgeNumber":0,"notetype":3,"startJudgeTime":16.574,"endJudgeTime":0.029,"xOffset":1,"speedGroup":0,"draginfolist":[]},{"isFakenote":false,"isSkynote":false,"skyjudgeNumber":0,"notetype":3,"startJudgeTime":16.665,"endJudgeTime":0.029,"xOffset":0.9803241,"speedGroup":0,"draginfolist":[]},{"isFakenote":false,"isSkynote":false,"skyjudgeNumber":0,"notetype":3,"startJudgeTime":16.756,"endJudgeTime":0.029,"xOffset":0.9936762,"speedGroup":0,"draginfolist":[]},{"isFakenote":false,"isSkynote":false,"skyjudgeNumber":0,"notetype":3,"startJudgeTime":16.938,"endJudgeTime":0.029,"xOffset":0.987001,"speedGroup":0,"draginfolist":[]},{"isFakenote":false,"isSkynote":false,"skyjudgeNumber":0,"notetype":3,"startJudgeTime":17.029,"endJudgeTime":0.029,"xOffset":1,"speedGroup":0,"draginfolist":[]},{"isFakenote":false,"isSkynote":false,"skyjudgeNumber":0,"notetype":3,"startJudgeTime":17.12,"endJudgeTime":0.029,"xOffset":1,"speedGroup":0,"draginfolist":[]},{"isFakenote":false,"isSkynote":false,"skyjudgeNumber":0,"notetype":3,"startJudgeTime":16.847,"endJudgeTime":0.029,"xOffset":1,"speedGroup":0,"draginfolist":[]},{"isFakenote":false,"isSkynote":false,"skyjudgeNumber":0,"notetype":3,"startJudgeTime":17.211,"endJudgeTime":0.029,"xOffset":0,"speedGroup":0,"draginfolist":[]},{"isFakenote":false,"isSkynote":false,"skyjudgeNumber":0,"notetype":3,"startJudgeTime":17.211,"endJudgeTime":0.029,"xOffset":0.9803238,"speedGroup":0,"draginfolist":[]},{"isFakenote":false,"isSkynote":false,"skyjudgeNumber":0,"notetype":0,"startJudgeTime":17.484,"endJudgeTime":0.029,"xOffset":0,"speedGroup":0,"draginfolist":[]},{"isFakenote":false,"isSkynote":false,"skyjudgeNumber":0,"notetype":0,"startJudgeTime":17.484,"endJudgeTime":0.029,"xOffset":1,"speedGroup":0,"draginfolist":[]},{"isFakenote":false,"isSkynote":true,"skyjudgeNumber":3,"notetype":1,"startJudgeTime":18.029,"endJudgeTime":0.029,"xOffset":0,"speedGroup":0,"draginfolist":[]},{"isFakenote":false,"isSkynote":false,"skyjudgeNumber":0,"notetype":0,"startJudgeTime":18.574,"endJudgeTime":0.029,"xOffset":0,"speedGroup":0,"draginfolist":[]},{"isFakenote":false,"isSkynote":false,"skyjudgeNumber":0,"notetype":0,"startJudgeTime":18.574,"endJudgeTime":0.029,"xOffset":1,"speedGroup":0,"draginfolist":[]},{"isFakenote":false,"isSkynote":true,"skyjudgeNumber":4,"notetype":1,"startJudgeTime":19.12,"endJudgeTime":0.029,"xOffset":0,"speedGroup":0,"draginfolist":[]},{"isFakenote":false,"isSkynote":false,"skyjudgeNumber":0,"notetype":0,"startJudgeTime":19.665,"endJudgeTime":0.029,"xOffset":0,"speedGroup":0,"draginfolist":[]},{"isFakenote":false,"isSkynote":false,"skyjudgeNumber":0,"notetype":0,"startJudgeTime":19.665,"endJudgeTime":0.029,"xOffset":1,"speedGroup":0,"draginfolist":[]},{"isFakenote":false,"isSkynote":false,"skyjudgeNumber":0,"notetype":0,"startJudgeTime":20.756,"endJudgeTime":0.029,"xOffset":0,"speedGroup":0,"draginfolist":[]},{"isFakenote":false,"isSkynote":false,"skyjudgeNumber":0,"notetype":0,"startJudgeTime":20.756,"endJudgeTime":0.029,"xOffset":1,"speedGroup":0,"draginfolist":[]},{"isFakenote":false,"isSkynote":true,"skyjudgeNumber":3,"notetype":1,"startJudgeTime":20.211,"endJudgeTime":0.029,"xOffset":0,"speedGroup":0,"draginfolist":[]},{"isFakenote":false,"isSkynote":true,"skyjudgeNumber":4,"notetype":1,"startJudgeTime":21.302,"endJudgeTime":0.029,"xOffset":0,"speedGroup":0,"draginfolist":[]},{"isFakenote":false,"isSkynote":false,"skyjudgeNumber":0,"notetype":0,"startJudgeTime":21.847,"endJudgeTime":0.029,"xOffset":0,"speedGroup":0,"draginfolist":[]},{"isFakenote":false,"isSkynote":false,"skyjudgeNumber":0,"notetype":0,"startJudgeTime":21.847,"endJudgeTime":0.029,"xOffset":1,"speedGroup":0,"draginfolist":[]},{"isFakenote":false,"isSkynote":false,"skyjudgeNumber":0,"notetype":0,"startJudgeTime":22.938,"endJudgeTime":0.029,"xOffset":0,"speedGroup":0,"draginfolist":[]},{"isFakenote":false,"isSkynote":false,"skyjudgeNumber":0,"notetype":0,"startJudgeTime":22.938,"endJudgeTime":0.029,"xOffset":1,"speedGroup":0,"draginfolist":[]},{"isFakenote":false,"isSkynote":false,"skyjudgeNumber":0,"notetype":0,"startJudgeTime":24.029,"endJudgeTime":0.029,"xOffset":0,"speedGroup":0,"draginfolist":[]},{"isFakenote":false,"isSkynote":false,"skyjudgeNumber":0,"notetype":0,"startJudgeTime":24.029,"endJudgeTime":0.029,"xOffset":1,"speedGroup":0,"draginfolist":[]},{"isFakenote":false,"isSkynote":false,"skyjudgeNumber":0,"notetype":0,"startJudgeTime":25.12,"endJudgeTime":0.029,"xOffset":0,"speedGroup":0,"draginfolist":[]},{"isFakenote":false,"isSkynote":false,"skyjudgeNumber":0,"notetype":0,"startJudgeTime":25.12,"endJudgeTime":0.029,"xOffset":1,"speedGroup":0,"draginfolist":[]},{"isFakenote":false,"isSkynote":true,"skyjudgeNumber":1,"notetype":1,"startJudgeTime":22.393,"endJudgeTime":0.029,"xOffset":0,"speedGroup":0,"draginfolist":[]},{"isFakenote":false,"isSkynote":true,"skyjudgeNumber":2,"notetype":1,"startJudgeTime":23.484,"endJudgeTime":0.029,"xOffset":0,"speedGroup":0,"draginfolist":[]},{"isFakenote":false,"isSkynote":true,"skyjudgeNumber":1,"notetype":1,"startJudgeTime":24.574,"endJudgeTime":0.029,"xOffset":0,"speedGroup":0,"draginfolist":[]},{"isFakenote":false,"isSkynote":true,"skyjudgeNumber":2,"notetype":1,"startJudgeTime":25.665,"endJudgeTime":0.029,"xOffset":0,"speedGroup":0,"draginfolist":[]},{"isFakenote":false,"isSkynote":false,"skyjudgeNumber":0,"notetype":2,"startJudgeTime":26.211,"endJudgeTime":28.393,"xOffset":0,"speedGroup":0,"draginfolist":[]},{"isFakenote":false,"isSkynote":false,"skyjudgeNumber":0,"notetype":0,"startJudgeTime":26.756,"endJudgeTime":0.029,"xOffset":1,"speedGroup":0,"draginfolist":[]},{"isFakenote":false,"isSkynote":false,"skyjudgeNumber":0,"notetype":2,"startJudgeTime":28.393,"endJudgeTime":30.574,"xOffset":1,"speedGroup":0,"draginfolist":[]},{"isFakenote":false,"isSkynote":false,"skyjudgeNumber":0,"notetype":0,"startJudgeTime":28.938,"endJudgeTime":0.029,"xOffset":0,"speedGroup":0,"draginfolist":[]},{"isFakenote":false,"isSkynote":true,"skyjudgeNumber":1,"notetype":2,"startJudgeTime":30.574,"endJudgeTime":32.756,"xOffset":0,"speedGroup":0,"draginfolist":[]},{"isFakenote":false,"isSkynote":false,"skyjudgeNumber":0,"notetype":0,"startJudgeTime":31.12,"endJudgeTime":0.029,"xOffset":0,"speedGroup":0,"draginfolist":[]},{"isFakenote":false,"isSkynote":true,"skyjudgeNumber":4,"notetype":0,"startJudgeTime":31.665,"endJudgeTime":0.029,"xOffset":0,"speedGroup":0,"draginfolist":[]},{"isFakenote":false,"isSkynote":false,"skyjudgeNumber":0,"notetype":0,"startJudgeTime":32.074,"endJudgeTime":0.029,"xOffset":1,"speedGroup":0,"draginfolist":[]},{"isFakenote":false,"isSkynote":false,"skyjudgeNumber":0,"notetype":0,"startJudgeTime":32.484,"endJudgeTime":0.029,"xOffset":0.5,"speedGroup":0,"draginfolist":[]},{"isFakenote":false,"isSkynote":false,"skyjudgeNumber":0,"notetype":0,"startJudgeTime":27.302,"endJudgeTime":0.029,"xOffset":0.75,"speedGroup":0,"draginfolist":[]},{"isFakenote":false,"isSkynote":true,"skyjudgeNumber":2,"notetype":2,"startJudgeTime":32.756,"endJudgeTime":34.938,"xOffset":0,"speedGroup":0,"draginfolist":[]},{"isFakenote":false,"isSkynote":true,"skyjudgeNumber":1,"notetype":3,"startJudgeTime":5.484,"endJudgeTime":0.029,"xOffset":0,"speedGroup":0,"draginfolist":[]},{"isFakenote":false,"isSkynote":true,"skyjudgeNumber":2,"notetype":3,"startJudgeTime":7.665,"endJudgeTime":0.029,"xOffset":0,"speedGroup":0,"draginfolist":[]},{"isFakenote":false,"isSkynote":true,"skyjudgeNumber":3,"notetype":0,"startJudgeTime":33.302,"endJudgeTime":0.029,"xOffset":0,"speedGroup":0,"draginfolist":[]},{"isFakenote":false,"isSkynote":false,"skyjudgeNumber":0,"notetype":0,"startJudgeTime":33.847,"endJudgeTime":0.029,"xOffset":0.5,"speedGroup":0,"draginfolist":[]},{"isFakenote":false,"isSkynote":false,"skyjudgeNumber":0,"notetype":0,"startJudgeTime":34.393,"endJudgeTime":0.029,"xOffset":0,"speedGroup":0,"draginfolist":[]},{"isFakenote":false,"isSkynote":false,"skyjudgeNumber":0,"notetype":2,"startJudgeTime":34.938,"endJudgeTime":35.484,"xOffset":0,"speedGroup":0,"draginfolist":[]},{"isFakenote":false,"isSkynote":false,"skyjudgeNumber":0,"notetype":2,"startJudgeTime":35.484,"endJudgeTime":36.029,"xOffset":1,"speedGroup":0,"draginfolist":[]},{"isFakenote":false,"isSkynote":true,"skyjudgeNumber":3,"notetype":2,"startJudgeTime":36.029,"endJudgeTime":36.574,"xOffset":0,"speedGroup":0,"draginfolist":[]},{"isFakenote":false,"isSkynote":true,"skyjudgeNumber":4,"notetype":2,"startJudgeTime":36.574,"endJudgeTime":37.12,"xOffset":0,"speedGroup":0,"draginfolist":[]},{"isFakenote":false,"isSkynote":true,"skyjudgeNumber":1,"notetype":2,"startJudgeTime":37.12,"endJudgeTime":37.665,"xOffset":0,"speedGroup":0,"draginfolist":[]},{"isFakenote":false,"isSkynote":true,"skyjudgeNumber":2,"notetype":2,"startJudgeTime":37.665,"endJudgeTime":38.211,"xOffset":0,"speedGroup":0,"draginfolist":[]},{"isFakenote":false,"isSkynote":true,"skyjudgeNumber":3,"notetype":2,"startJudgeTime":38.211,"endJudgeTime":38.756,"xOffset":0,"speedGroup":0,"draginfolist":[]},{"isFakenote":false,"isSkynote":true,"skyjudgeNumber":4,"notetype":2,"startJudgeTime":38.756,"endJudgeTime":39.302,"xOffset":0,"speedGroup":0,"draginfolist":[]},{"isFakenote":false,"isSkynote":false,"skyjudgeNumber":0,"notetype":3,"startJudgeTime":35.211,"endJudgeTime":0.029,"xOffset":0.005685389,"speedGroup":0,"draginfolist":[]},{"isFakenote":false,"isSkynote":false,"skyjudgeNumber":0,"notetype":3,"startJudgeTime":35.756,"endJudgeTime":0.029,"xOffset":1,"speedGroup":0,"draginfolist":[]},{"isFakenote":false,"isSkynote":true,"skyjudgeNumber":3,"notetype":3,"startJudgeTime":36.302,"endJudgeTime":0.029,"xOffset":0,"speedGroup":0,"draginfolist":[]},{"isFakenote":false,"isSkynote":true,"skyjudgeNumber":4,"notetype":3,"startJudgeTime":36.847,"endJudgeTime":0.029,"xOffset":0,"speedGroup":0,"draginfolist":[]},{"isFakenote":false,"isSkynote":true,"skyjudgeNumber":1,"notetype":3,"startJudgeTime":37.393,"endJudgeTime":0.029,"xOffset":0,"speedGroup":0,"draginfolist":[]},{"isFakenote":false,"isSkynote":true,"skyjudgeNumber":2,"notetype":3,"startJudgeTime":37.938,"endJudgeTime":0.029,"xOffset":0,"speedGroup":0,"draginfolist":[]},{"isFakenote":false,"isSkynote":true,"skyjudgeNumber":3,"notetype":3,"startJudgeTime":38.484,"endJudgeTime":0.029,"xOffset":0,"speedGroup":0,"draginfolist":[]},{"isFakenote":false,"isSkynote":true,"skyjudgeNumber":4,"notetype":3,"startJudgeTime":39.029,"endJudgeTime":0.029,"xOffset":0,"speedGroup":0,"draginfolist":[]},{"isFakenote":false,"isSkynote":true,"skyjudgeNumber":3,"notetype":3,"startJudgeTime":42.574,"endJudgeTime":0.029,"xOffset":0,"speedGroup":0,"draginfolist":[]},{"isFakenote":false,"isSkynote":true,"skyjudgeNumber":3,"notetype":3,"startJudgeTime":42.711,"endJudgeTime":0.029,"xOffset":0,"speedGroup":0,"draginfolist":[]},{"isFakenote":false,"isSkynote":true,"skyjudgeNumber":3,"notetype":3,"startJudgeTime":42.847,"endJudgeTime":0.029,"xOffset":0,"speedGroup":0,"draginfolist":[]},{"isFakenote":false,"isSkynote":true,"skyjudgeNumber":3,"notetype":3,"startJudgeTime":42.984,"endJudgeTime":0.029,"xOffset":0,"speedGroup":0,"draginfolist":[]},{"isFakenote":false,"isSkynote":true,"skyjudgeNumber":4,"notetype":3,"startJudgeTime":43.12,"endJudgeTime":0.029,"xOffset":0,"speedGroup":0,"draginfolist":[]},{"isFakenote":false,"isSkynote":true,"skyjudgeNumber":4,"notetype":3,"startJudgeTime":43.256,"endJudgeTime":0.029,"xOffset":0,"speedGroup":0,"draginfolist":[]},{"isFakenote":false,"isSkynote":true,"skyjudgeNumber":4,"notetype":3,"startJudgeTime":43.393,"endJudgeTime":0.029,"xOffset":0,"speedGroup":0,"draginfolist":[]},{"isFakenote":false,"isSkynote":true,"skyjudgeNumber":4,"notetype":3,"startJudgeTime":43.529,"endJudgeTime":0.029,"xOffset":0,"speedGroup":0,"draginfolist":[]},{"isFakenote":false,"isSkynote":false,"skyjudgeNumber":0,"notetype":2,"startJudgeTime":39.302,"endJudgeTime":39.847,"xOffset":0,"speedGroup":0,"draginfolist":[]},{"isFakenote":false,"isSkynote":false,"skyjudgeNumber":0,"notetype":2,"startJudgeTime":39.847,"endJudgeTime":40.393,"xOffset":1,"speedGroup":0,"draginfolist":[]},{"isFakenote":false,"isSkynote":true,"skyjudgeNumber":3,"notetype":2,"startJudgeTime":40.393,"endJudgeTime":40.938,"xOffset":0,"speedGroup":0,"draginfolist":[]},{"isFakenote":false,"isSkynote":true,"skyjudgeNumber":4,"notetype":2,"startJudgeTime":40.938,"endJudgeTime":41.484,"xOffset":0,"speedGroup":0,"draginfolist":[]},{"isFakenote":false,"isSkynote":true,"skyjudgeNumber":1,"notetype":2,"startJudgeTime":41.484,"endJudgeTime":42.029,"xOffset":0,"speedGroup":0,"draginfolist":[]},{"isFakenote":false,"isSkynote":true,"skyjudgeNumber":2,"notetype":2,"startJudgeTime":42.029,"endJudgeTime":42.574,"xOffset":0,"speedGroup":0,"draginfolist":[]},{"isFakenote":false,"isSkynote":false,"skyjudgeNumber":0,"notetype":3,"startJudgeTime":39.438,"endJudgeTime":0.029,"xOffset":0.005685538,"speedGroup":0,"draginfolist":[]},{"isFakenote":false,"isSkynote":false,"skyjudgeNumber":0,"notetype":3,"startJudgeTime":39.574,"endJudgeTime":0.029,"xOffset":0.01236215,"speedGroup":0,"draginfolist":[]},{"isFakenote":false,"isSkynote":false,"skyjudgeNumber":0,"notetype":3,"startJudgeTime":39.711,"endJudgeTime":0.029,"xOffset":0.03238737,"speedGroup":0,"draginfolist":[]},{"isFakenote":false,"isSkynote":true,"skyjudgeNumber":4,"notetype":3,"startJudgeTime":38.893,"endJudgeTime":0.029,"xOffset":0,"speedGroup":0,"draginfolist":[]},{"isFakenote":false,"isSkynote":true,"skyjudgeNumber":4,"notetype":3,"startJudgeTime":39.165,"endJudgeTime":0.029,"xOffset":0,"speedGroup":0,"draginfolist":[]},{"isFakenote":false,"isSkynote":true,"skyjudgeNumber":3,"notetype":3,"startJudgeTime":38.62,"endJudgeTime":0.029,"xOffset":0,"speedGroup":0,"draginfolist":[]},{"isFakenote":false,"isSkynote":true,"skyjudgeNumber":3,"notetype":3,"startJudgeTime":38.347,"endJudgeTime":0.029,"xOffset":0,"speedGroup":0,"draginfolist":[]},{"isFakenote":false,"isSkynote":true,"skyjudgeNumber":2,"notetype":3,"startJudgeTime":38.074,"endJudgeTime":0.029,"xOffset":0,"speedGroup":0,"draginfolist":[]},{"isFakenote":false,"isSkynote":true,"skyjudgeNumber":2,"notetype":3,"startJudgeTime":37.802,"endJudgeTime":0.029,"xOffset":0,"speedGroup":0,"draginfolist":[]},{"isFakenote":false,"isSkynote":true,"skyjudgeNumber":1,"notetype":3,"startJudgeTime":37.529,"endJudgeTime":0.029,"xOffset":0,"speedGroup":0,"draginfolist":[]},{"isFakenote":false,"isSkynote":true,"skyjudgeNumber":1,"notetype":3,"startJudgeTime":37.256,"endJudgeTime":0.029,"xOffset":0,"speedGroup":0,"draginfolist":[]},{"isFakenote":false,"isSkynote":true,"skyjudgeNumber":4,"notetype":3,"startJudgeTime":36.984,"endJudgeTime":0.029,"xOffset":0,"speedGroup":0,"draginfolist":[]},{"isFakenote":false,"isSkynote":true,"skyjudgeNumber":4,"notetype":3,"startJudgeTime":36.711,"endJudgeTime":0.029,"xOffset":0,"speedGroup":0,"draginfolist":[]},{"isFakenote":false,"isSkynote":true,"skyjudgeNumber":3,"notetype":3,"startJudgeTime":36.165,"endJudgeTime":0.029,"xOffset":0,"speedGroup":0,"draginfolist":[]},{"isFakenote":false,"isSkynote":true,"skyjudgeNumber":3,"notetype":3,"startJudgeTime":36.438,"endJudgeTime":0.029,"xOffset":0,"speedGroup":0,"draginfolist":[]},{"isFakenote":false,"isSkynote":false,"skyjudgeNumber":0,"notetype":3,"startJudgeTime":35.893,"endJudgeTime":0.029,"xOffset":1,"speedGroup":0,"draginfolist":[]},{"isFakenote":false,"isSkynote":false,"skyjudgeNumber":0,"notetype":3,"startJudgeTime":35.62,"endJudgeTime":0.029,"xOffset":0.9870013,"speedGroup":0,"draginfolist":[]},{"isFakenote":false,"isSkynote":false,"skyjudgeNumber":0,"notetype":3,"startJudgeTime":35.347,"endJudgeTime":0.029,"xOffset":0,"speedGroup":0,"draginfolist":[]},{"isFakenote":false,"isSkynote":false,"skyjudgeNumber":0,"notetype":3,"startJudgeTime":35.074,"endJudgeTime":0.029,"xOffset":0,"speedGroup":0,"draginfolist":[]},{"isFakenote":false,"isSkynote":false,"skyjudgeNumber":0,"notetype":3,"startJudgeTime":39.984,"endJudgeTime":0.029,"xOffset":1,"speedGroup":0,"draginfolist":[]},{"isFakenote":false,"isSkynote":false,"skyjudgeNumber":0,"notetype":3,"startJudgeTime":40.12,"endJudgeTime":0.029,"xOffset":1,"speedGroup":0,"draginfolist":[]},{"isFakenote":false,"isSkynote":false,"skyjudgeNumber":0,"notetype":3,"startJudgeTime":40.256,"endJudgeTime":0.029,"xOffset":1,"speedGroup":0,"draginfolist":[]},{"isFakenote":false,"isSkynote":true,"skyjudgeNumber":3,"notetype":3,"startJudgeTime":40.529,"endJudgeTime":0.029,"xOffset":0,"speedGroup":0,"draginfolist":[]},{"isFakenote":false,"isSkynote":true,"skyjudgeNumber":3,"notetype":3,"startJudgeTime":40.665,"endJudgeTime":0.029,"xOffset":0,"speedGroup":0,"draginfolist":[]},{"isFakenote":false,"isSkynote":true,"skyjudgeNumber":3,"notetype":3,"startJudgeTime":40.802,"endJudgeTime":0.029,"xOffset":0,"speedGroup":0,"draginfolist":[]},{"isFakenote":false,"isSkynote":true,"skyjudgeNumber":4,"notetype":3,"startJudgeTime":41.074,"endJudgeTime":0.029,"xOffset":0,"speedGroup":0,"draginfolist":[]},{"isFakenote":false,"isSkynote":true,"skyjudgeNumber":4,"notetype":3,"startJudgeTime":41.211,"endJudgeTime":0.029,"xOffset":0,"speedGroup":0,"draginfolist":[]},{"isFakenote":false,"isSkynote":true,"skyjudgeNumber":4,"notetype":3,"startJudgeTime":41.347,"endJudgeTime":0.029,"xOffset":0,"speedGroup":0,"draginfolist":[]},{"isFakenote":false,"isSkynote":true,"skyjudgeNumber":1,"notetype":3,"startJudgeTime":41.62,"endJudgeTime":0.029,"xOffset":0,"speedGroup":0,"draginfolist":[]},{"isFakenote":false,"isSkynote":true,"skyjudgeNumber":1,"notetype":3,"startJudgeTime":41.756,"endJudgeTime":0.029,"xOffset":0,"speedGroup":0,"draginfolist":[]},{"isFakenote":false,"isSkynote":true,"skyjudgeNumber":1,"notetype":3,"startJudgeTime":41.893,"endJudgeTime":0.029,"xOffset":0,"speedGroup":0,"draginfolist":[]},{"isFakenote":false,"isSkynote":true,"skyjudgeNumber":2,"notetype":3,"startJudgeTime":42.165,"endJudgeTime":0.029,"xOffset":0,"speedGroup":0,"draginfolist":[]},{"isFakenote":false,"isSkynote":true,"skyjudgeNumber":2,"notetype":3,"startJudgeTime":42.302,"endJudgeTime":0.029,"xOffset":0,"speedGroup":0,"draginfolist":[]},{"isFakenote":false,"isSkynote":true,"skyjudgeNumber":2,"notetype":3,"startJudgeTime":42.438,"endJudgeTime":0.029,"xOffset":0,"speedGroup":0,"draginfolist":[]},{"isFakenote":false,"isSkynote":false,"skyjudgeNumber":0,"notetype":0,"startJudgeTime":29.484,"endJudgeTime":0.029,"xOffset":0.25,"speedGroup":0,"draginfolist":[]},{"isFakenote":false,"isSkynote":true,"skyjudgeNumber":3,"notetype":0,"startJudgeTime":30.029,"endJudgeTime":0.029,"xOffset":0,"speedGroup":0,"draginfolist":[]},{"isFakenote":false,"isSkynote":true,"skyjudgeNumber":4,"notetype":0,"startJudgeTime":27.847,"endJudgeTime":0.029,"xOffset":0,"speedGroup":0,"draginfolist":[]},{"isFakenote":false,"isSkynote":true,"skyjudgeNumber":4,"notetype":2,"startJudgeTime":96.029,"endJudgeTime":96.574,"xOffset":0,"speedGroup":0,"draginfolist":[]},{"isFakenote":false,"isSkynote":false,"skyjudgeNumber":0,"notetype":1,"startJudgeTime":96.574,"endJudgeTime":0.029,"xOffset":0.5,"speedGroup":0,"draginfolist":[]},{"isFakenote":false,"isSkynote":true,"skyjudgeNumber":3,"notetype":2,"startJudgeTime":97.12,"endJudgeTime":97.665,"xOffset":0,"speedGroup":0,"draginfolist":[]},{"isFakenote":false,"isSkynote":true,"skyjudgeNumber":2,"notetype":2,"startJudgeTime":98.211,"endJudgeTime":98.756,"xOffset":0,"speedGroup":0,"draginfolist":[]},{"isFakenote":false,"isSkynote":true,"skyjudgeNumber":1,"notetype":2,"startJudgeTime":99.302,"endJudgeTime":99.847,"xOffset":0,"speedGroup":0,"draginfolist":[]},{"isFakenote":false,"isSkynote":false,"skyjudgeNumber":0,"notetype":2,"startJudgeTime":100.393,"endJudgeTime":100.938,"xOffset":1,"speedGroup":0,"draginfolist":[]},{"isFakenote":false,"isSkynote":false,"skyjudgeNumber":0,"notetype":2,"startJudgeTime":101.484,"endJudgeTime":102.029,"xOffset":0,"speedGroup":0,"draginfolist":[]},{"isFakenote":false,"isSkynote":true,"skyjudgeNumber":4,"notetype":2,"startJudgeTime":102.574,"endJudgeTime":103.12,"xOffset":0,"speedGroup":0,"draginfolist":[]},{"isFakenote":false,"isSkynote":true,"skyjudgeNumber":3,"notetype":2,"startJudgeTime":102.574,"endJudgeTime":103.12,"xOffset":0,"speedGroup":0,"draginfolist":[]},{"isFakenote":false,"isSkynote":true,"skyjudgeNumber":3,"notetype":1,"startJudgeTime":103.12,"endJudgeTime":0.029,"xOffset":0,"speedGroup":0,"draginfolist":[]},{"isFakenote":false,"isSkynote":true,"skyjudgeNumber":4,"notetype":1,"startJudgeTime":103.12,"endJudgeTime":0.029,"xOffset":0,"speedGroup":0,"draginfolist":[]},{"isFakenote":false,"isSkynote":true,"skyjudgeNumber":4,"notetype":3,"startJudgeTime":48.029,"endJudgeTime":0.029,"xOffset":0,"speedGroup":0,"draginfolist":[{"isFakenote":false,"isSkynote":true,"skyjudgeNumber":4,"startJudgeTime":48.302,"xOffset":0,"speedGroup":0},{"isFakenote":false,"isSkynote":true,"skyjudgeNumber":4,"startJudgeTime":48.574,"xOffset":0,"speedGroup":0},{"isFakenote":false,"isSkynote":true,"skyjudgeNumber":4,"startJudgeTime":48.847,"xOffset":0,"speedGroup":0},{"isFakenote":false,"isSkynote":true,"skyjudgeNumber":2,"startJudgeTime":50.211,"xOffset":0,"speedGroup":0},{"isFakenote":false,"isSkynote":true,"skyjudgeNumber":4,"startJudgeTime":52.393,"xOffset":0,"speedGroup":0},{"isFakenote":false,"isSkynote":false,"skyjudgeNumber":0,"startJudgeTime":52.938,"xOffset":1,"speedGroup":0},{"isFakenote":false,"isSkynote":false,"skyjudgeNumber":0,"startJudgeTime":53.211,"xOffset":1,"speedGroup":0},{"isFakenote":false,"isSkynote":true,"skyjudgeNumber":4,"startJudgeTime":53.484,"xOffset":0,"speedGroup":0},{"isFakenote":false,"isSkynote":true,"skyjudgeNumber":4,"startJudgeTime":53.893,"xOffset":0,"speedGroup":0},{"isFakenote":false,"isSkynote":true,"skyjudgeNumber":4,"startJudgeTime":54.302,"xOffset":0,"speedGroup":0},{"isFakenote":false,"isSkynote":true,"skyjudgeNumber":2,"startJudgeTime":54.574,"xOffset":0,"speedGroup":0},{"isFakenote":false,"isSkynote":true,"skyjudgeNumber":4,"startJudgeTime":55.393,"xOffset":0,"speedGroup":0},{"isFakenote":false,"isSkynote":true,"skyjudgeNumber":2,"startJudgeTime":56.484,"xOffset":0,"speedGroup":0},{"isFakenote":false,"isSkynote":true,"skyjudgeNumber":4,"startJudgeTime":56.756,"xOffset":0,"speedGroup":0},{"isFakenote":false,"isSkynote":false,"skyjudgeNumber":0,"startJudgeTime":57.165,"xOffset":1,"speedGroup":0},{"isFakenote":false,"isSkynote":true,"skyjudgeNumber":4,"startJudgeTime":57.574,"xOffset":0,"speedGroup":0},{"isFakenote":false,"isSkynote":false,"skyjudgeNumber":0,"startJudgeTime":57.847,"xOffset":1,"speedGroup":0},{"isFakenote":false,"isSkynote":false,"skyjudgeNumber":0,"startJudgeTime":58.393,"xOffset":1,"speedGroup":0}]},{"isFakenote":false,"isSkynote":false,"skyjudgeNumber":0,"notetype":2,"startJudgeTime":58.938,"endJudgeTime":60.574,"xOffset":0,"speedGroup":0,"draginfolist":[]},{"isFakenote":false,"isSkynote":false,"skyjudgeNumber":0,"notetype":2,"startJudgeTime":58.938,"endJudgeTime":60.574,"xOffset":1,"speedGroup":0,"draginfolist":[]},{"isFakenote":true,"isSkynote":false,"skyjudgeNumber":0,"notetype":3,"startJudgeTime":58.938,"endJudgeTime":0.029,"xOffset":0,"speedGroup":0,"draginfolist":[{"isFakenote":false,"isSkynote":true,"skyjudgeNumber":1,"startJudgeTime":61.12,"xOffset":0,"speedGroup":0},{"isFakenote":false,"isSkynote":true,"skyjudgeNumber":3,"startJudgeTime":61.529,"xOffset":0,"speedGroup":0},{"isFakenote":false,"isSkynote":true,"skyjudgeNumber":3,"startJudgeTime":61.938,"xOffset":0,"speedGroup":0}]},{"isFakenote":true,"isSkynote":false,"skyjudgeNumber":0,"notetype":3,"startJudgeTime":58.938,"endJudgeTime":0.029,"xOffset":1,"speedGroup":0,"draginfolist":[{"isFakenote":false,"isSkynote":true,"skyjudgeNumber":2,"startJudgeTime":61.12,"xOffset":0,"speedGroup":0}]},{"isFakenote":false,"isSkynote":true,"skyjudgeNumber":4,"notetype":1,"startJudgeTime":61.665,"endJudgeTime":0.029,"xOffset":0,"speedGroup":0,"draginfolist":[]},{"isFakenote":false,"isSkynote":true,"skyjudgeNumber":4,"notetype":1,"startJudgeTime":66.029,"endJudgeTime":0.029,"xOffset":0,"speedGroup":0,"draginfolist":[]},{"isFakenote":false,"isSkynote":true,"skyjudgeNumber":3,"notetype":1,"startJudgeTime":67.12,"endJudgeTime":0.029,"xOffset":0,"speedGroup":0,"draginfolist":[]},{"isFakenote":false,"isSkynote":true,"skyjudgeNumber":4,"notetype":1,"startJudgeTime":70.393,"endJudgeTime":0.029,"xOffset":0,"speedGroup":0,"draginfolist":[]},{"isFakenote":false,"isSkynote":true,"skyjudgeNumber":4,"notetype":1,"startJudgeTime":74.756,"endJudgeTime":0.029,"xOffset":0,"speedGroup":0,"draginfolist":[]},{"isFakenote":false,"isSkynote":true,"skyjudgeNumber":3,"notetype":1,"startJudgeTime":75.847,"endJudgeTime":0.029,"xOffset":0,"speedGroup":0,"draginfolist":[]},{"isFakenote":false,"isSkynote":true,"skyjudgeNumber":3,"notetype":1,"startJudgeTime":63.847,"endJudgeTime":0.029,"xOffset":0,"speedGroup":0,"draginfolist":[]},{"isFakenote":false,"isSkynote":true,"skyjudgeNumber":2,"notetype":3,"startJudgeTime":63.029,"endJudgeTime":0.029,"xOffset":0,"speedGroup":0,"draginfolist":[{"isFakenote":false,"isSkynote":true,"skyjudgeNumber":2,"startJudgeTime":63.302,"xOffset":0,"speedGroup":0},{"isFakenote":false,"isSkynote":true,"skyjudgeNumber":4,"startJudgeTime":63.711,"xOffset":0,"speedGroup":0},{"isFakenote":false,"isSkynote":true,"skyjudgeNumber":4,"startJudgeTime":64.12,"xOffset":0,"speedGroup":0}]},{"isFakenote":false,"isSkynote":false,"skyjudgeNumber":0,"notetype":1,"startJudgeTime":62.756,"endJudgeTime":0.029,"xOffset":0,"speedGroup":0,"draginfolist":[]},{"isFakenote":false,"isSkynote":false,"skyjudgeNumber":0,"notetype":1,"startJudgeTime":64.938,"endJudgeTime":0.029,"xOffset":1,"speedGroup":0,"draginfolist":[]},{"isFakenote":false,"isSkynote":true,"skyjudgeNumber":3,"notetype":3,"startJudgeTime":65.211,"endJudgeTime":0.029,"xOffset":0,"speedGroup":0,"draginfolist":[{"isFakenote":false,"isSkynote":true,"skyjudgeNumber":3,"startJudgeTime":65.484,"xOffset":0,"speedGroup":0},{"isFakenote":false,"isSkynote":true,"skyjudgeNumber":1,"startJudgeTime":65.893,"xOffset":0,"speedGroup":0},{"isFakenote":false,"isSkynote":true,"skyjudgeNumber":1,"startJudgeTime":66.302,"xOffset":0,"speedGroup":0}]},{"isFakenote":false,"isSkynote":true,"skyjudgeNumber":2,"notetype":3,"startJudgeTime":66.574,"endJudgeTime":0.029,"xOffset":0,"speedGroup":0,"draginfolist":[{"isFakenote":false,"isSkynote":true,"skyjudgeNumber":2,"startJudgeTime":66.984,"xOffset":0,"speedGroup":0},{"isFakenote":false,"isSkynote":true,"skyjudgeNumber":4,"startJudgeTime":67.393,"xOffset":0,"speedGroup":0}]},{"isFakenote":false,"isSkynote":true,"skyjudgeNumber":4,"notetype":2,"startJudgeTime":67.665,"endJudgeTime":69.302,"xOffset":0,"speedGroup":0,"draginfolist":[]},{"isFakenote":false,"isSkynote":true,"skyjudgeNumber":3,"notetype":2,"startJudgeTime":67.665,"endJudgeTime":69.302,"xOffset":0,"speedGroup":0,"draginfolist":[]},{"isFakenote":false,"isSkynote":true,"skyjudgeNumber":1,"notetype":3,"startJudgeTime":69.847,"endJudgeTime":0.029,"xOffset":0,"speedGroup":0,"draginfolist":[{"isFakenote":false,"isSkynote":true,"skyjudgeNumber":1,"startJudgeTime":70.256,"xOffset":0,"speedGroup":0},{"isFakenote":false,"isSkynote":true,"skyjudgeNumber":3,"startJudgeTime":70.665,"xOffset":0,"speedGroup":0}]},{"isFakenote":false,"isSkynote":false,"skyjudgeNumber":0,"notetype":1,"startJudgeTime":71.484,"endJudgeTime":0.029,"xOffset":0,"speedGroup":0,"draginfolist":[]},{"isFakenote":false,"isSkynote":true,"skyjudgeNumber":4,"notetype":3,"startJudgeTime":71.756,"endJudgeTime":0.029,"xOffset":0,"speedGroup":0,"draginfolist":[{"isFakenote":false,"isSkynote":true,"skyjudgeNumber":4,"startJudgeTime":71.893,"xOffset":0,"speedGroup":0},{"isFakenote":false,"isSkynote":true,"skyjudgeNumber":4,"startJudgeTime":72.029,"xOffset":0,"speedGroup":0},{"isFakenote":false,"isSkynote":true,"skyjudgeNumber":2,"startJudgeTime":72.438,"xOffset":0,"speedGroup":0},{"isFakenote":false,"isSkynote":true,"skyjudgeNumber":2,"startJudgeTime":72.847,"xOffset":0,"speedGroup":0}]},{"isFakenote":false,"isSkynote":true,"skyjudgeNumber":3,"notetype":1,"startJudgeTime":72.574,"endJudgeTime":0.029,"xOffset":0,"speedGroup":0,"draginfolist":[]},{"isFakenote":false,"isSkynote":false,"skyjudgeNumber":0,"notetype":1,"startJudgeTime":73.665,"endJudgeTime":0.029,"xOffset":1,"speedGroup":0,"draginfolist":[]},{"isFakenote":false,"isSkynote":true,"skyjudgeNumber":1,"notetype":3,"startJudgeTime":73.938,"endJudgeTime":0.029,"xOffset":0,"speedGroup":0,"draginfolist":[{"isFakenote":false,"isSkynote":true,"skyjudgeNumber":1,"startJudgeTime":74.211,"xOffset":0,"speedGroup":0},{"isFakenote":false,"isSkynote":true,"skyjudgeNumber":3,"startJudgeTime":74.62,"xOffset":0,"speedGroup":0},{"isFakenote":false,"isSkynote":true,"skyjudgeNumber":1,"startJudgeTime":75.029,"xOffset":0,"speedGroup":0}]},{"isFakenote":false,"isSkynote":true,"skyjudgeNumber":2,"notetype":3,"startJudgeTime":75.302,"endJudgeTime":0.029,"xOffset":0,"speedGroup":0,"draginfolist":[{"isFakenote":false,"isSkynote":true,"skyjudgeNumber":4,"startJudgeTime":75.711,"xOffset":0,"speedGroup":0},{"isFakenote":false,"isSkynote":true,"skyjudgeNumber":2,"startJudgeTime":76.12,"xOffset":0,"speedGroup":0}]},{"isFakenote":false,"isSkynote":false,"skyjudgeNumber":0,"notetype":2,"startJudgeTime":76.393,"endJudgeTime":78.029,"xOffset":0,"speedGroup":0,"draginfolist":[]},{"isFakenote":false,"isSkynote":false,"skyjudgeNumber":0,"notetype":2,"startJudgeTime":76.393,"endJudgeTime":78.029,"xOffset":1,"speedGroup":0,"draginfolist":[]},{"isFakenote":false,"isSkynote":false,"skyjudgeNumber":0,"notetype":1,"startJudgeTime":97.665,"endJudgeTime":0.029,"xOffset":0.5,"speedGroup":0,"draginfolist":[]},{"isFakenote":false,"isSkynote":false,"skyjudgeNumber":0,"notetype":1,"startJudgeTime":98.756,"endJudgeTime":0.029,"xOffset":0.5,"speedGroup":0,"draginfolist":[]},{"isFakenote":false,"isSkynote":false,"skyjudgeNumber":0,"notetype":1,"startJudgeTime":99.847,"endJudgeTime":0.029,"xOffset":0.5,"speedGroup":0,"draginfolist":[]},{"isFakenote":false,"isSkynote":true,"skyjudgeNumber":3,"notetype":1,"startJudgeTime":100.938,"endJudgeTime":0.029,"xOffset":0,"speedGroup":0,"draginfolist":[]},{"isFakenote":false,"isSkynote":true,"skyjudgeNumber":4,"notetype":1,"startJudgeTime":102.029,"endJudgeTime":0.029,"xOffset":0,"speedGroup":0,"draginfolist":[]},{"isFakenote":false,"isSkynote":true,"skyjudgeNumber":3,"notetype":2,"startJudgeTime":103.665,"endJudgeTime":103.938,"xOffset":0,"speedGroup":0,"draginfolist":[]},{"isFakenote":false,"isSkynote":false,"skyjudgeNumber":0,"notetype":2,"startJudgeTime":103.665,"endJudgeTime":103.938,"xOffset":0,"speedGroup":0,"draginfolist":[]},{"isFakenote":false,"isSkynote":false,"skyjudgeNumber":0,"notetype":2,"startJudgeTime":104.211,"endJudgeTime":104.484,"xOffset":1,"speedGroup":0,"draginfolist":[]},{"isFakenote":false,"isSkynote":true,"skyjudgeNumber":4,"notetype":2,"startJudgeTime":104.211,"endJudgeTime":104.484,"xOffset":0,"speedGroup":0,"draginfolist":[]},{"isFakenote":false,"isSkynote":true,"skyjudgeNumber":3,"notetype":2,"startJudgeTime":165.847,"endJudgeTime":169.665,"xOffset":0,"speedGroup":0,"draginfolist":[]},{"isFakenote":false,"isSkynote":true,"skyjudgeNumber":4,"notetype":2,"startJudgeTime":165.847,"endJudgeTime":169.665,"xOffset":0,"speedGroup":0,"draginfolist":[]},{"isFakenote":true,"isSkynote":false,"skyjudgeNumber":0,"notetype":3,"startJudgeTime":76.393,"endJudgeTime":0.029,"xOffset":0,"speedGroup":0,"draginfolist":[{"isFakenote":false,"isSkynote":true,"skyjudgeNumber":1,"startJudgeTime":78.574,"xOffset":0,"speedGroup":0},{"isFakenote":false,"isSkynote":true,"skyjudgeNumber":1,"startJudgeTime":78.847,"xOffset":0,"speedGroup":0},{"isFakenote":false,"isSkynote":true,"skyjudgeNumber":1,"startJudgeTime":79.12,"xOffset":0,"speedGroup":0},{"isFakenote":false,"isSkynote":true,"skyjudgeNumber":3,"startJudgeTime":79.393,"xOffset":0,"speedGroup":0},{"isFakenote":false,"isSkynote":true,"skyjudgeNumber":1,"startJudgeTime":80.756,"xOffset":0,"speedGroup":0},{"isFakenote":false,"isSkynote":true,"skyjudgeNumber":3,"startJudgeTime":81.165,"xOffset":0,"speedGroup":0},{"isFakenote":false,"isSkynote":true,"skyjudgeNumber":1,"startJudgeTime":82.938,"xOffset":0,"speedGroup":0},{"isFakenote":false,"isSkynote":true,"skyjudgeNumber":1,"startJudgeTime":83.211,"xOffset":0,"speedGroup":0},{"isFakenote":false,"isSkynote":true,"skyjudgeNumber":1,"startJudgeTime":83.484,"xOffset":0,"speedGroup":0},{"isFakenote":false,"isSkynote":true,"skyjudgeNumber":3,"startJudgeTime":83.756,"xOffset":0,"speedGroup":0},{"isFakenote":false,"isSkynote":true,"skyjudgeNumber":1,"startJudgeTime":84.029,"xOffset":0,"speedGroup":0},{"isFakenote":false,"isSkynote":true,"skyjudgeNumber":3,"startJudgeTime":84.393,"xOffset":0,"speedGroup":0},{"isFakenote":false,"isSkynote":false,"skyjudgeNumber":0,"startJudgeTime":84.756,"xOffset":0,"speedGroup":0}]},{"isFakenote":true,"isSkynote":false,"skyjudgeNumber":0,"notetype":3,"startJudgeTime":76.393,"endJudgeTime":0.029,"xOffset":1,"speedGroup":0,"draginfolist":[{"isFakenote":false,"isSkynote":true,"skyjudgeNumber":2,"startJudgeTime":78.574,"xOffset":0,"speedGroup":0},{"isFakenote":false,"isSkynote":true,"skyjudgeNumber":4,"startJudgeTime":79.665,"xOffset":0,"speedGroup":0},{"isFakenote":false,"isSkynote":true,"skyjudgeNumber":4,"startJudgeTime":80.074,"xOffset":0,"speedGroup":0},{"isFakenote":false,"isSkynote":true,"skyjudgeNumber":2,"startJudgeTime":80.484,"xOffset":0,"speedGroup":0},{"isFakenote":false,"isSkynote":true,"skyjudgeNumber":2,"startJudgeTime":80.756,"xOffset":0,"speedGroup":0},{"isFakenote":false,"isSkynote":true,"skyjudgeNumber":4,"startJudgeTime":81.165,"xOffset":0,"speedGroup":0},{"isFakenote":false,"isSkynote":true,"skyjudgeNumber":2,"startJudgeTime":82.938,"xOffset":0,"speedGroup":0},{"isFakenote":false,"isSkynote":true,"skyjudgeNumber":2,"startJudgeTime":83.211,"xOffset":0,"speedGroup":0},{"isFakenote":false,"isSkynote":true,"skyjudgeNumber":2,"startJudgeTime":83.484,"xOffset":0,"speedGroup":0},{"isFakenote":false,"isSkynote":true,"skyjudgeNumber":4,"startJudgeTime":83.756,"xOffset":0,"speedGroup":0},{"isFakenote":false,"isSkynote":true,"skyjudgeNumber":2,"startJudgeTime":84.029,"xOffset":0,"speedGroup":0},{"isFakenote":false,"isSkynote":true,"skyjudgeNumber":4,"startJudgeTime":84.393,"xOffset":0,"speedGroup":0},{"isFakenote":false,"isSkynote":false,"skyjudgeNumber":0,"startJudgeTime":84.756,"xOffset":1,"speedGroup":0}]},{"isFakenote":false,"isSkynote":false,"skyjudgeNumber":0,"notetype":2,"startJudgeTime":85.12,"endJudgeTime":86.756,"xOffset":0,"speedGroup":0,"draginfolist":[]},{"isFakenote":false,"isSkynote":false,"skyjudgeNumber":0,"notetype":2,"startJudgeTime":85.12,"endJudgeTime":86.756,"xOffset":1,"speedGroup":0,"draginfolist":[]},{"isFakenote":false,"isSkynote":false,"skyjudgeNumber":0,"notetype":3,"startJudgeTime":86.211,"endJudgeTime":0.029,"xOffset":0,"speedGroup":0,"draginfolist":[]},{"isFakenote":false,"isSkynote":false,"skyjudgeNumber":0,"notetype":3,"startJudgeTime":86.756,"endJudgeTime":0.029,"xOffset":0,"speedGroup":0,"draginfolist":[{"isFakenote":false,"isSkynote":true,"skyjudgeNumber":3,"startJudgeTime":87.302,"xOffset":0,"speedGroup":0},{"isFakenote":false,"isSkynote":true,"skyjudgeNumber":1,"startJudgeTime":88.393,"xOffset":0,"speedGroup":0},{"isFakenote":false,"isSkynote":true,"skyjudgeNumber":3,"startJudgeTime":88.802,"xOffset":0,"speedGroup":0},{"isFakenote":false,"isSkynote":true,"skyjudgeNumber":3,"startJudgeTime":89.211,"xOffset":0,"speedGroup":0},{"isFakenote":false,"isSkynote":true,"skyjudgeNumber":3,"startJudgeTime":89.484,"xOffset":0,"speedGroup":0},{"isFakenote":false,"isSkynote":true,"skyjudgeNumber":1,"startJudgeTime":90.302,"xOffset":0,"speedGroup":0},{"isFakenote":false,"isSkynote":true,"skyjudgeNumber":3,"startJudgeTime":91.393,"xOffset":0,"speedGroup":0},{"isFakenote":false,"isSkynote":true,"skyjudgeNumber":1,"startJudgeTime":91.665,"xOffset":0,"speedGroup":0},{"isFakenote":false,"isSkynote":true,"skyjudgeNumber":3,"startJudgeTime":92.074,"xOffset":0,"speedGroup":0},{"isFakenote":false,"isSkynote":false,"skyjudgeNumber":0,"startJudgeTime":92.484,"xOffset":0,"speedGroup":0},{"isFakenote":false,"isSkynote":true,"skyjudgeNumber":3,"startJudgeTime":92.756,"xOffset":0,"speedGroup":0},{"isFakenote":false,"isSkynote":false,"skyjudgeNumber":0,"startJudgeTime":93.302,"xOffset":0,"speedGroup":0},{"isFakenote":false,"isSkynote":true,"skyjudgeNumber":3,"startJudgeTime":93.847,"xOffset":0,"speedGroup":0},{"isFakenote":true,"isSkynote":true,"skyjudgeNumber":1,"startJudgeTime":95.484,"xOffset":0,"speedGroup":0}]},{"isFakenote":false,"isSkynote":false,"skyjudgeNumber":0,"notetype":3,"startJudgeTime":86.211,"endJudgeTime":0.029,"xOffset":1,"speedGroup":0,"draginfolist":[]},{"isFakenote":false,"isSkynote":false,"skyjudgeNumber":0,"notetype":3,"startJudgeTime":86.756,"endJudgeTime":0.029,"xOffset":1,"speedGroup":0,"draginfolist":[{"isFakenote":false,"isSkynote":true,"skyjudgeNumber":4,"startJudgeTime":87.302,"xOffset":0,"speedGroup":0},{"isFakenote":false,"isSkynote":true,"skyjudgeNumber":2,"startJudgeTime":87.847,"xOffset":0,"speedGroup":0},{"isFakenote":false,"isSkynote":true,"skyjudgeNumber":2,"startJudgeTime":88.12,"xOffset":0,"speedGroup":0},{"isFakenote":false,"isSkynote":true,"skyjudgeNumber":4,"startJudgeTime":89.484,"xOffset":0,"speedGroup":0},{"isFakenote":false,"isSkynote":true,"skyjudgeNumber":2,"startJudgeTime":90.302,"xOffset":0,"speedGroup":0},{"isFakenote":false,"isSkynote":true,"skyjudgeNumber":4,"startJudgeTime":91.393,"xOffset":0,"speedGroup":0},{"isFakenote":false,"isSkynote":true,"skyjudgeNumber":2,"startJudgeTime":91.665,"xOffset":0,"speedGroup":0},{"isFakenote":false,"isSkynote":true,"skyjudgeNumber":4,"startJudgeTime":92.074,"xOffset":0,"speedGroup":0},{"isFakenote":false,"isSkynote":false,"skyjudgeNumber":0,"startJudgeTime":92.484,"xOffset":1,"speedGroup":0},{"isFakenote":false,"isSkynote":true,"skyjudgeNumber":4,"startJudgeTime":92.756,"xOffset":0,"speedGroup":0},{"isFakenote":false,"isSkynote":false,"skyjudgeNumber":0,"startJudgeTime":93.302,"xOffset":1,"speedGroup":0},{"isFakenote":false,"isSkynote":true,"skyjudgeNumber":4,"startJudgeTime":93.847,"xOffset":0,"speedGroup":0},{"isFakenote":true,"isSkynote":true,"skyjudgeNumber":2,"startJudgeTime":95.484,"xOffset":0,"speedGroup":0}]},{"isFakenote":false,"isSkynote":true,"skyjudgeNumber":4,"notetype":2,"startJudgeTime":148.393,"endJudgeTime":150.574,"xOffset":0,"speedGroup":0,"draginfolist":[]},{"isFakenote":false,"isSkynote":true,"skyjudgeNumber":3,"notetype":2,"startJudgeTime":150.574,"endJudgeTime":152.756,"xOffset":0,"speedGroup":0,"draginfolist":[]},{"isFakenote":false,"isSkynote":true,"skyjudgeNumber":2,"notetype":2,"startJudgeTime":152.756,"endJudgeTime":154.938,"xOffset":0,"speedGroup":0,"draginfolist":[]},{"isFakenote":false,"isSkynote":true,"skyjudgeNumber":1,"notetype":2,"startJudgeTime":154.938,"endJudgeTime":157.12,"xOffset":0,"speedGroup":0,"draginfolist":[]},{"isFakenote":false,"isSkynote":false,"skyjudgeNumber":0,"notetype":2,"startJudgeTime":157.12,"endJudgeTime":159.302,"xOffset":1,"speedGroup":0,"draginfolist":[]},{"isFakenote":false,"isSkynote":false,"skyjudgeNumber":0,"notetype":2,"startJudgeTime":159.302,"endJudgeTime":161.484,"xOffset":0,"speedGroup":0,"draginfolist":[]},{"isFakenote":false,"isSkynote":false,"skyjudgeNumber":0,"notetype":2,"startJudgeTime":164.756,"endJudgeTime":165.302,"xOffset":1,"speedGroup":0,"draginfolist":[]},{"isFakenote":false,"isSkynote":true,"skyjudgeNumber":4,"notetype":2,"startJudgeTime":161.484,"endJudgeTime":162.029,"xOffset":0,"speedGroup":0,"draginfolist":[]},{"isFakenote":false,"isSkynote":true,"skyjudgeNumber":3,"notetype":2,"startJudgeTime":163.665,"endJudgeTime":164.211,"xOffset":0,"speedGroup":0,"draginfolist":[]},{"isFakenote":false,"isSkynote":false,"skyjudgeNumber":0,"notetype":2,"startJudgeTime":162.574,"endJudgeTime":163.12,"xOffset":0,"speedGroup":0,"draginfolist":[]},{"isFakenote":false,"isSkynote":true,"skyjudgeNumber":4,"notetype":3,"startJudgeTime":150.302,"endJudgeTime":0.029,"xOffset":0,"speedGroup":0,"draginfolist":[]},{"isFakenote":false,"isSkynote":true,"skyjudgeNumber":3,"notetype":3,"startJudgeTime":151.12,"endJudgeTime":0.029,"xOffset":0,"speedGroup":0,"draginfolist":[]},{"isFakenote":false,"isSkynote":true,"skyjudgeNumber":2,"notetype":3,"startJudgeTime":153.847,"endJudgeTime":0.029,"xOffset":0,"speedGroup":0,"draginfolist":[]},{"isFakenote":false,"isSkynote":true,"skyjudgeNumber":1,"notetype":3,"startJudgeTime":156.029,"endJudgeTime":0.029,"xOffset":0,"speedGroup":0,"draginfolist":[]},{"isFakenote":false,"isSkynote":false,"skyjudgeNumber":0,"notetype":3,"startJudgeTime":157.665,"endJudgeTime":0.029,"xOffset":0.9402723,"speedGroup":0,"draginfolist":[]},{"isFakenote":false,"isSkynote":false,"skyjudgeNumber":0,"notetype":3,"startJudgeTime":158.211,"endJudgeTime":0.029,"xOffset":0.9669743,"speedGroup":0,"draginfolist":[]},{"isFakenote":false,"isSkynote":false,"skyjudgeNumber":0,"notetype":3,"startJudgeTime":158.484,"endJudgeTime":0.029,"xOffset":0.973649,"speedGroup":0,"draginfolist":[]},{"isFakenote":false,"isSkynote":false,"skyjudgeNumber":0,"notetype":3,"startJudgeTime":159.029,"endJudgeTime":0.029,"xOffset":0.9803241,"speedGroup":0,"draginfolist":[]},{"isFakenote":false,"isSkynote":false,"skyjudgeNumber":0,"notetype":3,"startJudgeTime":159.847,"endJudgeTime":0.029,"xOffset":0,"speedGroup":0,"draginfolist":[]},{"isFakenote":false,"isSkynote":true,"skyjudgeNumber":3,"notetype":0,"startJudgeTime":104.756,"endJudgeTime":0.029,"xOffset":0,"speedGroup":0,"draginfolist":[]},{"isFakenote":false,"isSkynote":true,"skyjudgeNumber":4,"notetype":1,"startJudgeTime":105.302,"endJudgeTime":0.029,"xOffset":0,"speedGroup":0,"draginfolist":[]},{"isFakenote":false,"isSkynote":true,"skyjudgeNumber":4,"notetype":0,"startJudgeTime":105.847,"endJudgeTime":0.029,"xOffset":0,"speedGroup":0,"draginfolist":[]},{"isFakenote":false,"isSkynote":true,"skyjudgeNumber":3,"notetype":1,"startJudgeTime":106.393,"endJudgeTime":0.029,"xOffset":0,"speedGroup":0,"draginfolist":[]},{"isFakenote":false,"isSkynote":true,"skyjudgeNumber":3,"notetype":0,"startJudgeTime":106.938,"endJudgeTime":0.029,"xOffset":0,"speedGroup":0,"draginfolist":[]},{"isFakenote":false,"isSkynote":false,"skyjudgeNumber":0,"notetype":1,"startJudgeTime":107.484,"endJudgeTime":0.029,"xOffset":0.5,"speedGroup":0,"draginfolist":[]},{"isFakenote":false,"isSkynote":true,"skyjudgeNumber":4,"notetype":0,"startJudgeTime":108.029,"endJudgeTime":0.029,"xOffset":0,"speedGroup":0,"draginfolist":[]},{"isFakenote":false,"isSkynote":false,"skyjudgeNumber":0,"notetype":1,"startJudgeTime":108.574,"endJudgeTime":0.029,"xOffset":0.5,"speedGroup":0,"draginfolist":[]},{"isFakenote":false,"isSkynote":true,"skyjudgeNumber":3,"notetype":0,"startJudgeTime":109.12,"endJudgeTime":0.029,"xOffset":0,"speedGroup":0,"draginfolist":[]},{"isFakenote":false,"isSkynote":true,"skyjudgeNumber":2,"notetype":1,"startJudgeTime":109.665,"endJudgeTime":0.029,"xOffset":0,"speedGroup":0,"draginfolist":[]},{"isFakenote":false,"isSkynote":true,"skyjudgeNumber":4,"notetype":0,"startJudgeTime":110.211,"endJudgeTime":0.029,"xOffset":0,"speedGroup":0,"draginfolist":[]},{"isFakenote":false,"isSkynote":true,"skyjudgeNumber":1,"notetype":1,"startJudgeTime":110.756,"endJudgeTime":0.029,"xOffset":0,"speedGroup":0,"draginfolist":[]},{"isFakenote":false,"isSkynote":true,"skyjudgeNumber":4,"notetype":1,"startJudgeTime":114.029,"endJudgeTime":0.029,"xOffset":0,"speedGroup":0,"draginfolist":[]},{"isFakenote":false,"isSkynote":false,"skyjudgeNumber":0,"notetype":2,"startJudgeTime":114.574,"endJudgeTime":115.12,"xOffset":1,"speedGroup":0,"draginfolist":[]},{"isFakenote":false,"isSkynote":true,"skyjudgeNumber":3,"notetype":1,"startJudgeTime":115.12,"endJudgeTime":0.029,"xOffset":0,"speedGroup":0,"draginfolist":[]},{"isFakenote":false,"isSkynote":false,"skyjudgeNumber":0,"notetype":2,"startJudgeTime":115.665,"endJudgeTime":116.211,"xOffset":0,"speedGroup":0,"draginfolist":[]},{"isFakenote":false,"isSkynote":true,"skyjudgeNumber":2,"notetype":1,"startJudgeTime":116.211,"endJudgeTime":0.029,"xOffset":0,"speedGroup":0,"draginfolist":[]},{"isFakenote":false,"isSkynote":true,"skyjudgeNumber":1,"notetype":1,"startJudgeTime":117.302,"endJudgeTime":0.029,"xOffset":0,"speedGroup":0,"draginfolist":[]},{"isFakenote":false,"isSkynote":false,"skyjudgeNumber":0,"notetype":2,"startJudgeTime":116.756,"endJudgeTime":117.302,"xOffset":1,"speedGroup":0,"draginfolist":[]},{"isFakenote":false,"isSkynote":false,"skyjudgeNumber":0,"notetype":2,"startJudgeTime":139.665,"endJudgeTime":139.938,"xOffset":1,"speedGroup":0,"draginfolist":[]},{"isFakenote":false,"isSkynote":false,"skyjudgeNumber":0,"notetype":2,"startJudgeTime":140.074,"endJudgeTime":140.347,"xOffset":1,"speedGroup":0,"draginfolist":[]},{"isFakenote":false,"isSkynote":false,"skyjudgeNumber":0,"notetype":2,"startJudgeTime":140.484,"endJudgeTime":140.62,"xOffset":1,"speedGroup":0,"draginfolist":[]},{"isFakenote":false,"isSkynote":false,"skyjudgeNumber":0,"notetype":3,"startJudgeTime":139.802,"endJudgeTime":0.029,"xOffset":1,"speedGroup":0,"draginfolist":[]},{"isFakenote":false,"isSkynote":false,"skyjudgeNumber":0,"notetype":3,"startJudgeTime":139.938,"endJudgeTime":0.029,"xOffset":1,"speedGroup":0,"draginfolist":[]},{"isFakenote":false,"isSkynote":false,"skyjudgeNumber":0,"notetype":3,"startJudgeTime":140.211,"endJudgeTime":0.029,"xOffset":1,"speedGroup":0,"draginfolist":[]},{"isFakenote":false,"isSkynote":false,"skyjudgeNumber":0,"notetype":3,"startJudgeTime":140.347,"endJudgeTime":0.029,"xOffset":1,"speedGroup":0,"draginfolist":[]},{"isFakenote":false,"isSkynote":false,"skyjudgeNumber":0,"notetype":3,"startJudgeTime":140.62,"endJudgeTime":0.029,"xOffset":1,"speedGroup":0,"draginfolist":[]},{"isFakenote":false,"isSkynote":true,"skyjudgeNumber":3,"notetype":0,"startJudgeTime":140.756,"endJudgeTime":0.029,"xOffset":0,"speedGroup":0,"draginfolist":[]},{"isFakenote":false,"isSkynote":false,"skyjudgeNumber":0,"notetype":0,"startJudgeTime":141.029,"endJudgeTime":0.029,"xOffset":0,"speedGroup":0,"draginfolist":[]},{"isFakenote":false,"isSkynote":true,"skyjudgeNumber":4,"notetype":0,"startJudgeTime":141.302,"endJudgeTime":0.029,"xOffset":0,"speedGroup":0,"draginfolist":[]},{"isFakenote":false,"isSkynote":false,"skyjudgeNumber":0,"notetype":0,"startJudgeTime":141.574,"endJudgeTime":0.029,"xOffset":1,"speedGroup":0,"draginfolist":[]},{"isFakenote":false,"isSkynote":false,"skyjudgeNumber":0,"notetype":2,"startJudgeTime":141.847,"endJudgeTime":142.12,"xOffset":0,"speedGroup":0,"draginfolist":[]},{"isFakenote":false,"isSkynote":false,"skyjudgeNumber":0,"notetype":2,"startJudgeTime":142.256,"endJudgeTime":142.529,"xOffset":0,"speedGroup":0,"draginfolist":[]},{"isFakenote":false,"isSkynote":false,"skyjudgeNumber":0,"notetype":2,"startJudgeTime":142.665,"endJudgeTime":142.802,"xOffset":0,"speedGroup":0,"draginfolist":[]},{"isFakenote":false,"isSkynote":false,"skyjudgeNumber":0,"notetype":3,"startJudgeTime":141.984,"endJudgeTime":0.029,"xOffset":0,"speedGroup":0,"draginfolist":[]},{"isFakenote":false,"isSkynote":false,"skyjudgeNumber":0,"notetype":3,"startJudgeTime":142.12,"endJudgeTime":0.029,"xOffset":0,"speedGroup":0,"draginfolist":[]},{"isFakenote":false,"isSkynote":false,"skyjudgeNumber":0,"notetype":3,"startJudgeTime":142.393,"endJudgeTime":0.029,"xOffset":0,"speedGroup":0,"draginfolist":[]},{"isFakenote":false,"isSkynote":false,"skyjudgeNumber":0,"notetype":3,"startJudgeTime":142.529,"endJudgeTime":0.029,"xOffset":0,"speedGroup":0,"draginfolist":[]},{"isFakenote":false,"isSkynote":false,"skyjudgeNumber":0,"notetype":3,"startJudgeTime":142.802,"endJudgeTime":0.029,"xOffset":0,"speedGroup":0,"draginfolist":[]},{"isFakenote":false,"isSkynote":true,"skyjudgeNumber":2,"notetype":2,"startJudgeTime":147.302,"endJudgeTime":147.574,"xOffset":0,"speedGroup":0,"draginfolist":[]},{"isFakenote":false,"isSkynote":true,"skyjudgeNumber":1,"notetype":2,"startJudgeTime":147.574,"endJudgeTime":147.847,"xOffset":0,"speedGroup":0,"draginfolist":[]},{"isFakenote":false,"isSkynote":false,"skyjudgeNumber":0,"notetype":2,"startJudgeTime":147.847,"endJudgeTime":148.12,"xOffset":1,"speedGroup":0,"draginfolist":[]},{"isFakenote":false,"isSkynote":false,"skyjudgeNumber":0,"notetype":2,"startJudgeTime":148.12,"endJudgeTime":148.393,"xOffset":0,"speedGroup":0,"draginfolist":[]},{"isFakenote":false,"isSkynote":true,"skyjudgeNumber":2,"notetype":3,"startJudgeTime":147.438,"endJudgeTime":0.029,"xOffset":0,"speedGroup":0,"draginfolist":[]},{"isFakenote":false,"isSkynote":true,"skyjudgeNumber":1,"notetype":3,"startJudgeTime":147.711,"endJudgeTime":0.029,"xOffset":0,"speedGroup":0,"draginfolist":[]},{"isFakenote":false,"isSkynote":false,"skyjudgeNumber":0,"notetype":3,"startJudgeTime":147.984,"endJudgeTime":0.029,"xOffset":1,"speedGroup":0,"draginfolist":[]},{"isFakenote":false,"isSkynote":false,"skyjudgeNumber":0,"notetype":3,"startJudgeTime":148.256,"endJudgeTime":0.029,"xOffset":0.0257121,"speedGroup":0,"draginfolist":[]},{"isFakenote":false,"isSkynote":true,"skyjudgeNumber":4,"notetype":0,"startJudgeTime":142.938,"endJudgeTime":0.029,"xOffset":0,"speedGroup":0,"draginfolist":[]},{"isFakenote":false,"isSkynote":true,"skyjudgeNumber":3,"notetype":0,"startJudgeTime":143.484,"endJudgeTime":0.029,"xOffset":0,"speedGroup":0,"draginfolist":[]},{"isFakenote":false,"isSkynote":false,"skyjudgeNumber":0,"notetype":0,"startJudgeTime":143.756,"endJudgeTime":0.029,"xOffset":0,"speedGroup":0,"draginfolist":[]},{"isFakenote":false,"isSkynote":false,"skyjudgeNumber":0,"notetype":0,"startJudgeTime":143.211,"endJudgeTime":0.029,"xOffset":1,"speedGroup":0,"draginfolist":[]},{"isFakenote":false,"isSkynote":true,"skyjudgeNumber":1,"notetype":0,"startJudgeTime":145.12,"endJudgeTime":0.029,"xOffset":0,"speedGroup":0,"draginfolist":[]},{"isFakenote":false,"isSkynote":false,"skyjudgeNumber":0,"notetype":0,"startJudgeTime":145.393,"endJudgeTime":0.029,"xOffset":0,"speedGroup":0,"draginfolist":[]},{"isFakenote":false,"isSkynote":true,"skyjudgeNumber":2,"notetype":0,"startJudgeTime":145.665,"endJudgeTime":0.029,"xOffset":0,"speedGroup":0,"draginfolist":[]},{"isFakenote":false,"isSkynote":false,"skyjudgeNumber":0,"notetype":0,"startJudgeTime":145.938,"endJudgeTime":0.029,"xOffset":1,"speedGroup":0,"draginfolist":[]},{"isFakenote":false,"isSkynote":false,"skyjudgeNumber":0,"notetype":2,"startJudgeTime":144.029,"endJudgeTime":144.302,"xOffset":1,"speedGroup":0,"draginfolist":[]},{"isFakenote":false,"isSkynote":false,"skyjudgeNumber":0,"notetype":2,"startJudgeTime":144.438,"endJudgeTime":144.711,"xOffset":1,"speedGroup":0,"draginfolist":[]},{"isFakenote":false,"isSkynote":false,"skyjudgeNumber":0,"notetype":2,"startJudgeTime":144.847,"endJudgeTime":144.984,"xOffset":1,"speedGroup":0,"draginfolist":[]},{"isFakenote":false,"isSkynote":false,"skyjudgeNumber":0,"notetype":3,"startJudgeTime":144.302,"endJudgeTime":0.029,"xOffset":0.987001,"speedGroup":0,"draginfolist":[]},{"isFakenote":false,"isSkynote":false,"skyjudgeNumber":0,"notetype":3,"startJudgeTime":144.574,"endJudgeTime":0.029,"xOffset":1,"speedGroup":0,"draginfolist":[]},{"isFakenote":false,"isSkynote":false,"skyjudgeNumber":0,"notetype":3,"startJudgeTime":144.711,"endJudgeTime":0.029,"xOffset":1,"speedGroup":0,"draginfolist":[]},{"isFakenote":false,"isSkynote":false,"skyjudgeNumber":0,"notetype":3,"startJudgeTime":144.984,"endJudgeTime":0.029,"xOffset":1,"speedGroup":0,"draginfolist":[]},{"isFakenote":false,"isSkynote":false,"skyjudgeNumber":0,"notetype":3,"startJudgeTime":144.165,"endJudgeTime":0.029,"xOffset":1,"speedGroup":0,"draginfolist":[]},{"isFakenote":false,"isSkynote":false,"skyjudgeNumber":0,"notetype":3,"startJudgeTime":146.756,"endJudgeTime":0.029,"xOffset":0,"speedGroup":0,"draginfolist":[]},{"isFakenote":false,"isSkynote":false,"skyjudgeNumber":0,"notetype":3,"startJudgeTime":146.347,"endJudgeTime":0.029,"xOffset":0,"speedGroup":0,"draginfolist":[]},{"isFakenote":false,"isSkynote":false,"skyjudgeNumber":0,"notetype":2,"startJudgeTime":146.211,"endJudgeTime":146.484,"xOffset":0,"speedGroup":0,"draginfolist":[]},{"isFakenote":false,"isSkynote":false,"skyjudgeNumber":0,"notetype":2,"startJudgeTime":146.62,"endJudgeTime":146.893,"xOffset":0,"speedGroup":0,"draginfolist":[]},{"isFakenote":false,"isSkynote":false,"skyjudgeNumber":0,"notetype":2,"startJudgeTime":147.029,"endJudgeTime":147.165,"xOffset":0,"speedGroup":0,"draginfolist":[]},{"isFakenote":false,"isSkynote":false,"skyjudgeNumber":0,"notetype":3,"startJudgeTime":147.165,"endJudgeTime":0.029,"xOffset":0,"speedGroup":0,"draginfolist":[]},{"isFakenote":false,"isSkynote":false,"skyjudgeNumber":0,"notetype":3,"startJudgeTime":146.893,"endJudgeTime":0.029,"xOffset":0,"speedGroup":0,"draginfolist":[]},{"isFakenote":false,"isSkynote":false,"skyjudgeNumber":0,"notetype":3,"startJudgeTime":146.484,"endJudgeTime":0.029,"xOffset":0,"speedGroup":0,"draginfolist":[]},{"isFakenote":false,"isSkynote":false,"skyjudgeNumber":0,"notetype":2,"startJudgeTime":117.847,"endJudgeTime":118.393,"xOffset":0,"speedGroup":0,"draginfolist":[]},{"isFakenote":false,"isSkynote":false,"skyjudgeNumber":0,"notetype":2,"startJudgeTime":118.938,"endJudgeTime":119.484,"xOffset":1,"speedGroup":0,"draginfolist":[]},{"isFakenote":false,"isSkynote":true,"skyjudgeNumber":4,"notetype":1,"startJudgeTime":118.393,"endJudgeTime":0.029,"xOffset":0,"speedGroup":0,"draginfolist":[]},{"isFakenote":false,"isSkynote":true,"skyjudgeNumber":3,"notetype":1,"startJudgeTime":119.484,"endJudgeTime":0.029,"xOffset":0,"speedGroup":0,"draginfolist":[]},{"isFakenote":false,"isSkynote":true,"skyjudgeNumber":4,"notetype":2,"startJudgeTime":122.211,"endJudgeTime":122.756,"xOffset":0,"speedGroup":0,"draginfolist":[]},{"isFakenote":false,"isSkynote":true,"skyjudgeNumber":3,"notetype":2,"startJudgeTime":123.302,"endJudgeTime":123.847,"xOffset":0,"speedGroup":0,"draginfolist":[]},{"isFakenote":false,"isSkynote":true,"skyjudgeNumber":4,"notetype":2,"startJudgeTime":124.393,"endJudgeTime":124.938,"xOffset":0,"speedGroup":0,"draginfolist":[]},{"isFakenote":false,"isSkynote":true,"skyjudgeNumber":3,"notetype":2,"startJudgeTime":125.484,"endJudgeTime":126.029,"xOffset":0,"speedGroup":0,"draginfolist":[]},{"isFakenote":false,"isSkynote":true,"skyjudgeNumber":4,"notetype":2,"startJudgeTime":126.574,"endJudgeTime":127.12,"xOffset":0,"speedGroup":0,"draginfolist":[]},{"isFakenote":false,"isSkynote":true,"skyjudgeNumber":3,"notetype":2,"startJudgeTime":127.665,"endJudgeTime":128.211,"xOffset":0,"speedGroup":0,"draginfolist":[]},{"isFakenote":false,"isSkynote":true,"skyjudgeNumber":3,"notetype":3,"startJudgeTime":138.165,"endJudgeTime":0.029,"xOffset":0,"speedGroup":0,"draginfolist":[]},{"isFakenote":false,"isSkynote":true,"skyjudgeNumber":3,"notetype":3,"startJudgeTime":138.302,"endJudgeTime":0.029,"xOffset":0,"speedGroup":0,"draginfolist":[]},{"isFakenote":false,"isSkynote":true,"skyjudgeNumber":3,"notetype":3,"startJudgeTime":138.438,"endJudgeTime":0.029,"xOffset":0,"speedGroup":0,"draginfolist":[]},{"isFakenote":false,"isSkynote":true,"skyjudgeNumber":2,"notetype":3,"startJudgeTime":138.711,"endJudgeTime":0.029,"xOffset":0,"speedGroup":0,"draginfolist":[]},{"isFakenote":false,"isSkynote":true,"skyjudgeNumber":2,"notetype":3,"startJudgeTime":138.847,"endJudgeTime":0.029,"xOffset":0,"speedGroup":0,"draginfolist":[]},{"isFakenote":false,"isSkynote":true,"skyjudgeNumber":1,"notetype":3,"startJudgeTime":139.256,"endJudgeTime":0.029,"xOffset":0,"speedGroup":0,"draginfolist":[]},{"isFakenote":false,"isSkynote":true,"skyjudgeNumber":1,"notetype":3,"startJudgeTime":139.393,"endJudgeTime":0.029,"xOffset":0,"speedGroup":0,"draginfolist":[]},{"isFakenote":false,"isSkynote":true,"skyjudgeNumber":1,"notetype":3,"startJudgeTime":139.529,"endJudgeTime":0.029,"xOffset":0,"speedGroup":0,"draginfolist":[]},{"isFakenote":false,"isSkynote":true,"skyjudgeNumber":4,"notetype":2,"startJudgeTime":137.484,"endJudgeTime":138.029,"xOffset":0,"speedGroup":0,"draginfolist":[]},{"isFakenote":false,"isSkynote":true,"skyjudgeNumber":3,"notetype":2,"startJudgeTime":138.029,"endJudgeTime":138.574,"xOffset":0,"speedGroup":0,"draginfolist":[]},{"isFakenote":false,"isSkynote":true,"skyjudgeNumber":2,"notetype":2,"startJudgeTime":138.574,"endJudgeTime":139.12,"xOffset":0,"speedGroup":0,"draginfolist":[]},{"isFakenote":false,"isSkynote":true,"skyjudgeNumber":1,"notetype":2,"startJudgeTime":139.12,"endJudgeTime":139.665,"xOffset":0,"speedGroup":0,"draginfolist":[]},{"isFakenote":false,"isSkynote":true,"skyjudgeNumber":2,"notetype":3,"startJudgeTime":138.984,"endJudgeTime":0.029,"xOffset":0,"speedGroup":0,"draginfolist":[]},{"isFakenote":false,"isSkynote":true,"skyjudgeNumber":4,"notetype":0,"startJudgeTime":104.756,"endJudgeTime":0.029,"xOffset":0,"speedGroup":0,"draginfolist":[]},{"isFakenote":false,"isSkynote":true,"skyjudgeNumber":3,"notetype":0,"startJudgeTime":105.847,"endJudgeTime":0.029,"xOffset":0,"speedGroup":0,"draginfolist":[]},{"isFakenote":false,"isSkynote":true,"skyjudgeNumber":4,"notetype":0,"startJudgeTime":106.938,"endJudgeTime":0.029,"xOffset":0,"speedGroup":0,"draginfolist":[]},{"isFakenote":false,"isSkynote":true,"skyjudgeNumber":3,"notetype":0,"startJudgeTime":108.029,"endJudgeTime":0.029,"xOffset":0,"speedGroup":0,"draginfolist":[]},{"isFakenote":false,"isSkynote":true,"skyjudgeNumber":4,"notetype":0,"startJudgeTime":109.12,"endJudgeTime":0.029,"xOffset":0,"speedGroup":0,"draginfolist":[]},{"isFakenote":false,"isSkynote":true,"skyjudgeNumber":3,"notetype":0,"startJudgeTime":110.211,"endJudgeTime":0.029,"xOffset":0,"speedGroup":0,"draginfolist":[]},{"isFakenote":false,"isSkynote":false,"skyjudgeNumber":0,"notetype":2,"startJudgeTime":113.484,"endJudgeTime":114.029,"xOffset":0,"speedGroup":0,"draginfolist":[]},{"isFakenote":false,"isSkynote":false,"skyjudgeNumber":0,"notetype":2,"startJudgeTime":130.938,"endJudgeTime":132.029,"xOffset":1,"speedGroup":0,"draginfolist":[]},{"isFakenote":false,"isSkynote":false,"skyjudgeNumber":0,"notetype":3,"startJudgeTime":131.62,"endJudgeTime":0.029,"xOffset":1,"speedGroup":0,"draginfolist":[]},{"isFakenote":false,"isSkynote":false,"skyjudgeNumber":0,"notetype":3,"startJudgeTime":131.756,"endJudgeTime":0.029,"xOffset":1,"speedGroup":0,"draginfolist":[]},{"isFakenote":false,"isSkynote":false,"skyjudgeNumber":0,"notetype":3,"startJudgeTime":131.893,"endJudgeTime":0.029,"xOffset":1,"speedGroup":0,"draginfolist":[]},{"isFakenote":false,"isSkynote":true,"skyjudgeNumber":3,"notetype":0,"startJudgeTime":132.029,"endJudgeTime":0.029,"xOffset":0,"speedGroup":0,"draginfolist":[]},{"isFakenote":false,"isSkynote":false,"skyjudgeNumber":0,"notetype":0,"startJudgeTime":132.302,"endJudgeTime":0.029,"xOffset":0.25,"speedGroup":0,"draginfolist":[]},{"isFakenote":false,"isSkynote":false,"skyjudgeNumber":0,"notetype":0,"startJudgeTime":132.574,"endJudgeTime":0.029,"xOffset":0.75,"speedGroup":0,"draginfolist":[]},{"isFakenote":false,"isSkynote":true,"skyjudgeNumber":4,"notetype":0,"startJudgeTime":132.847,"endJudgeTime":0.029,"xOffset":0,"speedGroup":0,"draginfolist":[]},{"isFakenote":false,"isSkynote":false,"skyjudgeNumber":0,"notetype":1,"startJudgeTime":131.484,"endJudgeTime":0.029,"xOffset":0,"speedGroup":0,"draginfolist":[]},{"isFakenote":false,"isSkynote":false,"skyjudgeNumber":0,"notetype":2,"startJudgeTime":133.12,"endJudgeTime":134.211,"xOffset":0,"speedGroup":0,"draginfolist":[]},{"isFakenote":false,"isSkynote":false,"skyjudgeNumber":0,"notetype":3,"startJudgeTime":133.256,"endJudgeTime":0.029,"xOffset":0,"speedGroup":0,"draginfolist":[]},{"isFakenote":false,"isSkynote":false,"skyjudgeNumber":0,"notetype":3,"startJudgeTime":133.393,"endJudgeTime":0.029,"xOffset":0,"speedGroup":0,"draginfolist":[]},{"isFakenote":false,"isSkynote":false,"skyjudgeNumber":0,"notetype":3,"startJudgeTime":133.529,"endJudgeTime":0.029,"xOffset":0,"speedGroup":0,"draginfolist":[]},{"isFakenote":false,"isSkynote":false,"skyjudgeNumber":0,"notetype":3,"startJudgeTime":133.665,"endJudgeTime":0.029,"xOffset":0,"speedGroup":0,"draginfolist":[]},{"isFakenote":false,"isSkynote":false,"skyjudgeNumber":0,"notetype":3,"startJudgeTime":133.802,"endJudgeTime":0.029,"xOffset":0,"speedGroup":0,"draginfolist":[]},{"isFakenote":false,"isSkynote":false,"skyjudgeNumber":0,"notetype":3,"startJudgeTime":133.938,"endJudgeTime":0.029,"xOffset":0,"speedGroup":0,"draginfolist":[]},{"isFakenote":false,"isSkynote":false,"skyjudgeNumber":0,"notetype":3,"startJudgeTime":134.074,"endJudgeTime":0.029,"xOffset":0,"speedGroup":0,"draginfolist":[]},{"isFakenote":false,"isSkynote":false,"skyjudgeNumber":0,"notetype":1,"startJudgeTime":133.665,"endJudgeTime":0.029,"xOffset":1,"speedGroup":0,"draginfolist":[]},{"isFakenote":false,"isSkynote":true,"skyjudgeNumber":4,"notetype":0,"startJudgeTime":134.211,"endJudgeTime":0.029,"xOffset":0,"speedGroup":0,"draginfolist":[]},{"isFakenote":false,"isSkynote":false,"skyjudgeNumber":0,"notetype":0,"startJudgeTime":134.484,"endJudgeTime":0.029,"xOffset":0.75,"speedGroup":0,"draginfolist":[]},{"isFakenote":false,"isSkynote":false,"skyjudgeNumber":0,"notetype":0,"startJudgeTime":134.756,"endJudgeTime":0.029,"xOffset":0.25,"speedGroup":0,"draginfolist":[]},{"isFakenote":false,"isSkynote":true,"skyjudgeNumber":3,"notetype":0,"startJudgeTime":135.029,"endJudgeTime":0.029,"xOffset":0,"speedGroup":0,"draginfolist":[]},{"isFakenote":false,"isSkynote":false,"skyjudgeNumber":0,"notetype":1,"startJudgeTime":135.847,"endJudgeTime":0.029,"xOffset":0.5,"speedGroup":0,"draginfolist":[]},{"isFakenote":false,"isSkynote":true,"skyjudgeNumber":4,"notetype":0,"startJudgeTime":136.393,"endJudgeTime":0.029,"xOffset":0,"speedGroup":0,"draginfolist":[]},{"isFakenote":false,"isSkynote":false,"skyjudgeNumber":0,"notetype":0,"startJudgeTime":136.665,"endJudgeTime":0.029,"xOffset":1,"speedGroup":0,"draginfolist":[]},{"isFakenote":false,"isSkynote":true,"skyjudgeNumber":3,"notetype":0,"startJudgeTime":136.938,"endJudgeTime":0.029,"xOffset":0,"speedGroup":0,"draginfolist":[]},{"isFakenote":false,"isSkynote":false,"skyjudgeNumber":0,"notetype":0,"startJudgeTime":137.211,"endJudgeTime":0.029,"xOffset":0,"speedGroup":0,"draginfolist":[]},{"isFakenote":false,"isSkynote":false,"skyjudgeNumber":0,"notetype":1,"startJudgeTime":124.938,"endJudgeTime":0.029,"xOffset":0,"speedGroup":0,"draginfolist":[]},{"isFakenote":false,"isSkynote":false,"skyjudgeNumber":0,"notetype":1,"startJudgeTime":123.847,"endJudgeTime":0.029,"xOffset":1,"speedGroup":0,"draginfolist":[]},{"isFakenote":false,"isSkynote":false,"skyjudgeNumber":0,"notetype":1,"startJudgeTime":122.756,"endJudgeTime":0.029,"xOffset":0,"speedGroup":0,"draginfolist":[]},{"isFakenote":false,"isSkynote":false,"skyjudgeNumber":0,"notetype":1,"startJudgeTime":126.029,"endJudgeTime":0.029,"xOffset":1,"speedGroup":0,"draginfolist":[]},{"isFakenote":false,"isSkynote":true,"skyjudgeNumber":1,"notetype":1,"startJudgeTime":127.12,"endJudgeTime":0.029,"xOffset":0,"speedGroup":0,"draginfolist":[]},{"isFakenote":false,"isSkynote":true,"skyjudgeNumber":2,"notetype":1,"startJudgeTime":128.211,"endJudgeTime":0.029,"xOffset":0,"speedGroup":0,"draginfolist":[]},{"isFakenote":false,"isSkynote":true,"skyjudgeNumber":2,"notetype":3,"startJudgeTime":111.302,"endJudgeTime":0.029,"xOffset":0,"speedGroup":0,"draginfolist":[{"isFakenote":false,"isSkynote":true,"skyjudgeNumber":4,"startJudgeTime":111.574,"xOffset":0,"speedGroup":0},{"isFakenote":false,"isSkynote":false,"skyjudgeNumber":0,"startJudgeTime":111.847,"xOffset":1,"speedGroup":0},{"isFakenote":false,"isSkynote":false,"skyjudgeNumber":0,"startJudgeTime":112.12,"xOffset":0.5,"speedGroup":0}]},{"isFakenote":false,"isSkynote":true,"skyjudgeNumber":1,"notetype":3,"startJudgeTime":112.393,"endJudgeTime":0.029,"xOffset":0,"speedGroup":0,"draginfolist":[{"isFakenote":false,"isSkynote":true,"skyjudgeNumber":3,"startJudgeTime":112.665,"xOffset":0,"speedGroup":0},{"isFakenote":false,"isSkynote":false,"skyjudgeNumber":0,"startJudgeTime":112.938,"xOffset":0,"speedGroup":0},{"isFakenote":false,"isSkynote":false,"skyjudgeNumber":0,"startJudgeTime":113.211,"xOffset":0.5,"speedGroup":0}]},{"isFakenote":false,"isSkynote":true,"skyjudgeNumber":2,"notetype":3,"startJudgeTime":120.029,"endJudgeTime":0.029,"xOffset":0,"speedGroup":0,"draginfolist":[{"isFakenote":false,"isSkynote":true,"skyjudgeNumber":4,"startJudgeTime":120.302,"xOffset":0,"speedGroup":0},{"isFakenote":false,"isSkynote":false,"skyjudgeNumber":0,"startJudgeTime":120.574,"xOffset":1,"speedGroup":0},{"isFakenote":false,"isSkynote":false,"skyjudgeNumber":0,"startJudgeTime":120.847,"xOffset":0.5,"speedGroup":0}]},{"isFakenote":false,"isSkynote":true,"skyjudgeNumber":1,"notetype":3,"startJudgeTime":121.12,"endJudgeTime":0.029,"xOffset":0,"speedGroup":0,"draginfolist":[{"isFakenote":false,"isSkynote":true,"skyjudgeNumber":3,"startJudgeTime":121.393,"xOffset":0,"speedGroup":0},{"isFakenote":false,"isSkynote":false,"skyjudgeNumber":0,"startJudgeTime":121.665,"xOffset":0,"speedGroup":0},{"isFakenote":false,"isSkynote":false,"skyjudgeNumber":0,"startJudgeTime":121.938,"xOffset":0.5,"speedGroup":0}]},{"isFakenote":false,"isSkynote":true,"skyjudgeNumber":2,"notetype":3,"startJudgeTime":128.756,"endJudgeTime":0.029,"xOffset":0,"speedGroup":0,"draginfolist":[{"isFakenote":false,"isSkynote":true,"skyjudgeNumber":4,"startJudgeTime":129.029,"xOffset":0,"speedGroup":0},{"isFakenote":false,"isSkynote":false,"skyjudgeNumber":0,"startJudgeTime":129.302,"xOffset":1,"speedGroup":0},{"isFakenote":false,"isSkynote":false,"skyjudgeNumber":0,"startJudgeTime":129.574,"xOffset":0.5,"speedGroup":0}]},{"isFakenote":false,"isSkynote":true,"skyjudgeNumber":1,"notetype":3,"startJudgeTime":129.847,"endJudgeTime":0.029,"xOffset":0,"speedGroup":0,"draginfolist":[{"isFakenote":false,"isSkynote":true,"skyjudgeNumber":3,"startJudgeTime":130.12,"xOffset":0,"speedGroup":0},{"isFakenote":false,"isSkynote":false,"skyjudgeNumber":0,"startJudgeTime":130.393,"xOffset":0,"speedGroup":0},{"isFakenote":false,"isSkynote":false,"skyjudgeNumber":0,"startJudgeTime":130.665,"xOffset":0.5,"speedGroup":0}]},{"isFakenote":false,"isSkynote":false,"skyjudgeNumber":0,"notetype":2,"startJudgeTime":135.302,"endJudgeTime":135.574,"xOffset":0,"speedGroup":0,"draginfolist":[]},{"isFakenote":false,"isSkynote":false,"skyjudgeNumber":0,"notetype":2,"startJudgeTime":135.302,"endJudgeTime":135.574,"xOffset":1,"speedGroup":0,"draginfolist":[]},{"isFakenote":false,"isSkynote":false,"skyjudgeNumber":0,"notetype":3,"startJudgeTime":135.574,"endJudgeTime":0.029,"xOffset":0,"speedGroup":0,"draginfolist":[]},{"isFakenote":false,"isSkynote":false,"skyjudgeNumber":0,"notetype":3,"startJudgeTime":135.574,"endJudgeTime":0.029,"xOffset":1,"speedGroup":0,"draginfolist":[]},{"isFakenote":false,"isSkynote":true,"skyjudgeNumber":4,"notetype":3,"startJudgeTime":148.938,"endJudgeTime":0.029,"xOffset":0,"speedGroup":0,"draginfolist":[]},{"isFakenote":false,"isSkynote":true,"skyjudgeNumber":4,"notetype":3,"startJudgeTime":149.484,"endJudgeTime":0.029,"xOffset":0,"speedGroup":0,"draginfolist":[]},{"isFakenote":false,"isSkynote":true,"skyjudgeNumber":4,"notetype":3,"startJudgeTime":149.756,"endJudgeTime":0.029,"xOffset":0,"speedGroup":0,"draginfolist":[]},{"isFakenote":false,"isSkynote":false,"skyjudgeNumber":0,"notetype":3,"startJudgeTime":131.074,"endJudgeTime":0.029,"xOffset":1,"speedGroup":0,"draginfolist":[]},{"isFakenote":false,"isSkynote":false,"skyjudgeNumber":0,"notetype":3,"startJudgeTime":131.211,"endJudgeTime":0.029,"xOffset":1,"speedGroup":0,"draginfolist":[]},{"isFakenote":false,"isSkynote":false,"skyjudgeNumber":0,"notetype":3,"startJudgeTime":131.347,"endJudgeTime":0.029,"xOffset":1,"speedGroup":0,"draginfolist":[]},{"isFakenote":false,"isSkynote":false,"skyjudgeNumber":0,"notetype":3,"startJudgeTime":131.484,"endJudgeTime":0.029,"xOffset":1,"speedGroup":0,"draginfolist":[]},{"isFakenote":false,"isSkynote":true,"skyjudgeNumber":4,"notetype":3,"startJudgeTime":137.62,"endJudgeTime":0.029,"xOffset":0,"speedGroup":0,"draginfolist":[]},{"isFakenote":false,"isSkynote":true,"skyjudgeNumber":4,"notetype":3,"startJudgeTime":137.756,"endJudgeTime":0.029,"xOffset":0,"speedGroup":0,"draginfolist":[]},{"isFakenote":false,"isSkynote":true,"skyjudgeNumber":4,"notetype":3,"startJudgeTime":137.893,"endJudgeTime":0.029,"xOffset":0,"speedGroup":0,"draginfolist":[]}],"speedGroupInGames":[{"speedGroupNumber":0,"time":[0.029,114514],"speed":[10,10]}]}